{"assets":[{"id":"el-640","layers":[{"ddd":0,"ind":1,"ty":4,"nm":"Layer 1","hd":false,"sr":1,"ks":{"a":{"a":0,"k":[67.47,10.66]},"o":{"a":0,"k":100},"p":{"a":0,"k":[67.47,10.66]},"r":{"a":0,"k":0},"s":{"a":0,"k":[100,100]},"sk":{"a":0,"k":0},"sa":{"a":0,"k":0}},"ao":0,"ip":0,"op":121,"st":0,"bm":0,"shapes":[{"ty":"gr","hd":false,"nm":"Path 1 Group","bm":0,"it":[{"ty":"sh","hd":false,"nm":"Path 1","d":1,"ks":{"a":0,"k":{"c":false,"i":[[0,0],[0,0],[0,0]],"o":[[0,0],[0,0],[0,0]],"v":[[129.5,5.5],[134.5,10.5],[129.5,15.5]]}}},{"ty":"st","hd":false,"bm":0,"c":{"a":0,"k":[0.243,0.247,0.271]},"lc":2,"lj":2,"ml":4,"o":{"a":0,"k":100},"w":{"a":0,"k":1.511}},{"ty":"tr","nm":"Transform","a":{"a":0,"k":[0,0]},"o":{"a":0,"k":100},"p":{"a":0,"k":[0,0]},"r":{"a":0,"k":0},"s":{"a":0,"k":[100,100]},"sk":{"a":0,"k":0},"sa":{"a":0,"k":0}}],"np":0},{"ty":"gr","hd":false,"nm":"Path 1 (25) Group","bm":0,"it":[{"ty":"sh","hd":false,"nm":"Path 1 (25)","d":1,"ks":{"a":0,"k":{"c":true,"i":[[0,0],[-2.776,-0.484],[0,0],[0.865,1.78],[2.212,-0.47],[0,0],[-0.008,2.036],[0,0],[0,0]],"o":[[0,2.043],[0,0],[-2.219,-0.461],[-0.871,1.765],[0,0],[2.732,-0.498],[0,0],[0,0],[0,0]],"v":[[7.28,5.878],[12.056,10.463],[11.323,11.825],[6.423,8.236],[1.523,11.826],[0.806,10.463],[5.552,5.878],[5.552,4.896],[7.28,4.896]]}}},{"ty":"sh","hd":false,"nm":"Path 1 (25)","d":1,"ks":{"a":0,"k":{"c":true,"i":[[0,0],[0,0],[0,0],[0,0]],"o":[[0,0],[0,0],[0,0],[0,0]],"v":[[0.44,15.619],[0.44,14.271],[12.54,14.271],[12.54,15.619]]}}},{"ty":"sh","hd":false,"nm":"Path 1 (25)","d":1,"ks":{"a":0,"k":{"c":true,"i":[[0,0],[0,0],[0,0],[0,0],[-0.564,0.059],[0,0],[2.314,-0.008],[0,0],[-0.527,0],[0,0],[0,0],[0,0]],"o":[[0,0],[0,0],[0,0],[0.594,-0.044],[0,0],[-2.688,0.41],[0,0],[0.476,0],[0,0],[0,0],[0,0],[0,0]],"v":[[21.166,5.058],[21.166,6.39],[19.98,6.39],[19.98,10.015],[21.724,9.861],[21.826,11.062],[13.799,11.532],[13.623,10.184],[15.132,10.176],[15.132,6.391],[13.975,6.391],[13.975,5.058]]}}},{"ty":"sh","hd":false,"nm":"Path 1 (25)","d":1,"ks":{"a":0,"k":{"c":true,"i":[[0,0],[0,0],[0,0],[0,0],[0,0],[0,0]],"o":[[0,0],[0,0],[0,0],[0,0],[0,0],[0,0]],"v":[[15.394,14.023],[15.394,12.704],[24.433,12.704],[24.433,17.304],[22.792,17.304],[22.792,14.023]]}}},{"ty":"sh","hd":false,"nm":"Path 1 (25)","d":1,"ks":{"a":0,"k":{"c":true,"i":[[0,0],[-0.579,0.021],[0,0],[0,0]],"o":[[0.571,-0.007],[0,0],[0,0],[0,0]],"v":[[16.698,10.148],[18.427,10.097],[18.427,6.39],[16.698,6.39]]}}},{"ty":"sh","hd":false,"nm":"Path 1 (25)","d":1,"ks":{"a":0,"k":{"c":true,"i":[[0,0],[0,0],[0,0],[0,0]],"o":[[0,0],[0,0],[0,0],[0,0]],"v":[[22.792,12.148],[22.792,4.062],[24.432,4.062],[24.432,12.148]]}}},{"ty":"sh","hd":false,"nm":"Path 1 (25)","d":1,"ks":{"a":0,"k":{"c":true,"i":[[0,0],[4.739,-2.439],[0,0],[-0.784,1.575],[0,0],[0,0],[0,0],[-0.045,0.669],[0,0],[0,0]],"o":[[-0.008,3.992],[0,0],[2.197,-1.135],[0,0],[0,0],[0,0],[0.184,-0.645],[0,0],[0,0],[0,0]],"v":[[33.134,5.365],[27.201,15.238],[26.308,13.993],[30.658,9.965],[26.601,10.345],[26.366,8.955],[31.164,8.661],[31.508,6.684],[27.055,6.684],[27.055,5.365]]}}},{"ty":"sh","hd":false,"nm":"Path 1 (25)","d":1,"ks":{"a":0,"k":{"c":true,"i":[[0,0],[0,0],[0,0],[0,0],[0,0],[0,0],[0,0],[0,0]],"o":[[0,0],[0,0],[0,0],[0,0],[0,0],[0,0],[0,0],[0,0]],"v":[[33.104,10.565],[33.104,9.232],[35.829,9.232],[35.829,4.062],[37.455,4.062],[37.455,17.304],[35.83,17.304],[35.83,10.565]]}}},{"ty":"sh","hd":false,"nm":"Path 1 (25)","d":1,"ks":{"a":0,"k":{"c":true,"i":[[0,0],[0,0],[0,0],[0,0]],"o":[[0,0],[0,0],[0,0],[0,0]],"v":[[53.92,4.076],[53.92,13.744],[52.28,13.744],[52.28,4.076]]}}},{"ty":"sh","hd":false,"nm":"Path 1 (25)","d":1,"ks":{"a":0,"k":{"c":true,"i":[[0,0],[0.007,1.904],[0,0],[0,0],[0,0],[-2.102,-0.703],[0,0],[0.586,1.355],[1.56,-0.564]],"o":[[2.146,-0.754],[0,0],[0,0],[0,0],[-0.007,1.845],[0,0],[-1.509,-0.528],[-0.585,1.45],[0,0]],"v":[[42.904,10.624],[46.142,6.098],[46.142,4.808],[47.826,4.808],[47.826,6.098],[51.005,10.39],[50.17,11.679],[46.998,8.742],[43.754,11.913]]}}},{"ty":"sh","hd":false,"nm":"Path 1 (25)","d":1,"ks":{"a":0,"k":{"c":true,"i":[[0,0],[0,0],[0,0],[0,0],[0,0],[0,0]],"o":[[0,0],[0,0],[0,0],[0,0],[0,0],[0,0]],"v":[[45.16,17.04],[45.16,12.821],[46.8,12.821],[46.8,15.721],[54.286,15.721],[54.286,17.04]]}}},{"ty":"sh","hd":false,"nm":"Path 1 (25)","d":1,"ks":{"a":0,"k":{"c":true,"i":[[0,0],[-2.08,-0.564],[0,0],[0.608,1.15],[1.582,-0.468],[0,0],[0,1.597],[0,0],[0,0],[0,0],[0,0],[0,0],[0,0],[0,0],[0,0],[0,0],[0,0]],"o":[[-0.007,1.45],[0,0],[-1.524,-0.418],[-0.58,1.297],[0,0],[2.073,-0.63],[0,0],[0,0],[0,0],[0,0],[0,0],[0,0],[0,0],[0,0],[0,0],[0,0],[0,0]],"v":[[60.615,6.889],[63.823,10.331],[63.062,11.591],[59.832,9.137],[56.572,11.927],[55.81,10.668],[58.99,6.888],[58.99,6.815],[56.22,6.815],[56.22,5.526],[58.99,5.526],[58.99,4.003],[60.63,4.003],[60.63,5.526],[63.384,5.526],[63.384,6.816],[60.615,6.816]]}}},{"ty":"sh","hd":false,"nm":"Path 1 (25)","d":1,"ks":{"a":0,"k":{"c":false,"i":[[0,0],[-2.783,0],[-0.007,-1.574],[2.798,0],[-0.015,1.574]],"o":[[-0.015,-1.575],[2.798,0],[-0.007,1.576],[-2.783,0],[0,0]],"v":[[57.964,14.799],[62.461,12.338],[66.987,14.798],[62.461,17.289],[57.964,14.799]]}}},{"ty":"sh","hd":false,"nm":"Path 1 (25)","d":1,"ks":{"a":0,"k":{"c":false,"i":[[0,0],[-1.838,0],[0,0.783],[1.875,0.007],[-0.007,-0.791]],"o":[[-0.007,0.784],[1.875,0],[0,-0.791],[-1.838,0.007],[0,0]],"v":[[59.575,14.799],[62.461,16.029],[65.361,14.799],[62.461,13.583],[59.575,14.799]]}}},{"ty":"sh","hd":false,"nm":"Path 1 (25)","d":1,"ks":{"a":0,"k":{"c":true,"i":[[0,0],[0,0],[0,0],[0,0],[0,0],[0,0],[0,0],[0,0]],"o":[[0,0],[0,0],[0,0],[0,0],[0,0],[0,0],[0,0],[0,0]],"v":[[62.988,9.013],[62.988,7.694],[65.318,7.694],[65.318,4.062],[66.943,4.062],[66.943,12.074],[65.317,12.074],[65.317,9.013]]}}},{"ty":"sh","hd":false,"nm":"Path 1 (25)","d":1,"ks":{"a":0,"k":{"c":true,"i":[[0,0],[0,0],[0,0],[0,0],[0,0],[0,0],[0,0],[0,0]],"o":[[0,0],[0,0],[0,0],[0,0],[0,0],[0,0],[0,0],[0,0]],"v":[[79.19,4.062],[79.19,9.335],[81.227,9.335],[81.227,10.683],[79.19,10.683],[79.19,17.303],[77.58,17.303],[77.58,4.063]]}}},{"ty":"sh","hd":false,"nm":"Path 1 (25)","d":1,"ks":{"a":0,"k":{"c":true,"i":[[0,0],[0,0],[0,0],[0,0],[0,0],[0,0],[0,0],[0,0]],"o":[[0,0],[0,0],[0,0],[0,0],[0,0],[0,0],[0,0],[0,0]],"v":[[68.746,7.402],[68.746,6.097],[71.881,6.097],[71.881,4.252],[73.507,4.252],[73.507,6.098],[76.554,6.098],[76.554,7.4]]}}},{"ty":"sh","hd":false,"nm":"Path 1 (25)","d":1,"ks":{"a":0,"k":{"c":false,"i":[[0,0],[-1.933,-0.008],[-0.007,-1.831],[1.905,0],[-0.014,1.824]],"o":[[-0.014,-1.831],[1.904,-0.008],[-0.007,1.824],[-1.933,0],[0,0]],"v":[[69.361,11.386],[72.701,8.266],[76.026,11.386],[72.701,14.491],[69.361,11.386]]}}},{"ty":"sh","hd":false,"nm":"Path 1 (25)","d":1,"ks":{"a":0,"k":{"c":false,"i":[[0,0],[-1.04,0.007],[-0.015,1.076],[1.018,0],[-0.007,-1.077]],"o":[[-0.007,1.076],[1.018,0.007],[-0.015,-1.077],[-1.04,0],[0,0]],"v":[[70.914,11.386],[72.701,13.144],[74.474,11.386],[72.701,9.599],[70.914,11.386]]}}},{"ty":"sh","hd":false,"nm":"Path 1 (25)","d":1,"ks":{"a":0,"k":{"c":true,"i":[[0,0],[0,0],[0,0],[0,0],[0,0],[0,0],[0,0],[0,0]],"o":[[0,0],[0,0],[0,0],[0,0],[0,0],[0,0],[0,0],[0,0]],"v":[[92.872,4.062],[92.872,17.318],[91.246,17.318],[91.246,10.272],[88.976,10.272],[88.976,8.94],[91.246,8.94],[91.246,4.062]]}}},{"ty":"sh","hd":false,"nm":"Path 1 (25)","d":1,"ks":{"a":0,"k":{"c":true,"i":[[0,0],[0,0],[0,0],[0,0],[0,0],[0,0],[-1.78,0.322],[0,0],[2.277,-0.007],[0,0],[0,0],[0,0],[0,0]],"o":[[0,0],[0,0],[0,0],[0,0],[0,0],[1.97,-0.008],[0,0],[-1.97,0.344],[0,0],[0,0],[0,0],[0,0],[0,0]],"v":[[82.222,6.537],[82.222,5.22],[88.214,5.22],[88.214,10.068],[83.878,10.068],[83.878,12.852],[89.21,12.456],[89.342,13.789],[83.322,14.214],[82.267,14.214],[82.267,8.749],[86.617,8.749],[86.617,6.537]]}}},{"ty":"sh","hd":false,"nm":"Path 1 (25)","d":1,"ks":{"a":0,"k":{"c":true,"i":[[0,0],[0,0],[0,0],[0,0],[0,0],[0,0],[0,0],[0,0]],"o":[[0,0],[0,0],[0,0],[0,0],[0,0],[0,0],[0,0],[0,0]],"v":[[108.678,4.062],[108.678,9.232],[110.641,9.232],[110.641,10.595],[108.678,10.595],[108.678,17.275],[107.052,17.275],[107.052,4.061]]}}},{"ty":"sh","hd":false,"nm":"Path 1 (25)","d":1,"ks":{"a":0,"k":{"c":true,"i":[[0,0],[-0.323,3.018],[0,0],[0,0],[0,0],[4.401,-2.168]],"o":[[3.223,-1.611],[0,0],[0,0],[0,0],[-0.008,3.89],[0,0]],"v":[[98.233,13.656],[103.522,6.786],[98.952,6.786],[98.952,5.438],[105.177,5.438],[99.157,14.916]]}}},{"ty":"sh","hd":false,"nm":"Path 1 (25)","d":1,"ks":{"a":0,"k":{"c":true,"i":[[0,0],[0,0],[0,0],[0,0]],"o":[[0,0],[0,0],[0,0],[0,0]],"v":[[122.33,4.062],[122.33,17.304],[120.689,17.304],[120.689,4.062]]}}},{"ty":"sh","hd":false,"nm":"Path 1 (25)","d":1,"ks":{"a":0,"k":{"c":true,"i":[[0,0],[-0.293,3.011],[0,0],[0,0],[0,0],[4.636,-2.205]],"o":[[3.472,-1.648],[0,0],[0,0],[0,0],[0,3.94],[0,0]],"v":[[111.358,13.656],[116.72,6.756],[112.032,6.756],[112.032,5.469],[118.375,5.469],[112.208,14.961]]}}},{"ty":"fl","hd":false,"bm":0,"c":{"a":0,"k":[0.243,0.247,0.271]},"r":1,"o":{"a":0,"k":100}},{"ty":"tr","nm":"Transform","a":{"a":0,"k":[0,0]},"o":{"a":0,"k":100},"p":{"a":0,"k":[0,0]},"r":{"a":0,"k":0},"s":{"a":0,"k":[100,100]},"sk":{"a":0,"k":0},"sa":{"a":0,"k":0}}],"np":0}]}]},{"id":"el-622","layers":[{"ddd":0,"ind":5,"ty":4,"nm":"Layer 1","hd":false,"sr":1,"ks":{"a":{"a":0,"k":[121.204,26.126]},"o":{"a":0,"k":100},"p":{"a":0,"k":[121.204,26.126]},"r":{"a":0,"k":0},"s":{"a":0,"k":[100,100]},"sk":{"a":0,"k":0},"sa":{"a":0,"k":0}},"ao":0,"ip":0,"op":121,"st":0,"bm":0,"shapes":[{"ty":"gr","hd":false,"nm":"Path 1 (5) Group","bm":0,"it":[{"ty":"sh","hd":false,"nm":"Path 1 (5)","d":1,"ks":{"a":0,"k":{"c":true,"i":[[0,0],[0,0],[0,0],[0,0],[0,0],[0,0]],"o":[[0,0],[0,0],[0,0],[0,0],[0,0],[0,0]],"v":[[16.586,38.549],[16.586,40.74],[2.793,40.74],[2.793,33.307],[5.543,33.307],[5.543,38.549]]}}},{"ty":"sh","hd":false,"nm":"Path 1 (5)","d":1,"ks":{"a":0,"k":{"c":true,"i":[[0,0],[0,0],[0,0],[0,0],[0,0],[0,0],[0,0],[0,0]],"o":[[0,0],[0,0],[0,0],[0,0],[0,0],[0,0],[0,0],[0,0]],"v":[[0.58,45.209],[0.58,42.975],[18.477,42.975],[18.477,45.209],[10.807,45.209],[10.807,51.977],[8.057,51.977],[8.057,45.209]]}}},{"ty":"sh","hd":false,"nm":"Path 1 (5)","d":1,"ks":{"a":0,"k":{"c":true,"i":[[0,0],[0,0],[0.495,-2.739],[0,0],[0,0],[0,0],[0,0],[0,0],[0,0],[0,0],[0,0],[0,0],[-0.012,1.686],[0,0],[0,0]],"o":[[0,0],[-0.01,1.826],[0,0],[0,0],[0,0],[0,0],[0,0],[0,0],[0,0],[0,0],[0,0],[0.506,-2.514],[0,0],[0,0],[0,0]],"v":[[35.342,33.565],[35.342,35.326],[34.837,41.879],[37.426,41.879],[37.426,44.092],[29.799,44.092],[29.799,51.998],[27.049,51.998],[27.049,44.092],[19.594,44.092],[19.594,41.879],[32.054,41.879],[32.614,35.756],[21.634,35.756],[21.634,33.565]]}}},{"ty":"sh","hd":false,"nm":"Path 1 (5)","d":1,"ks":{"a":0,"k":{"c":true,"i":[[0,0],[0,0],[0,0],[0,0],[0,0],[0,0],[0,0],[0,0]],"o":[[0,0],[0,0],[0,0],[0,0],[0,0],[0,0],[0,0],[0,0]],"v":[[56.805,39.838],[56.805,42.072],[54.033,42.072],[54.033,51.934],[51.283,51.934],[51.283,32.426],[54.033,32.426],[54.033,39.838]]}}},{"ty":"sh","hd":false,"nm":"Path 1 (5)","d":1,"ks":{"a":0,"k":{"c":true,"i":[[0,0],[0,0],[0,0],[0,0],[-2.64,0.526],[0,0],[2.879,0]],"o":[[0,0],[0,0],[0,0],[2.692,-0.039],[0,0],[-3.276,0.666],[0,0]],"v":[[39.23,47.164],[39.23,34.294],[41.958,34.294],[41.958,44.898],[49.972,44.048],[50.251,46.326],[40.927,47.164]]}}},{"ty":"fl","hd":false,"bm":0,"c":{"a":0,"k":[0.329,0.318,1]},"r":1,"o":{"a":0,"k":100}},{"ty":"tr","nm":"Transform","a":{"a":0,"k":[0,0]},"o":{"a":0,"k":100},"p":{"a":0,"k":[0,0]},"r":{"a":0,"k":0},"s":{"a":0,"k":[100,100]},"sk":{"a":0,"k":0},"sa":{"a":0,"k":0}}],"np":0},{"ty":"gr","hd":false,"nm":"Path 1 (57) Group","bm":0,"it":[{"ty":"sh","hd":false,"nm":"Path 1 (57)","d":1,"ks":{"a":0,"k":{"c":false,"i":[[0,0],[-0.022,-2.342],[4.275,0.01],[-0.011,2.309],[-4.242,0]],"o":[[4.275,0],[-0.021,2.31],[-4.243,0.01],[-0.011,-2.342],[0,0]],"v":[[9.389,12.607],[16.371,16.303],[9.389,19.977],[2.428,16.303],[9.388,12.607]]}}},{"ty":"sh","hd":false,"nm":"Path 1 (57)","d":1,"ks":{"a":0,"k":{"c":true,"i":[[0,0],[0,0],[0,0],[0,0],[0,0],[0,0],[0,0],[0,0]],"o":[[0,0],[0,0],[0,0],[0,0],[0,0],[0,0],[0,0],[0,0]],"v":[[0.623,11.361],[0.623,9.148],[7.283,9.148],[7.283,5.732],[9.99,5.732],[9.99,9.148],[18.37,9.148],[18.37,11.361]]}}},{"ty":"sh","hd":false,"nm":"Path 1 (57)","d":1,"ks":{"a":0,"k":{"c":true,"i":[[0,0],[0,0],[0,0],[0,0],[0.569,-2.009],[0,0],[-0.021,1.332]],"o":[[0,0],[0,0],[0,0],[0.01,1.557],[0,0],[0.44,-1.773],[0,0]],"v":[[2.621,3.455],[2.621,1.307],[16.264,1.307],[16.264,2.897],[15.705,8.139],[13.02,7.88],[13.535,3.454]]}}},{"ty":"sh","hd":false,"nm":"Path 1 (57)","d":1,"ks":{"a":0,"k":{"c":false,"i":[[0,0],[-2.697,0],[0,1.052],[2.696,-0.01],[-0.01,-1.085]],"o":[[-0.01,1.052],[2.697,0],[0,-1.085],[-2.697,-0.01],[0,0]],"v":[[5.156,16.303],[9.389,17.893],[13.643,16.303],[9.389,14.648],[5.156,16.303]]}}},{"ty":"sh","hd":false,"nm":"Path 1 (57)","d":1,"ks":{"a":0,"k":{"c":true,"i":[[0,0],[0,0],[0,0],[0,0],[0,0],[0,0],[0,0],[0,0],[0,0],[0,0],[0,0],[0,0]],"o":[[0,0],[0,0],[0,0],[0,0],[0,0],[0,0],[0,0],[0,0],[0,0],[0,0],[0,0],[0,0]],"v":[[37.469,11.297],[37.469,13.51],[33.279,13.51],[33.279,19.977],[30.486,19.977],[30.486,13.51],[26.49,13.51],[26.49,19.977],[23.676,19.977],[23.676,13.51],[19.572,13.51],[19.572,11.297]]}}},{"ty":"sh","hd":false,"nm":"Path 1 (57)","d":1,"ks":{"a":0,"k":{"c":false,"i":[[0,0],[-4.2,0.011],[0,-2.696],[4.2,0.011],[-0.01,2.632]],"o":[[-0.01,-2.697],[4.2,0.011],[0,2.632],[-4.2,0.01],[0,0]],"v":[[21.377,5.497],[28.467,1.07],[35.6,5.496],[28.467,9.793],[21.377,5.496]]}}},{"ty":"sh","hd":false,"nm":"Path 1 (57)","d":1,"ks":{"a":0,"k":{"c":false,"i":[[0,0],[-2.621,-0.011],[0,1.375],[2.642,0.01],[-0.01,-1.439]],"o":[[-0.01,1.374],[2.642,-0.011],[0,-1.44],[-2.621,0.01],[0,0]],"v":[[24.191,5.496],[28.467,7.644],[32.764,5.495],[28.467,3.261],[24.191,5.495]]}}},{"ty":"sh","hd":false,"nm":"Path 1 (57)","d":1,"ks":{"a":0,"k":{"c":true,"i":[[0,0],[0,0],[0,0],[0,0],[0,0],[0,0],[0,0],[0,0]],"o":[[0,0],[0,0],[0,0],[0,0],[0,0],[0,0],[0,0],[0,0]],"v":[[54.033,0.425],[54.033,8.073],[56.913,8.073],[56.913,10.329],[54.033,10.329],[54.033,19.976],[51.326,19.976],[51.326,0.426]]}}},{"ty":"sh","hd":false,"nm":"Path 1 (57)","d":1,"ks":{"a":0,"k":{"c":true,"i":[[0,0],[0,0],[0,0],[0,0],[0,0],[0,0],[0,0],[0,0]],"o":[[0,0],[0,0],[0,0],[0,0],[0,0],[0,0],[0,0],[0,0]],"v":[[38.5,5.539],[38.5,3.348],[42.926,3.348],[42.926,0.727],[45.676,0.727],[45.676,3.347],[49.994,3.347],[49.994,5.54]]}}},{"ty":"sh","hd":false,"nm":"Path 1 (57)","d":1,"ks":{"a":0,"k":{"c":false,"i":[[0,0],[-2.89,-0.011],[0,-2.729],[2.847,-0.011],[-0.011,2.728]],"o":[[-0.01,-2.729],[2.846,-0.011],[0,2.729],[-2.89,-0.01],[0,0]],"v":[[39.295,11.297],[44.301,6.635],[49.285,11.297],[44.301,15.959],[39.295,11.297]]}}},{"ty":"sh","hd":false,"nm":"Path 1 (57)","d":1,"ks":{"a":0,"k":{"c":false,"i":[[0,0],[-1.386,0.011],[0,1.515],[1.364,0.022],[0,-1.504]],"o":[[0,1.515],[1.364,0.01],[0,-1.504],[-1.386,0.022],[0,0]],"v":[[41.916,11.297],[44.301,13.703],[46.664,11.297],[44.301,8.847],[41.916,11.297]]}}},{"ty":"sh","hd":false,"nm":"Path 1 (57)","d":1,"ks":{"a":0,"k":{"c":true,"i":[[0,0],[0,0],[0.784,-4.146],[0,0],[-0.01,2.299],[0,0],[0,0]],"o":[[0,0],[-0.01,2.449],[0,0],[0.751,-3.695],[0,0],[0,0],[0,0]],"v":[[73.734,2.123],[73.734,3.971],[72.94,13.316],[70.19,13.037],[70.984,4.293],[59.47,4.293],[59.47,2.123]]}}},{"ty":"sh","hd":false,"nm":"Path 1 (57)","d":1,"ks":{"a":0,"k":{"c":true,"i":[[0,0],[0,0],[0,0],[0,0],[0,0],[0,0],[0,0],[0,0]],"o":[[0,0],[0,0],[0,0],[0,0],[0,0],[0,0],[0,0],[0,0]],"v":[[57.621,17.592],[57.621,15.357],[64.002,15.357],[64.002,8.633],[66.731,8.633],[66.731,15.357],[75.453,15.357],[75.453,17.592]]}}},{"ty":"sh","hd":false,"nm":"Path 1 (57)","d":1,"ks":{"a":0,"k":{"c":true,"i":[[0,0],[0,0],[0,0],[0,0]],"o":[[0,0],[0,0],[0,0],[0,0]],"v":[[98.076,0.447],[98.076,11.275],[95.326,11.275],[95.326,0.447]]}}},{"ty":"sh","hd":false,"nm":"Path 1 (57)","d":1,"ks":{"a":0,"k":{"c":true,"i":[[0,0],[0,2.417],[0,0],[0,0],[0,0],[-3.201,-0.881],[0,0],[0.892,1.75],[2.342,-0.709]],"o":[[3.265,-0.988],[0,0],[0,0],[0,0],[-0.021,2.32],[0,0],[-2.257,-0.666],[-0.891,1.89],[0,0]],"v":[[81.641,8.847],[86.346,3.004],[86.346,1.114],[89.203,1.114],[89.203,3.004],[93.801,8.504],[92.491,10.674],[87.785,6.904],[82.951,10.996]]}}},{"ty":"sh","hd":false,"nm":"Path 1 (57)","d":1,"ks":{"a":0,"k":{"c":true,"i":[[0,0],[0,0],[0,0],[0,0],[0,0],[0,0],[0,0],[0,0],[0,0],[0,0],[0,0],[0,0]],"o":[[0,0],[0,0],[0,0],[0,0],[0,0],[0,0],[0,0],[0,0],[0,0],[0,0],[0,0],[0,0]],"v":[[84.584,19.762],[84.584,17.57],[87.119,17.57],[87.119,14.326],[84.756,14.326],[84.756,12.156],[98.184,12.156],[98.184,14.326],[95.842,14.326],[95.842,17.57],[98.356,17.57],[98.356,19.762]]}}},{"ty":"sh","hd":false,"nm":"Path 1 (57)","d":1,"ks":{"a":0,"k":{"c":true,"i":[[0,0],[0,0],[0,0],[0,0]],"o":[[0,0],[0,0],[0,0],[0,0]],"v":[[89.826,17.57],[93.135,17.57],[93.135,14.326],[89.826,14.326]]}}},{"ty":"sh","hd":false,"nm":"Path 1 (57)","d":1,"ks":{"a":0,"k":{"c":true,"i":[[0,0],[0,0],[0,0],[0,0]],"o":[[0,0],[0,0],[0,0],[0,0]],"v":[[118.551,10.416],[118.551,12.607],[100.719,12.607],[100.719,10.416]]}}},{"ty":"sh","hd":false,"nm":"Path 1 (57)","d":1,"ks":{"a":0,"k":{"c":false,"i":[[0,0],[-4.308,-0.021],[-0.011,-2.492],[4.275,0],[0,2.503]],"o":[[0,-2.492],[4.275,-0.021],[-0.011,2.503],[-4.308,0],[0,0]],"v":[[102.502,5.023],[109.635,1.027],[116.746,5.023],[109.635,9.063],[102.502,5.023]]}}},{"ty":"sh","hd":false,"nm":"Path 1 (57)","d":1,"ks":{"a":0,"k":{"c":true,"i":[[0,0],[0,0],[0,0],[0,0],[0,0],[0,0]],"o":[[0,0],[0,0],[0,0],[0,0],[0,0],[0,0]],"v":[[102.867,19.633],[102.867,13.918],[105.617,13.918],[105.617,17.441],[116.531,17.441],[116.531,19.633]]}}},{"ty":"sh","hd":false,"nm":"Path 1 (57)","d":1,"ks":{"a":0,"k":{"c":false,"i":[[0,0],[-2.718,0],[0,1.214],[2.696,0.021],[-0.021,-1.181]],"o":[[-0.021,1.214],[2.696,0],[0,-1.181],[-2.718,0.021],[0,0]],"v":[[105.359,5.023],[109.635,6.85],[113.91,5.023],[109.635,3.176],[105.359,5.023]]}}},{"ty":"sh","hd":false,"nm":"Path 1 (57)","d":1,"ks":{"a":0,"k":{"c":true,"i":[[0,0],[0,0],[0,0],[0,0],[0,0],[0,0],[0,0],[0,0],[0,0],[4.297,-1.171],[0,0],[-0.386,2.686],[0,0],[0,0],[0,0],[0.097,-0.604],[0,0],[0,0]],"o":[[0,0],[0,0],[0,0],[0,0],[0,0],[0,0],[0,0],[0,0],[-1.225,3.094],[0,0],[4.49,-1.171],[0,0],[0,0],[0,0],[0.004,0.611],[0,0],[0,0],[0,0]],"v":[[141.281,0.447],[141.281,11.705],[138.553,11.705],[138.553,9.793],[134.148,9.793],[134.148,7.602],[138.553,7.602],[138.553,5.732],[134.353,5.732],[126.049,12.135],[124.975,9.965],[132.064,3.949],[126.027,3.949],[126.027,1.758],[135.051,1.758],[134.911,3.584],[138.553,3.584],[138.553,0.447]]}}},{"ty":"sh","hd":false,"nm":"Path 1 (57)","d":1,"ks":{"a":0,"k":{"c":false,"i":[[0,0],[-4.017,0.011],[-0.011,-2.418],[3.964,0],[-0.011,2.449]],"o":[[-0.011,-2.418],[3.964,0.011],[-0.011,2.449],[-4.017,0],[0,0]],"v":[[128.09,15.895],[134.771,11.941],[141.432,15.895],[134.771,19.891],[128.09,15.895]]}}},{"ty":"sh","hd":false,"nm":"Path 1 (57)","d":1,"ks":{"a":0,"k":{"c":false,"i":[[0,0],[-2.481,0],[-0.011,1.213],[2.428,-0.022],[0,-1.204]],"o":[[0,1.213],[2.428,0],[-0.011,-1.204],[-2.481,-0.022],[0,0]],"v":[[130.818,15.895],[134.771,17.721],[138.682,15.895],[134.771,14.09],[130.818,15.895]]}}},{"ty":"sh","hd":false,"nm":"Path 1 (57)","d":1,"ks":{"a":0,"k":{"c":true,"i":[[0,0],[0,0],[0,0],[0,0],[0,0],[0,0],[0,0],[0,0]],"o":[[0,0],[0,0],[0,0],[0,0],[0,0],[0,0],[0,0],[0,0]],"v":[[160.295,0.425],[160.295,12.242],[157.566,12.242],[157.566,8.396],[155.031,8.396],[155.031,6.162],[157.566,6.162],[157.566,0.426]]}}},{"ty":"sh","hd":false,"nm":"Path 1 (57)","d":1,"ks":{"a":0,"k":{"c":true,"i":[[0,0],[0,0],[0,0],[0,0],[0,0],[0,0],[0,0],[0,0]],"o":[[0,0],[0,0],[0,0],[0,0],[0,0],[0,0],[0,0],[0,0]],"v":[[143.859,4.315],[143.859,2.122],[148.285,2.122],[148.285,0.253],[150.992,0.253],[150.992,2.123],[155.375,2.123],[155.375,4.314]]}}},{"ty":"sh","hd":false,"nm":"Path 1 (57)","d":1,"ks":{"a":0,"k":{"c":false,"i":[[0,0],[-2.74,0],[0,-2.042],[2.739,-0.011],[0,2.138]],"o":[[0,-2.041],[2.75,0],[0,2.138],[-2.74,-0.01],[0,0]],"v":[[144.934,8.461],[149.639,4.959],[154.322,8.461],[149.639,12.006],[144.934,8.461]]}}},{"ty":"sh","hd":false,"nm":"Path 1 (57)","d":1,"ks":{"a":0,"k":{"c":true,"i":[[0,0],[0,0],[0,0],[0,0]],"o":[[0,0],[0,0],[0,0],[0,0]],"v":[[147.146,19.761],[147.146,13.081],[160.295,13.081],[160.295,19.761]]}}},{"ty":"sh","hd":false,"nm":"Path 1 (57)","d":1,"ks":{"a":0,"k":{"c":false,"i":[[0,0],[-1.279,-0.01],[0,0.988],[1.246,-0.01],[-0.021,-0.924]],"o":[[-0.021,0.988],[1.246,-0.01],[0,-0.924],[-1.279,-0.01],[0,0]],"v":[[147.576,8.461],[149.639,9.986],[151.701,8.461],[149.639,7.021],[147.576,8.461]]}}},{"ty":"sh","hd":false,"nm":"Path 1 (57)","d":1,"ks":{"a":0,"k":{"c":true,"i":[[0,0],[0,0],[0,0],[0,0]],"o":[[0,0],[0,0],[0,0],[0,0]],"v":[[149.896,17.571],[157.609,17.571],[157.609,15.228],[149.896,15.228]]}}},{"ty":"sh","hd":false,"nm":"Path 1 (57)","d":1,"ks":{"a":0,"k":{"c":true,"i":[[0,0],[0,0],[0,0],[0,0]],"o":[[0,0],[0,0],[0,0],[0,0]],"v":[[172.799,2.037],[172.799,11.426],[163.41,11.426],[163.41,2.037]]}}},{"ty":"sh","hd":false,"nm":"Path 1 (57)","d":1,"ks":{"a":0,"k":{"c":true,"i":[[0,0],[0,0],[0,0],[0,0],[0,0],[0,0]],"o":[[0,0],[0,0],[0,0],[0,0],[0,0],[0,0]],"v":[[165.666,19.633],[165.666,13.295],[168.395,13.295],[168.395,17.441],[179.051,17.441],[179.051,19.633]]}}},{"ty":"sh","hd":false,"nm":"Path 1 (57)","d":1,"ks":{"a":0,"k":{"c":true,"i":[[0,0],[0,0],[0,0],[0,0]],"o":[[0,0],[0,0],[0,0],[0,0]],"v":[[166.117,9.277],[170.092,9.277],[170.092,4.23],[166.117,4.23]]}}},{"ty":"sh","hd":false,"nm":"Path 1 (57)","d":1,"ks":{"a":0,"k":{"c":true,"i":[[0,0],[0,0],[0,0],[0,0],[0,0],[0,0],[0,0],[0,0]],"o":[[0,0],[0,0],[0,0],[0,0],[0,0],[0,0],[0,0],[0,0]],"v":[[175.592,14.691],[175.592,0.426],[178.342,0.426],[178.342,6.055],[180.984,6.055],[180.984,8.31],[178.342,8.31],[178.342,14.69]]}}},{"ty":"sh","hd":false,"nm":"Path 1 (57)","d":1,"ks":{"a":0,"k":{"c":true,"i":[[0,0],[-1.58,-1.075],[0,1.45],[0,0],[0,0],[0,0],[-2.61,-0.806],[0,0],[0.677,1.514],[1.751,-0.687],[0.633,1.504],[1.783,-0.633],[0,0],[-0.01,1.901],[0,0],[0,0]],"o":[[0,1.568],[1.622,-1.15],[0,0],[0,0],[0,0],[-0.022,2.04],[0,0],[-1.869,-0.633],[-0.645,1.514],[-1.837,-0.666],[-0.699,1.45],[0,0],[2.567,-0.88],[0,0],[0,0],[0,0]],"v":[[194.025,12.973],[196.271,17.248],[198.602,12.973],[198.602,12.307],[201.309,12.307],[201.309,12.973],[204.982,17.699],[203.65,19.697],[199.88,16.357],[196.346,19.869],[192.726,16.432],[189.041,19.697],[187.688,17.699],[191.361,12.973],[191.361,12.307],[194.025,12.307]]}}},{"ty":"sh","hd":false,"nm":"Path 1 (57)","d":1,"ks":{"a":0,"k":{"c":false,"i":[[0,0],[-3.05,0],[-0.011,-2.772],[3.04,0.01],[0,2.717]],"o":[[0,-2.772],[3.04,0],[-0.011,2.717],[-3.05,0.01],[0,0]],"v":[[187.215,6.141],[192.564,1.436],[197.914,6.141],[192.564,10.803],[187.215,6.141]]}}},{"ty":"sh","hd":false,"nm":"Path 1 (57)","d":1,"ks":{"a":0,"k":{"c":false,"i":[[0,0],[-1.568,0.011],[-0.011,1.471],[1.526,0],[-0.021,-1.515]],"o":[[-0.021,1.471],[1.526,0.011],[-0.011,-1.515],[-1.568,0],[0,0]],"v":[[189.9,6.141],[192.564,8.525],[195.207,6.141],[192.564,3.734],[189.9,6.141]]}}},{"ty":"sh","hd":false,"nm":"Path 1 (57)","d":1,"ks":{"a":0,"k":{"c":true,"i":[[0,0],[0,0],[0,0],[0,0]],"o":[[0,0],[0,0],[0,0],[0,0]],"v":[[200.535,11.491],[200.535,0.446],[203.285,0.446],[203.285,11.49]]}}},{"ty":"sh","hd":false,"nm":"Path 1 (57)","d":1,"ks":{"a":0,"k":{"c":true,"i":[[0,0],[0,0],[0,0],[0,0],[0,0],[0,0],[0,0],[0,0]],"o":[[0,0],[0,0],[0,0],[0,0],[0,0],[0,0],[0,0],[0,0]],"v":[[221.354,0.425],[221.354,7.687],[224.232,7.687],[224.232,9.921],[221.354,9.921],[221.354,20.02],[218.604,20.02],[218.604,0.425]]}}},{"ty":"sh","hd":false,"nm":"Path 1 (57)","d":1,"ks":{"a":0,"k":{"c":true,"i":[[0,0],[0,0],[0,0],[0,0],[0,0],[0,0],[-2.6,0.451],[0,0],[3.449,0.011]],"o":[[0,0],[0,0],[0,0],[0,0],[0,0],[2.836,-0.022],[0,0],[-3.04,0.516],[0,0]],"v":[[206.701,15.271],[206.701,2.23],[215.875,2.23],[215.875,4.443],[209.43,4.443],[209.43,13.016],[217.207,12.393],[217.508,14.691],[208.355,15.271]]}}},{"ty":"sh","hd":false,"nm":"Path 1 (57)","d":1,"ks":{"a":0,"k":{"c":true,"i":[[0,0],[0,0],[0,0],[0,0],[0,0],[0,0],[0,0],[0,0],[0,0],[0,0],[0,0],[0,0]],"o":[[0,0],[0,0],[0,0],[0,0],[0,0],[0,0],[0,0],[0,0],[0,0],[0,0],[0,0],[0,0]],"v":[[235.039,2.015],[235.039,3.497],[238.691,3.497],[238.691,0.448],[241.42,0.448],[241.42,14.67],[238.691,14.67],[238.691,9.879],[235.039,9.879],[235.039,11.533],[225.758,11.533],[225.758,2.016]]}}},{"ty":"sh","hd":false,"nm":"Path 1 (57)","d":1,"ks":{"a":0,"k":{"c":true,"i":[[0,0],[0,0],[0,0],[0,0],[0,0],[0,0]],"o":[[0,0],[0,0],[0,0],[0,0],[0,0],[0,0]],"v":[[228.4,19.633],[228.4,13.316],[231.172,13.316],[231.172,17.441],[241.828,17.441],[241.828,19.633]]}}},{"ty":"sh","hd":false,"nm":"Path 1 (57)","d":1,"ks":{"a":0,"k":{"c":true,"i":[[0,0],[0,0],[0,0],[0,0]],"o":[[0,0],[0,0],[0,0],[0,0]],"v":[[228.486,9.406],[232.354,9.406],[232.354,4.186],[228.486,4.186]]}}},{"ty":"sh","hd":false,"nm":"Path 1 (57)","d":1,"ks":{"a":0,"k":{"c":true,"i":[[0,0],[0,0],[0,0],[0,0]],"o":[[0,0],[0,0],[0,0],[0,0]],"v":[[235.039,7.709],[238.691,7.709],[238.691,5.711],[235.039,5.711]]}}},{"ty":"sh","hd":false,"nm":"Path 1 (57)","d":1,"ks":{"a":0,"k":{"c":true,"i":[[0,0],[0,0],[0,0],[0,0],[0,0],[0,0],[0,0],[0,0]],"o":[[0,0],[0,0],[0,0],[0,0],[0,0],[0,0],[0,0],[0,0]],"v":[[78.117,32.426],[78.117,39.924],[80.889,39.924],[80.889,42.18],[78.117,42.18],[78.117,51.934],[75.367,51.934],[75.367,32.426]]}}},{"ty":"sh","hd":false,"nm":"Path 1 (57)","d":1,"ks":{"a":0,"k":{"c":true,"i":[[0,0],[-0.515,4.361],[0,0],[0,0],[0,0],[6.574,-3.233]],"o":[[4.63,-2.321],[0,0],[0,0],[0,0],[-0.022,5.844],[0,0]],"v":[[62.477,46.456],[70.114,36.658],[63.594,36.658],[63.594,34.424],[72.897,34.424],[64.023,48.56]]}}},{"ty":"sh","hd":false,"nm":"Path 1 (57)","d":1,"ks":{"a":0,"k":{"c":true,"i":[[0,0],[0,0],[0,0],[0,0],[0,0],[0,0]],"o":[[0,0],[0,0],[0,0],[0,0],[0,0],[0,0]],"v":[[97.561,37.324],[97.561,39.516],[83.961,39.516],[83.961,32.726],[86.689,32.726],[86.689,37.324]]}}},{"ty":"sh","hd":false,"nm":"Path 1 (57)","d":1,"ks":{"a":0,"k":{"c":true,"i":[[0,0],[0,0],[0,0],[0,0]],"o":[[0,0],[0,0],[0,0],[0,0]],"v":[[81.705,43.426],[81.705,41.19],[99.58,41.19],[99.58,43.425]]}}},{"ty":"sh","hd":false,"nm":"Path 1 (57)","d":1,"ks":{"a":0,"k":{"c":false,"i":[[0,0],[-4.276,0.01],[-0.021,-2.31],[4.243,0],[0,2.33]],"o":[[0,-2.31],[4.243,0.01],[-0.021,2.331],[-4.276,0],[0,0]],"v":[[83.746,48.281],[90.6,44.651],[97.41,48.281],[90.6,51.912],[83.746,48.282]]}}},{"ty":"sh","hd":false,"nm":"Path 1 (57)","d":1,"ks":{"a":0,"k":{"c":false,"i":[[0,0],[-2.706,-0.011],[-0.011,1.021],[2.653,0.022],[-0.012,-1.042]],"o":[[-0.01,1.02],[2.654,-0.01],[-0.01,-1.042],[-2.707,0.022],[0,0]],"v":[[86.539,48.282],[90.599,49.829],[94.66,48.282],[90.6,46.778],[86.54,48.282]]}}},{"ty":"sh","hd":false,"nm":"Path 1 (57)","d":1,"ks":{"a":0,"k":{"c":true,"i":[[0,0],[0,0],[0,0],[0,0],[0,0],[0,0],[0,0],[0,0]],"o":[[0,0],[0,0],[0,0],[0,0],[0,0],[0,0],[0,0],[0,0]],"v":[[110.151,35.413],[110.151,37.583],[100.698,37.583],[100.698,35.413],[104.093,35.413],[104.093,32.963],[106.8,32.963],[106.8,35.413]]}}},{"ty":"sh","hd":false,"nm":"Path 1 (57)","d":1,"ks":{"a":0,"k":{"c":false,"i":[[0,0],[-2.492,0.01],[-0.011,-2.717],[2.503,0],[0,2.729]],"o":[[0,-2.717],[2.503,0.01],[-0.011,2.729],[-2.492,0],[0,0]],"v":[[101.149,43.104],[105.468,38.464],[109.765,43.104],[105.468,47.767],[101.149,43.104]]}}},{"ty":"sh","hd":false,"nm":"Path 1 (57)","d":1,"ks":{"a":0,"k":{"c":false,"i":[[0,0],[-1.139,0],[-0.01,1.494],[1.095,0],[0,-1.471]],"o":[[0,1.494],[1.095,0],[-0.01,-1.471],[-1.139,0],[0,0]],"v":[[103.556,43.104],[105.468,45.446],[107.358,43.104],[105.468,40.741],[103.556,43.104]]}}},{"ty":"sh","hd":false,"nm":"Path 1 (57)","d":1,"ks":{"a":0,"k":{"c":true,"i":[[0,0],[0,0],[0,0],[0,0],[0,0],[0,0],[0,0],[0,0],[0,0],[0,0],[0,0],[0,0]],"o":[[0,0],[0,0],[0,0],[0,0],[0,0],[0,0],[0,0],[0,0],[0,0],[0,0],[0,0],[0,0]],"v":[[110.882,51.14],[110.882,32.812],[113.439,32.812],[113.439,40.375],[115.028,40.375],[115.028,32.425],[117.628,32.425],[117.628,51.977],[115.028,51.977],[115.028,42.567],[113.439,42.567],[113.439,51.139]]}}},{"ty":"sh","hd":false,"nm":"Path 1 (57)","d":1,"ks":{"a":0,"k":{"c":true,"i":[[0,0],[0,0],[0,0],[0,0],[0,0],[0,0],[0,1.718],[-4.253,0.011],[-0.011,-3.169],[1.472,-0.914],[0,0]],"o":[[0,0],[0,0],[0,0],[0,0],[0,0],[-1.515,-0.914],[0,-3.17],[4.233,0.01],[-0.011,1.686],[0,0],[0,0]],"v":[[137.63,47.444],[137.63,49.7],[119.733,49.7],[119.733,47.444],[123.73,47.444],[123.73,42.654],[121.302,38.636],[128.649,33.372],[136.019,38.636],[133.655,42.6],[133.655,47.444]]}}},{"ty":"sh","hd":false,"nm":"Path 1 (57)","d":1,"ks":{"a":0,"k":{"c":false,"i":[[0,0],[-2.803,0],[-0.011,1.912],[2.761,-0.011],[0,-1.966]],"o":[[0,1.912],[2.761,0],[-0.011,-1.966],[-2.803,-0.01],[0,0]],"v":[[124.009,38.636],[128.649,41.729],[133.312,38.636],[128.649,35.542],[124.009,38.636]]}}},{"ty":"sh","hd":false,"nm":"Path 1 (57)","d":1,"ks":{"a":0,"k":{"c":true,"i":[[0,0],[0,0],[0,0],[0.785,0],[0.687,0.129]],"o":[[0,0],[0,0],[-0.698,0.14],[-0.785,0],[0,0]],"v":[[126.437,47.444],[130.884,47.444],[130.884,43.642],[128.649,43.857],[126.437,43.652]]}}},{"ty":"fl","hd":false,"bm":0,"c":{"a":0,"k":[0.133,0.133,0.141]},"r":1,"o":{"a":0,"k":100}},{"ty":"tr","nm":"Transform","a":{"a":0,"k":[0,0]},"o":{"a":0,"k":100},"p":{"a":0,"k":[0,0]},"r":{"a":0,"k":0},"s":{"a":0,"k":[100,100]},"sk":{"a":0,"k":0},"sa":{"a":0,"k":0}}],"np":0}]}]}],"ddd":0,"fr":30,"h":280,"ip":0,"layers":[{"ddd":0,"ind":4,"ty":0,"nm":"Frame 117127572ㄹ5","hd":false,"sr":1,"ks":{"a":{"a":0,"k":[70,10.5]},"o":{"a":0,"k":100},"p":{"a":0,"k":[90,113.36]},"r":{"a":0,"k":0},"s":{"a":0,"k":[100,100]},"sk":{"a":0,"k":0},"sa":{"a":0,"k":0}},"ao":0,"ip":0,"op":121,"st":0,"bm":0,"h":21,"refId":"el-640","w":140},{"ddd":0,"ind":8,"ty":0,"nm":"공유하고 싶은 경험만 있다면 누구나 가능해요","hd":false,"sr":1,"ks":{"a":{"a":0,"k":[121,26]},"o":{"a":0,"k":100},"p":{"a":0,"k":[141,52.5]},"r":{"a":0,"k":0},"s":{"a":0,"k":[100,100]},"sk":{"a":0,"k":0},"sa":{"a":0,"k":0}},"ao":0,"ip":0,"op":121,"st":0,"bm":0,"h":52,"refId":"el-622","w":242},{"ddd":0,"ind":9,"ty":4,"nm":"star1","hd":false,"sr":1,"ks":{"a":{"a":0,"k":[0,0]},"o":{"a":0,"k":100},"p":{"a":0,"k":[206.501,213.369]},"r":{"a":1,"k":[{"t":0,"s":[0],"i":{"x":0.5,"y":1},"o":{"x":0.12,"y":0.23}},{"t":82.8,"s":[360],"i":{"x":0,"y":0},"o":{"x":1,"y":1}}]},"s":{"a":0,"k":[100,100]},"sk":{"a":0,"k":0},"sa":{"a":0,"k":0}},"ao":0,"ip":0,"op":121,"st":0,"bm":0,"shapes":[{"ty":"gr","hd":false,"nm":"Layer 3 Group","bm":0,"it":[{"ty":"gr","hd":false,"nm":"Path 1 (2) Group","bm":0,"it":[{"ty":"sh","hd":false,"nm":"Path 1 (2)","d":1,"ks":{"a":0,"k":{"c":false,"i":[[0,0],[4.194,-4.412],[0.372,-1.015],[1.28,0.628],[1.205,-0.001],[0,-4.366],[-0.518,-1.051],[0.256,-0.615],[0.729,-0.245],[-4.567,-4.026],[-1.055,-0.332],[-0.269,-0.608],[0.323,-0.697],[-5.777,0.001],[-1.043,0.483],[-0.608,-0.269],[-0.23,-0.732],[-4.119,4.482],[-0.347,1.117],[-0.605,0.271],[-0.696,-0.318],[-2.232,1.33],[2.234,3.751],[-0.246,0.562],[-0.65,0.152],[4.162,4.441],[1.255,0.414],[0.261,0.597],[-0.31,0.679],[6.059,-0.574],[1.006,-0.599],[0.534,0.209],[0.185,0.601]],"o":[[-1.724,-5.838],[-0.745,0.783],[-0.491,1.341],[-1.083,-0.529],[-4.366,0],[0,1.254],[0.34,0.69],[-0.257,0.614],[-5.77,1.943],[0.83,0.731],[0.732,0.229],[0.269,0.608],[-2.431,5.24],[1.149,0.001],[0.696,-0.324],[0.608,0.269],[1.822,5.808],[0.791,-0.861],[0.226,-0.73],[0.605,-0.271],[2.362,1.084],[3.752,-2.233],[-0.307,-0.531],[0.216,-0.508],[5.927,-1.384],[-0.904,-0.964],[-0.708,-0.234],[-0.26,-0.596],[2.532,-5.534],[-1.166,0.11],[-0.586,0.349],[-0.588,-0.224],[0,0]],"v":[[213.848,190.669],[200.534,187.46],[198.841,190.186],[195.42,191.559],[191.943,190.756],[184.038,198.661],[184.847,202.15],[184.882,204.222],[183.386,205.656],[180.68,219.085],[183.539,220.697],[185.061,222.095],[185.072,224.163],[192.245,235.396],[195.573,234.664],[197.64,234.674],[199.039,236.196],[212.407,239.18],[214.136,236.176],[215.524,234.654],[217.584,234.633],[224.922,234.239],[227.671,223.403],[227.573,221.664],[228.893,220.531],[232.864,207.426],[229.575,205.325],[228.101,203.948],[228.094,201.932],[220.159,190.772],[216.861,191.849],[215.072,191.977],[213.848,190.669]]}}},{"ty":"sh","hd":false,"nm":"Path 1 (2)","d":1,"ks":{"a":0,"k":{"c":false,"i":[[0,0],[-0.559,0.333],[-0.093,-6.854],[0.549,-1.2],[-0.795,-0.262],[5.117,-4.561],[0.488,-0.291],[0.889,-0.21],[-0.307,-0.515],[4.227,-2.515],[2.661,1.22],[0.254,-0.82],[4.651,5.041],[0.394,1.254],[0.781,-0.363],[-0.607,6.829],[-0.434,0.935],[0.822,0.258],[-5.053,4.638],[-1.179,0.397],[0.381,0.775],[-6.595,-0.002],[-1.182,-0.58],[-0.286,0.782],[-4.395,-5.261],[-0.242,-0.406],[-0.207,-0.697]],"o":[[0.184,0.623],[5.89,-3.508],[0.018,1.32],[-0.348,0.762],[6.509,2.151],[-0.424,0.378],[-0.786,0.467],[-0.583,0.136],[2.516,4.226],[-2.514,1.498],[-0.78,-0.357],[-2.04,6.549],[-0.891,-0.966],[-0.257,-0.822],[-6.218,2.889],[0.091,-1.027],[0.363,-0.781],[-6.543,-2.057],[0.917,-0.841],[0.819,-0.275],[-2.911,-5.918],[1.406,0],[0.748,0.367],[2.358,-6.437],[0.303,0.363],[0.389,0.653],[0,0]],"v":[[214.807,190.385],[216.35,190.99],[229.811,198.52],[229.004,202.347],[229.889,204.375],[233.02,219.478],[231.648,220.483],[229.121,221.505],[228.531,222.891],[225.433,235.098],[217.168,235.543],[215.091,236.473],[200.036,239.866],[198.084,236.495],[195.994,235.571],[183.371,226.705],[184.165,223.741],[183.24,221.651],[179.888,206.587],[183.067,204.708],[183.95,202.591],[191.943,189.756],[195.86,190.661],[197.902,189.842],[213.097,187.196],[213.916,188.352],[214.807,190.385]]}}},{"ty":"gf","hd":false,"bm":0,"e":{"a":0,"k":[181.06333210881155,229.40161895755392]},"g":{"p":2,"k":{"a":0,"k":[0,1,1,1,1,1,1,1,0,1,1,0.17]}},"t":1,"a":{"a":0,"k":0},"h":{"a":0,"k":0},"o":{"a":0,"k":100},"r":1,"s":{"a":0,"k":[206.50000143633156,187.198288879985]}},{"ty":"tr","nm":"Transform","a":{"a":0,"k":[0,0]},"o":{"a":0,"k":100},"p":{"a":0,"k":[0,0]},"r":{"a":0,"k":0},"s":{"a":0,"k":[100,100]},"sk":{"a":0,"k":0},"sa":{"a":0,"k":0}}],"np":0},{"ty":"tr","nm":"Transform","a":{"a":0,"k":[206.501,213.368]},"o":{"a":0,"k":100},"p":{"a":0,"k":[0,-0.001]},"r":{"a":0,"k":0},"s":{"a":0,"k":[100,100]},"sk":{"a":0,"k":0},"sa":{"a":0,"k":0}}],"np":0},{"ty":"gr","hd":false,"nm":"Layer 4 Group","bm":0,"it":[{"ty":"gr","hd":false,"nm":"Path 1 Group","bm":0,"it":[{"ty":"sh","hd":false,"nm":"Path 1","d":1,"ks":{"a":0,"k":{"c":false,"i":[[0,0],[0.184,0.623],[0.38,0.638],[3.349,-5.981],[0.163,-0.444],[0.748,0.367],[1.358,-0.001],[-2.911,-5.918],[0.819,-0.275],[-5.147,-4.534],[-1.187,-0.373],[0.363,-0.781],[-6.829,0.607],[-0.935,0.434],[-0.257,-0.822],[-4.64,5.05],[-0.391,1.257],[-0.78,-0.357],[-2.514,1.498],[2.516,4.226],[-0.583,0.136],[-0.786,0.467],[5.981,3.349],[0.539,0.178],[-0.348,0.762],[6.825,-0.646],[1.134,-0.675]],"o":[[-0.559,0.333],[-0.212,-0.712],[-3.505,-5.891],[-0.231,0.413],[-0.286,0.782],[-1.22,-0.596],[-6.595,-0.002],[0.381,0.775],[-6.5,2.191],[0.934,0.822],[0.822,0.258],[-2.889,6.217],[1.027,-0.091],[0.781,-0.363],[2.054,6.543],[0.891,-0.969],[0.254,-0.82],[2.661,1.22],[4.227,-2.515],[-0.307,-0.515],[0.889,-0.21],[5.891,-3.505],[-0.496,-0.278],[-0.795,-0.262],[2.853,-6.233],[-1.314,0.124],[0,0]],"v":[[216.35,190.99],[214.807,190.385],[213.916,188.352],[198.493,188.555],[197.902,189.842],[195.86,190.661],[191.943,189.756],[183.95,202.591],[183.067,204.708],[180.023,219.837],[183.24,221.651],[184.165,223.741],[193.03,236.365],[195.994,235.571],[198.084,236.495],[213.145,239.854],[215.091,236.473],[217.168,235.543],[225.433,235.098],[228.531,222.891],[229.121,221.505],[231.648,220.483],[231.445,205.06],[229.889,204.375],[229.004,202.347],[220.068,189.775],[216.35,190.99]]}}},{"ty":"fl","hd":false,"bm":0,"c":{"a":0,"k":[0.435,0.42,1]},"r":1,"o":{"a":0,"k":92}},{"ty":"tr","nm":"Transform","a":{"a":0,"k":[0,0]},"o":{"a":0,"k":100},"p":{"a":0,"k":[0,0]},"r":{"a":0,"k":0},"s":{"a":0,"k":[100,100]},"sk":{"a":0,"k":0},"sa":{"a":0,"k":0}}],"np":0},{"ty":"tr","nm":"Transform","a":{"a":0,"k":[206.5,213.37]},"o":{"a":0,"k":100},"p":{"a":0,"k":[-0.001,0.001]},"r":{"a":0,"k":0},"s":{"a":0,"k":[100,100]},"sk":{"a":0,"k":0},"sa":{"a":0,"k":0}}],"np":0}]},{"ddd":0,"ind":14,"ty":4,"nm":"Layer 5","hd":false,"sr":1,"ks":{"a":{"a":0,"k":[165.37,189.037]},"o":{"a":1,"k":[{"t":0,"s":[0],"i":{"x":0.75,"y":0.75},"o":{"x":0.25,"y":0.25}},{"t":12.3,"s":[0],"i":{"x":0.75,"y":0.75},"o":{"x":0.25,"y":0.25}},{"t":37.5,"s":[100],"i":{"x":0,"y":0},"o":{"x":1,"y":1}}]},"p":{"a":1,"k":[{"t":0,"s":[139.406,215.216],"i":{"x":0.75,"y":0.75},"o":{"x":0.25,"y":0.25},"ti":[0,0],"to":[0,0]},{"t":38.4,"s":[164.367,187.038],"i":{"x":0,"y":0},"o":{"x":1,"y":1}}]},"r":{"a":0,"k":0},"s":{"a":0,"k":[100,100]},"sk":{"a":0,"k":0},"sa":{"a":0,"k":0}},"ao":0,"ip":0,"op":121,"st":0,"bm":0,"shapes":[{"ty":"gr","hd":false,"nm":"Path 1 Group","bm":0,"it":[{"ty":"sh","hd":false,"nm":"Path 1","d":1,"ks":{"a":0,"k":{"c":true,"i":[[0,0],[0,0],[0,-0.583],[0,0],[0.583,0],[0,0],[0,0.583],[0,0],[-0.583,0]],"o":[[0,0],[0.583,0],[0,0],[0,0.583],[0,0],[-0.583,0],[0,0],[0,-0.583],[0,0]],"v":[[187.793,164.328],[250.98,164.328],[252.036,165.383],[252.036,165.383],[250.98,166.439],[187.793,166.439],[186.737,165.383],[186.737,165.383],[187.793,164.328]]}}},{"ty":"gf","hd":false,"bm":0,"e":{"a":0,"k":[245.67433684226214,165.3093311347346]},"g":{"p":2,"k":{"a":0,"k":[0,0.933,0.933,1,1,0.882,0.878,1,0,1,1,0]}},"t":1,"a":{"a":0,"k":0},"h":{"a":0,"k":0},"o":{"a":0,"k":100},"r":1,"s":{"a":0,"k":[186.736998597057,165.38400256454094]}},{"ty":"tr","nm":"Transform","a":{"a":0,"k":[186.737,164.328]},"o":{"a":0,"k":100},"p":{"a":0,"k":[186.737,164.328]},"r":{"a":0,"k":129},"s":{"a":0,"k":[100,100]},"sk":{"a":0,"k":0},"sa":{"a":0,"k":0}}],"np":0}]},{"ddd":0,"ind":16,"ty":4,"nm":"Group 5","hd":false,"sr":1,"ks":{"a":{"a":0,"k":[0,0]},"o":{"a":1,"k":[{"t":0,"s":[0],"i":{"x":0.75,"y":0.75},"o":{"x":0.25,"y":0.25}},{"t":10.8,"s":[0],"i":{"x":0.75,"y":0.75},"o":{"x":0.25,"y":0.25}},{"t":21.6,"s":[50],"i":{"x":0,"y":0},"o":{"x":1,"y":1}}]},"p":{"a":0,"k":[4.861,243.541]},"r":{"a":0,"k":0},"s":{"a":0,"k":[100,100]},"sk":{"a":0,"k":0},"sa":{"a":0,"k":0}},"ao":0,"ip":0,"op":121,"st":0,"bm":0,"shapes":[{"ty":"gr","hd":false,"nm":"Layer 6 Group","bm":0,"it":[{"ty":"gr","hd":false,"nm":"Path 1 Group","bm":0,"it":[{"ty":"sh","hd":false,"nm":"Path 1","d":1,"ks":{"a":0,"k":{"c":true,"i":[[0,0],[0,0],[0,-0.409],[0,0],[0.409,0],[0,0],[0,0.409],[0,0],[-0.409,0]],"o":[[0,0],[0.409,0],[0,0],[0,0.409],[0,0],[-0.409,0],[0,0],[0,-0.409],[0,0]],"v":[[26.735,203.461],[71.081,203.461],[71.822,204.202],[71.822,204.202],[71.081,204.943],[26.735,204.943],[25.994,204.202],[25.994,204.202],[26.735,203.461]]}}},{"ty":"gf","hd":false,"bm":0,"e":{"a":0,"k":[104.30932593088706,196.79933671622064]},"g":{"p":2,"k":{"a":0,"k":[0,0.933,0.933,1,1,0.576,0.569,1,0,1,1,0.45]}},"t":1,"a":{"a":0,"k":0},"h":{"a":0,"k":0},"o":{"a":0,"k":100},"r":1,"s":{"a":0,"k":[25.993990751443846,204.20199599946645]}},{"ty":"tr","nm":"Transform","a":{"a":0,"k":[25.994,203.461]},"o":{"a":0,"k":100},"p":{"a":0,"k":[25.994,203.461]},"r":{"a":0,"k":129},"s":{"a":0,"k":[100,100]},"sk":{"a":0,"k":0},"sa":{"a":0,"k":0}}],"np":0},{"ty":"tr","nm":"Transform","a":{"a":0,"k":[10.998,220.802]},"o":{"a":0,"k":100},"p":{"a":0,"k":[-2.758,3.264]},"r":{"a":0,"k":0},"s":{"a":0,"k":[100,100]},"sk":{"a":0,"k":0},"sa":{"a":0,"k":0}}],"np":0},{"ty":"gr","hd":false,"nm":"Layer 15 Group","bm":0,"it":[{"ty":"gr","hd":false,"nm":"Path 1 Group","bm":0,"it":[{"ty":"sh","hd":false,"nm":"Path 1","d":1,"ks":{"a":0,"k":{"c":true,"i":[[0,0],[0.969,0],[0,0.969],[-0.969,0],[0,-0.969]],"o":[[0,0.969],[-0.969,0],[0,-0.969],[0.969,0],[0,0]],"v":[[31.51,197.755],[29.755,199.51],[28,197.755],[29.755,196],[31.51,197.755]]}}},{"ty":"fl","hd":false,"bm":0,"c":{"a":0,"k":[1,1,1]},"r":1,"o":{"a":0,"k":100}},{"ty":"tr","nm":"Transform","a":{"a":0,"k":[0,0]},"o":{"a":0,"k":100},"p":{"a":0,"k":[0,0]},"r":{"a":0,"k":0},"s":{"a":0,"k":[100,100]},"sk":{"a":0,"k":0},"sa":{"a":0,"k":0}}],"np":0},{"ty":"tr","nm":"Transform","a":{"a":0,"k":[29.755,197.755]},"o":{"a":0,"k":100},"p":{"a":0,"k":[15.999,-19.783]},"r":{"a":0,"k":0},"s":{"a":0,"k":[100,100]},"sk":{"a":0,"k":0},"sa":{"a":0,"k":0}}],"np":0},{"ty":"tm","hd":false,"bm":0,"e":{"a":0,"k":100},"o":{"a":0,"k":0},"s":{"a":0,"k":0},"m":1}]},{"ddd":0,"ind":21,"ty":4,"nm":"circle","hd":false,"sr":1,"ks":{"a":{"a":0,"k":[311.5,212.5]},"o":{"a":1,"k":[{"t":0,"s":[0],"i":{"x":0.75,"y":0.75},"o":{"x":0.25,"y":0.25}},{"t":48,"s":[0],"i":{"x":0.75,"y":0.75},"o":{"x":0.25,"y":0.25}},{"t":60.9,"s":[50],"i":{"x":0,"y":0},"o":{"x":1,"y":1}}]},"p":{"a":0,"k":[311.5,212.5]},"r":{"a":0,"k":0},"s":{"a":0,"k":[100,100]},"sk":{"a":0,"k":0},"sa":{"a":0,"k":0}},"ao":0,"ip":0,"op":121,"st":0,"bm":0,"shapes":[{"ty":"gr","hd":false,"nm":"Path 1 Group","bm":0,"it":[{"ty":"sh","hd":false,"nm":"Path 1","d":1,"ks":{"a":0,"k":{"c":true,"i":[[0,0],[1.381,0],[0,1.381],[-1.381,0],[0,-1.381]],"o":[[0,1.381],[-1.381,0],[0,-1.381],[1.381,0],[0,0]],"v":[[314,212.5],[311.5,215],[309,212.5],[311.5,210],[314,212.5]]}}},{"ty":"fl","hd":false,"bm":0,"c":{"a":0,"k":[1,1,1]},"r":1,"o":{"a":0,"k":100}},{"ty":"tr","nm":"Transform","a":{"a":0,"k":[0,0]},"o":{"a":0,"k":100},"p":{"a":0,"k":[0,0]},"r":{"a":0,"k":0},"s":{"a":0,"k":[100,100]},"sk":{"a":0,"k":0},"sa":{"a":0,"k":0}}],"np":0}]},{"ddd":0,"ind":23,"ty":4,"nm":"white","hd":false,"sr":1,"ks":{"a":{"a":0,"k":[0,0]},"o":{"a":0,"k":100},"p":{"a":0,"k":[0,0]},"r":{"a":0,"k":0},"s":{"a":0,"k":[100,100]},"sk":{"a":0,"k":0},"sa":{"a":0,"k":0}},"ao":0,"ip":0,"op":121,"st":0,"bm":0,"shapes":[{"ty":"sh","hd":false,"nm":"white","d":1,"ks":{"a":0,"k":{"c":true,"i":[[0,0],[83.671,0],[0,83.671],[-83.671,0],[0,-83.671]],"o":[[0,83.671],[-83.671,0],[0,-83.671],[83.671,0],[0,0]],"v":[[420,32.5],[268.5,184],[117,32.5],[268.5,-119],[420,32.5]]}}},{"ty":"gf","hd":false,"bm":0,"e":{"a":0,"k":[268.5,175.33557625758897]},"g":{"p":2,"k":{"a":0,"k":[0,1,1,1,1,1,1,1,0,1,1,0]}},"t":2,"a":{"a":0,"k":0},"h":{"a":0,"k":0},"o":{"a":0,"k":100},"r":1,"s":{"a":0,"k":[268.5,32.5]}}]},{"ddd":0,"ind":24,"ty":4,"nm":"line","hd":false,"sr":1,"ks":{"a":{"a":0,"k":[268.5,84.037]},"o":{"a":1,"k":[{"t":0,"s":[0],"i":{"x":0.75,"y":0.75},"o":{"x":0.25,"y":0.25}},{"t":10.2,"s":[0],"i":{"x":0.75,"y":0.75},"o":{"x":0.25,"y":0.25}},{"t":33.6,"s":[100],"i":{"x":0,"y":0},"o":{"x":1,"y":1}}]},"p":{"a":1,"k":[{"t":0,"s":[256.5,101.037],"i":{"x":0.75,"y":0.75},"o":{"x":0.25,"y":0.25},"ti":[0,0],"to":[0,0]},{"t":33.6,"s":[268.5,84.037],"i":{"x":0,"y":0},"o":{"x":1,"y":1}}]},"r":{"a":0,"k":0},"s":{"a":0,"k":[100,100]},"sk":{"a":0,"k":0},"sa":{"a":0,"k":0}},"ao":0,"ip":0,"op":121,"st":0,"bm":0,"shapes":[{"ty":"gr","hd":false,"nm":"Path 1 Group","bm":0,"it":[{"ty":"sh","hd":false,"nm":"Path 1","d":1,"ks":{"a":0,"k":{"c":true,"i":[[0,0],[0,0],[0,-0.583],[0,0],[0.583,0],[0,0],[0,0.583],[0,0],[-0.583,0]],"o":[[0,0],[0.583,0],[0,0],[0,0.583],[0,0],[-0.583,0],[0,0],[0,-0.583],[0,0]],"v":[[294.793,236.328],[357.98,236.328],[359.036,237.383],[359.036,237.383],[357.98,238.439],[294.793,238.439],[293.737,237.383],[293.737,237.383],[294.793,236.328]]}}},{"ty":"gf","hd":false,"bm":0,"e":{"a":0,"k":[359.1203238096947,237.46733608097176]},"g":{"p":2,"k":{"a":0,"k":[0,0.933,0.933,1,1,0.576,0.569,1,0,1,1,1]}},"t":1,"a":{"a":0,"k":0},"h":{"a":0,"k":0},"o":{"a":0,"k":100},"r":1,"s":{"a":0,"k":[293.73699889722417,237.38400274205353]}},{"ty":"tr","nm":"Transform","a":{"a":0,"k":[293.737,236.328]},"o":{"a":0,"k":100},"p":{"a":0,"k":[293.737,236.328]},"r":{"a":0,"k":129},"s":{"a":0,"k":[100,100]},"sk":{"a":0,"k":0},"sa":{"a":0,"k":0}}],"np":0}]},{"ddd":0,"ind":26,"ty":4,"nm":"circle","hd":false,"sr":1,"ks":{"a":{"a":0,"k":[300.499,226.5]},"o":{"a":1,"k":[{"t":0,"s":[0],"i":{"x":0.75,"y":0.75},"o":{"x":0.25,"y":0.25}},{"t":36.9,"s":[0],"i":{"x":0.75,"y":0.75},"o":{"x":0.25,"y":0.25}},{"t":53.7,"s":[100],"i":{"x":0,"y":0},"o":{"x":1,"y":1}}]},"p":{"a":0,"k":[300.499,226.5]},"r":{"a":0,"k":0},"s":{"a":0,"k":[100,100]},"sk":{"a":0,"k":0},"sa":{"a":0,"k":0}},"ao":0,"ip":0,"op":121,"st":0,"bm":0,"shapes":[{"ty":"gr","hd":false,"nm":"Path 1 Group","bm":0,"it":[{"ty":"sh","hd":false,"nm":"Path 1","d":1,"ks":{"a":0,"k":{"c":true,"i":[[0,0],[1.381,0],[0,1.381],[-1.381,0],[0,-1.381]],"o":[[0,1.381],[-1.381,0],[0,-1.381],[1.381,0],[0,0]],"v":[[302.999,226.5],[300.499,229],[297.999,226.5],[300.499,224],[302.999,226.5]]}}},{"ty":"fl","hd":false,"bm":0,"c":{"a":0,"k":[1,1,1]},"r":1,"o":{"a":0,"k":100}},{"ty":"tr","nm":"Transform","a":{"a":0,"k":[0,0]},"o":{"a":0,"k":100},"p":{"a":0,"k":[0,0]},"r":{"a":0,"k":0},"s":{"a":0,"k":[100,100]},"sk":{"a":0,"k":0},"sa":{"a":0,"k":0}}],"np":0}]},{"ddd":0,"ind":28,"ty":4,"nm":"lili","hd":false,"sr":1,"ks":{"a":{"a":0,"k":[107.737,257.328]},"o":{"a":1,"k":[{"t":0,"s":[0],"i":{"x":0.75,"y":0.75},"o":{"x":0.25,"y":0.25}},{"t":12,"s":[0],"i":{"x":0.75,"y":0.75},"o":{"x":0.25,"y":0.25}},{"t":27.3,"s":[80],"i":{"x":0,"y":0},"o":{"x":1,"y":1}}]},"p":{"a":0,"k":[107.737,257.328]},"r":{"a":0,"k":129},"s":{"a":0,"k":[100,100]},"sk":{"a":0,"k":0},"sa":{"a":0,"k":0}},"ao":0,"ip":0,"op":121,"st":0,"bm":0,"shapes":[{"ty":"sh","hd":false,"nm":"lili","d":1,"ks":{"a":0,"k":{"c":true,"i":[[0,0],[0,0],[0,-0.583],[0,0],[0.583,0],[0,0],[0,0.583],[0,0],[-0.583,0]],"o":[[0,0],[0.583,0],[0,0],[0,0.583],[0,0],[-0.583,0],[0,0],[0,-0.583],[0,0]],"v":[[108.793,257.328],[171.98,257.328],[173.036,258.384],[173.036,258.384],[171.98,259.439],[108.793,259.439],[107.737,258.384],[107.737,258.384],[108.793,257.328]]}}},{"ty":"gf","hd":false,"bm":0,"e":{"a":0,"k":[173.12034009939043,258.46733608229556]},"g":{"p":2,"k":{"a":0,"k":[0,0.933,0.933,1,1,0.576,0.569,1,0,1,1,1]}},"t":1,"a":{"a":0,"k":0},"h":{"a":0,"k":0},"o":{"a":1,"k":[{"t":0,"s":[100],"i":{"x":0.75,"y":0.75},"o":{"x":0.25,"y":0.25}},{"t":12,"s":[0],"i":{"x":0.75,"y":0.75},"o":{"x":0.25,"y":0.25}},{"t":27.3,"s":[75],"i":{"x":0,"y":0},"o":{"x":1,"y":1}}]},"r":1,"s":{"a":0,"k":[107.73699950629775,258.3840027429502]}}]},{"ddd":0,"ind":29,"ty":4,"nm":"circir","hd":false,"sr":1,"ks":{"a":{"a":0,"k":[0,0]},"o":{"a":1,"k":[{"t":0,"s":[0],"i":{"x":0.75,"y":0.75},"o":{"x":0.25,"y":0.25}},{"t":28.8,"s":[0],"i":{"x":0.75,"y":0.75},"o":{"x":0.25,"y":0.25}},{"t":39,"s":[100],"i":{"x":0,"y":0},"o":{"x":1,"y":1}}]},"p":{"a":0,"k":[0,0]},"r":{"a":0,"k":0},"s":{"a":0,"k":[100,100]},"sk":{"a":0,"k":0},"sa":{"a":0,"k":0}},"ao":0,"ip":0,"op":121,"st":0,"bm":0,"shapes":[{"ty":"sh","hd":false,"nm":"circir","d":1,"ks":{"a":0,"k":{"c":true,"i":[[0,0],[1.105,0],[0,1.105],[-1.105,0],[0,-1.105]],"o":[[0,1.105],[-1.105,0],[0,-1.105],[1.105,0],[0,0]],"v":[[121,241],[119,243],[117,241],[119,239],[121,241]]}}},{"ty":"fl","hd":false,"bm":0,"c":{"a":0,"k":[1,1,1]},"r":1,"o":{"a":0,"k":100}}]},{"ddd":0,"ind":30,"ty":4,"nm":"white1","hd":false,"sr":1,"ks":{"a":{"a":0,"k":[108,32.5]},"o":{"a":0,"k":100},"p":{"a":0,"k":[108,32.5]},"r":{"a":0,"k":0},"s":{"a":0,"k":[100,100]},"sk":{"a":0,"k":0},"sa":{"a":0,"k":0}},"ao":0,"ip":0,"op":121,"st":0,"bm":0,"shapes":[{"ty":"gr","hd":false,"nm":"Path 1 Group","bm":0,"it":[{"ty":"sh","hd":false,"nm":"Path 1","d":1,"ks":{"a":0,"k":{"c":true,"i":[[0,0],[83.671,0],[0,83.671],[-83.671,0],[0,-83.671]],"o":[[0,83.671],[-83.671,0],[0,-83.671],[83.671,0],[0,0]],"v":[[202,32.5],[50.5,184],[-101,32.5],[50.5,-119],[202,32.5]]}}},{"ty":"gf","hd":false,"bm":0,"e":{"a":0,"k":[50.5,175.33557625758897]},"g":{"p":2,"k":{"a":0,"k":[0,1,1,1,1,1,1,1,0,1,1,0]}},"t":2,"a":{"a":0,"k":0},"h":{"a":0,"k":0},"o":{"a":0,"k":100},"r":1,"s":{"a":0,"k":[50.5,32.5]}},{"ty":"tr","nm":"Transform","a":{"a":0,"k":[0,0]},"o":{"a":0,"k":100},"p":{"a":0,"k":[0,0]},"r":{"a":0,"k":0},"s":{"a":0,"k":[100,100]},"sk":{"a":0,"k":0},"sa":{"a":0,"k":0}}],"np":0},{"ty":"gr","hd":false,"nm":"Path 1 Group","bm":0,"it":[{"ty":"sh","hd":false,"nm":"Path 1","d":1,"ks":{"a":0,"k":{"c":true,"i":[[0,0],[83.671,0],[0,83.671],[-83.671,0],[0,-83.671]],"o":[[0,83.671],[-83.671,0],[0,-83.671],[83.671,0],[0,0]],"v":[[317,32.5],[165.5,184],[14,32.5],[165.5,-119],[317,32.5]]}}},{"ty":"gf","hd":false,"bm":0,"e":{"a":0,"k":[165.5,175.33557625758897]},"g":{"p":2,"k":{"a":0,"k":[0,1,1,1,1,1,1,1,0,1,1,0]}},"t":2,"a":{"a":0,"k":0},"h":{"a":0,"k":0},"o":{"a":0,"k":100},"r":1,"s":{"a":0,"k":[165.5,32.5]}},{"ty":"tr","nm":"Transform","a":{"a":0,"k":[0,0]},"o":{"a":0,"k":100},"p":{"a":0,"k":[0,0]},"r":{"a":0,"k":0},"s":{"a":0,"k":[100,100]},"sk":{"a":0,"k":0},"sa":{"a":0,"k":0}}],"np":0}]},{"ddd":0,"ind":33,"ty":4,"nm":"star3","hd":false,"sr":1,"ks":{"a":{"a":0,"k":[103.4,185.401]},"o":{"a":0,"k":100},"p":{"a":0,"k":[103.4,185.401]},"r":{"a":1,"k":[{"t":0,"s":[0],"i":{"x":0.5,"y":1},"o":{"x":0.12,"y":0.23}},{"t":106.8,"s":[360],"i":{"x":0,"y":0},"o":{"x":1,"y":1}}]},"s":{"a":0,"k":[100,100]},"sk":{"a":0,"k":0},"sa":{"a":0,"k":0}},"ao":0,"ip":0,"op":121,"st":0,"bm":0,"shapes":[{"ty":"gr","hd":false,"nm":"Path 1 Group","bm":0,"it":[{"ty":"sh","hd":false,"nm":"Path 1","d":1,"ks":{"a":0,"k":{"c":false,"i":[[0,0],[0,0],[0,0],[-0.776,-1.197],[0,0],[0,0],[0.297,-1.395],[0,0],[0,0],[1.196,-0.776],[0,0],[0,0],[1.394,0.297],[0,0],[0,0],[0.776,1.197],[0,0],[0,0],[-0.297,1.395],[0,0],[0,0],[-1.197,0.776],[0,0],[0,0],[-1.394,-0.297]],"o":[[0,0],[0,0],[-0.186,-1.414],[0,0],[0,0],[0.868,-1.131],[0,0],[0,0],[1.413,-0.187],[0,0],[0,0],[1.131,0.868],[0,0],[0,0],[0.186,1.413],[0,0],[0,0],[-0.868,1.131],[0,0],[0,0],[-1.414,0.187],[0,0],[0,0],[-1.131,-0.868],[0,0]],"v":[[97.092,182.054],[99.945,182.662],[99.564,179.77],[102.013,178.867],[103.601,181.314],[105.376,179],[107.746,180.093],[107.138,182.946],[110.031,182.565],[110.934,185.014],[108.486,186.602],[110.801,188.377],[109.708,190.747],[106.855,190.139],[107.236,193.032],[104.786,193.934],[103.199,191.487],[101.423,193.801],[99.053,192.708],[99.661,189.856],[96.769,190.236],[95.866,187.787],[98.313,186.199],[96,184.424],[97.093,182.054]]}}},{"ty":"fl","hd":false,"bm":0,"c":{"a":0,"k":[1,1,1]},"r":1,"o":{"a":0,"k":100}},{"ty":"tr","nm":"Transform","a":{"a":0,"k":[0,0]},"o":{"a":0,"k":100},"p":{"a":0,"k":[0,-1]},"r":{"a":0,"k":0},"s":{"a":0,"k":[100,100]},"sk":{"a":0,"k":0},"sa":{"a":0,"k":0}}],"np":0}]},{"ddd":0,"ind":35,"ty":4,"nm":"star2","hd":false,"sr":1,"ks":{"a":{"a":0,"k":[368.792,200.792]},"o":{"a":1,"k":[{"t":0,"s":[0],"i":{"x":0.75,"y":0.75},"o":{"x":0.25,"y":0.25}},{"t":43.8,"s":[100],"i":{"x":0,"y":0},"o":{"x":1,"y":1}}]},"p":{"a":0,"k":[368.792,200.792]},"r":{"a":1,"k":[{"t":0,"s":[0],"i":{"x":0.5,"y":1},"o":{"x":0.12,"y":0.23}},{"t":96,"s":[360],"i":{"x":0,"y":0},"o":{"x":1,"y":1}}]},"s":{"a":0,"k":[100,100]},"sk":{"a":0,"k":0},"sa":{"a":0,"k":0}},"ao":0,"ip":0,"op":121,"st":0,"bm":0,"shapes":[{"ty":"gr","hd":false,"nm":"Path 1 Group","bm":0,"it":[{"ty":"sh","hd":false,"nm":"Path 1","d":1,"ks":{"a":0,"k":{"c":false,"i":[[0,0],[0,0],[0,0],[-1.483,-2.286],[0,0],[0,0],[0.568,-2.665],[0,0],[0,0],[2.287,-1.483],[0,0],[0,0],[2.665,0.568],[0,0],[0,0],[1.483,2.286],[0,0],[0,0],[-0.568,2.665],[0,0],[0,0],[-2.287,1.483],[0,0],[0,0],[-2.666,-0.568]],"o":[[0,0],[0,0],[-0.356,-2.702],[0,0],[0,0],[1.659,-2.162],[0,0],[0,0],[2.702,-0.356],[0,0],[0,0],[2.162,1.659],[0,0],[0,0],[0.356,2.702],[0,0],[0,0],[-1.659,2.162],[0,0],[0,0],[-2.702,0.356],[0,0],[0,0],[-2.162,-1.659],[0,0]],"v":[[356.734,192.483],[362.187,193.645],[361.459,188.116],[366.141,186.39],[369.176,191.068],[372.57,186.644],[377.1,188.734],[375.939,194.187],[381.467,193.459],[383.193,198.141],[378.515,201.176],[382.939,204.57],[380.85,209.1],[375.396,207.939],[376.124,213.467],[371.442,215.194],[368.407,210.515],[365.013,214.939],[360.483,212.85],[361.645,207.396],[356.116,208.124],[354.39,203.443],[359.068,200.407],[354.644,197.013],[356.734,192.483]]}}},{"ty":"fl","hd":false,"bm":0,"c":{"a":0,"k":[0.886,0.882,1]},"r":1,"o":{"a":0,"k":100}},{"ty":"tr","nm":"Transform","a":{"a":0,"k":[0,0]},"o":{"a":0,"k":100},"p":{"a":0,"k":[0,0]},"r":{"a":0,"k":0},"s":{"a":0,"k":[100,100]},"sk":{"a":0,"k":0},"sa":{"a":0,"k":0}}],"np":0}]},{"ddd":0,"ind":37,"ty":4,"nm":"circircir","hd":false,"sr":1,"ks":{"a":{"a":0,"k":[194.499,150.5]},"o":{"a":0,"k":100},"p":{"a":0,"k":[194.499,150.5]},"r":{"a":0,"k":0},"s":{"a":0,"k":[100,100]},"sk":{"a":0,"k":0},"sa":{"a":0,"k":0}},"ao":0,"ip":0,"op":121,"st":0,"bm":0,"shapes":[{"ty":"gr","hd":false,"nm":"cicicici Group","bm":0,"it":[{"ty":"sh","hd":false,"nm":"cicicici","d":1,"ks":{"a":0,"k":{"c":true,"i":[[0,0],[1.381,0],[0,1.381],[-1.381,0],[0,-1.381]],"o":[[0,1.381],[-1.381,0],[0,-1.381],[1.381,0],[0,0]],"v":[[196.999,150.5],[194.499,153],[191.999,150.5],[194.499,148],[196.999,150.5]]}}},{"ty":"fl","hd":false,"bm":0,"c":{"a":0,"k":[1,1,1]},"r":1,"o":{"a":0,"k":100}},{"ty":"tr","nm":"Transform","a":{"a":0,"k":[0,0]},"o":{"a":1,"k":[{"t":0,"s":[0],"i":{"x":0.75,"y":0.75},"o":{"x":0.25,"y":0.25}},{"t":41.4,"s":[0],"i":{"x":0.75,"y":0.75},"o":{"x":0.25,"y":0.25}},{"t":55.2,"s":[100],"i":{"x":0,"y":0},"o":{"x":1,"y":1}}]},"p":{"a":0,"k":[0,0]},"r":{"a":0,"k":0},"s":{"a":0,"k":[100,100]},"sk":{"a":0,"k":0},"sa":{"a":0,"k":0}}],"np":0}]},{"ddd":0,"ind":39,"ty":4,"nm":"white","hd":false,"sr":1,"ks":{"a":{"a":0,"k":[94.5,23.5]},"o":{"a":0,"k":100},"p":{"a":0,"k":[94.5,23.5]},"r":{"a":0,"k":0},"s":{"a":0,"k":[100,100]},"sk":{"a":0,"k":0},"sa":{"a":0,"k":0}},"ao":0,"ip":0,"op":121,"st":0,"bm":0,"shapes":[{"ty":"gr","hd":false,"nm":"Path 1 Group","bm":0,"it":[{"ty":"sh","hd":false,"nm":"Path 1","d":1,"ks":{"a":0,"k":{"c":true,"i":[[0,0],[83.671,0],[0,83.671],[-83.671,0],[0,-83.671]],"o":[[0,83.671],[-83.671,0],[0,-83.671],[83.671,0],[0,0]],"v":[[246,23.5],[94.5,175],[-57,23.5],[94.5,-128],[246,23.5]]}}},{"ty":"gf","hd":false,"bm":0,"e":{"a":0,"k":[94.5,166.33557625758897]},"g":{"p":2,"k":{"a":0,"k":[0,1,1,1,1,1,1,1,0,1,1,0]}},"t":2,"a":{"a":0,"k":0},"h":{"a":0,"k":0},"o":{"a":0,"k":100},"r":1,"s":{"a":0,"k":[94.5,23.5]}},{"ty":"tr","nm":"Transform","a":{"a":0,"k":[0,0]},"o":{"a":0,"k":100},"p":{"a":0,"k":[0,0]},"r":{"a":0,"k":0},"s":{"a":0,"k":[100,100]},"sk":{"a":0,"k":0},"sa":{"a":0,"k":0}}],"np":0}]},{"ddd":0,"ind":41,"ty":4,"nm":"circle1","hd":false,"sr":1,"ks":{"a":{"a":0,"k":[350,159]},"o":{"a":1,"k":[{"t":0,"s":[0],"i":{"x":0.75,"y":0.75},"o":{"x":0.25,"y":0.25}},{"t":37.5,"s":[0],"i":{"x":0.75,"y":0.75},"o":{"x":0.25,"y":0.25}},{"t":72.3,"s":[75],"i":{"x":0,"y":0},"o":{"x":1,"y":1}}]},"p":{"a":0,"k":[350,159]},"r":{"a":0,"k":0},"s":{"a":0,"k":[100,100]},"sk":{"a":0,"k":0},"sa":{"a":0,"k":0}},"ao":0,"ip":0,"op":121,"st":0,"bm":0,"shapes":[{"ty":"gr","hd":false,"nm":"Path 1 Group","bm":0,"it":[{"ty":"sh","hd":false,"nm":"Path 1","d":1,"ks":{"a":0,"k":{"c":true,"i":[[0,0],[2.209,0],[0,2.209],[-2.209,0],[0,-2.209]],"o":[[0,2.209],[-2.209,0],[0,-2.209],[2.209,0],[0,0]],"v":[[354,159],[350,163],[346,159],[350,155],[354,159]]}}},{"ty":"fl","hd":false,"bm":0,"c":{"a":0,"k":[1,1,1]},"r":1,"o":{"a":1,"k":[{"t":0,"s":[100],"i":{"x":0.75,"y":0.75},"o":{"x":0.25,"y":0.25}},{"t":97.2,"s":[50],"i":{"x":0,"y":0},"o":{"x":1,"y":1}}]}},{"ty":"tr","nm":"Transform","a":{"a":0,"k":[0,0]},"o":{"a":0,"k":100},"p":{"a":0,"k":[0,0]},"r":{"a":0,"k":0},"s":{"a":0,"k":[100,100]},"sk":{"a":0,"k":0},"sa":{"a":0,"k":0}}],"np":0}]},{"ddd":0,"ind":43,"ty":4,"nm":"linecircle","hd":false,"sr":1,"ks":{"a":{"a":0,"k":[273.543,244.543]},"o":{"a":0,"k":100},"p":{"a":1,"k":[{"t":0,"s":[262.543,257.543],"i":{"x":0.75,"y":0.75},"o":{"x":0.25,"y":0.25},"ti":[0,0],"to":[0,0]},{"t":16.5,"s":[273.543,244.543],"i":{"x":0,"y":0},"o":{"x":1,"y":1}}]},"r":{"a":0,"k":0},"s":{"a":0,"k":[100,100]},"sk":{"a":0,"k":0},"sa":{"a":0,"k":0}},"ao":0,"ip":0,"op":121,"st":0,"bm":0,"shapes":[{"ty":"gr","hd":false,"nm":"Layer 25 Group","bm":0,"it":[{"ty":"gr","hd":false,"nm":"Path 1 Group","bm":0,"it":[{"ty":"sh","hd":false,"nm":"Path 1","d":1,"ks":{"a":0,"k":{"c":true,"i":[[0,0],[35.8,0],[0,35.8],[-35.8,0],[0,-35.8]],"o":[[0,35.8],[-35.8,0],[0,-35.8],[35.8,0],[0,0]],"v":[[338.365,244.543],[273.543,309.365],[208.721,244.543],[273.543,179.721],[338.365,244.543]]}}},{"ty":"gf","hd":false,"bm":0,"e":{"a":0,"k":[273.6263325902639,309.4483226228316]},"g":{"p":2,"k":{"a":0,"k":[0.5,1,1,1,1,1,1,1,0.5,0.14,1,1]}},"t":1,"a":{"a":0,"k":0},"h":{"a":0,"k":0},"o":{"a":0,"k":18},"r":1,"s":{"a":0,"k":[273.5429992577774,179.72099304373438]}},{"ty":"tr","nm":"Transform","a":{"a":0,"k":[273.543,244.543]},"o":{"a":0,"k":100},"p":{"a":0,"k":[273.543,244.543]},"r":{"a":0,"k":24},"s":{"a":0,"k":[100,100]},"sk":{"a":0,"k":0},"sa":{"a":0,"k":0}}],"np":0},{"ty":"tr","nm":"Transform","a":{"a":0,"k":[273.543,244.543]},"o":{"a":0,"k":100},"p":{"a":0,"k":[273.543,244.543]},"r":{"a":0,"k":0},"s":{"a":0,"k":[100,100]},"sk":{"a":0,"k":0},"sa":{"a":0,"k":0}}],"np":0},{"ty":"gr","hd":false,"nm":"Path 1 Group","bm":0,"it":[{"ty":"sh","hd":false,"nm":"Path 1","d":1,"ks":{"a":0,"k":{"c":true,"i":[[0,0],[34.696,0],[0,34.696],[-34.696,0],[0,-34.696]],"o":[[0,34.696],[-34.696,0],[0,-34.696],[34.696,0],[0,0]],"v":[[336.365,244.543],[273.543,307.365],[210.721,244.543],[273.543,181.721],[336.365,244.543]]}}},{"ty":"gs","hd":false,"bm":0,"o":{"a":0,"k":100},"e":{"a":1,"k":[{"t":0,"s":[271.5133262594674,289.2793410688357],"i":{"x":0,"y":0},"o":{"x":1,"y":1}},{"t":120,"s":[271.5133262594674,289.2793410688357],"i":{"x":0,"y":0},"o":{"x":1,"y":1}}]},"g":{"p":2,"k":{"a":1,"k":[{"t":0,"s":[0,1,1,1,1,1,1,1,0,1,1,0],"i":{"x":0.75,"y":0.75},"o":{"x":0.25,"y":0.25}},{"t":120,"s":[0,1,1,1,0.81,1,1,1,0,1,0.81,0],"i":{"x":0,"y":0},"o":{"x":1,"y":1}}]}},"t":1,"a":{"a":0,"k":0},"h":{"a":0,"k":0},"s":{"a":1,"k":[{"t":0,"s":[273.5429995378976,179.72099289405037],"i":{"x":0,"y":0},"o":{"x":1,"y":1}},{"t":120,"s":[273.5429995378976,179.72099289405037],"i":{"x":0,"y":0},"o":{"x":1,"y":1}}]},"lc":1,"lj":1,"ml":4,"w":{"a":0,"k":4}},{"ty":"tr","nm":"Transform","a":{"a":0,"k":[273.543,244.543]},"o":{"a":0,"k":100},"p":{"a":0,"k":[273.543,244.543]},"r":{"a":0,"k":24},"s":{"a":0,"k":[100,100]},"sk":{"a":0,"k":0},"sa":{"a":0,"k":0}}],"np":0}]},{"ddd":0,"ind":47,"ty":4,"nm":"bar3","hd":false,"sr":1,"ks":{"a":{"a":0,"k":[137.596,322.886]},"o":{"a":1,"k":[{"t":0,"s":[50],"i":{"x":0.75,"y":0.75},"o":{"x":0.25,"y":0.25}},{"t":18.9,"s":[100],"i":{"x":0,"y":0},"o":{"x":1,"y":1}}]},"p":{"a":1,"k":[{"t":0,"s":[115.596,346.886],"i":{"x":0.88,"y":0.77},"o":{"x":0.5,"y":0},"ti":[0,0],"to":[0,0]},{"t":18.9,"s":[137.596,322.886],"i":{"x":0,"y":0},"o":{"x":1,"y":1}}]},"r":{"a":0,"k":0},"s":{"a":0,"k":[100,100]},"sk":{"a":0,"k":0},"sa":{"a":0,"k":0}},"ao":0,"ip":0,"op":121,"st":0,"bm":0,"shapes":[{"ty":"gr","hd":false,"nm":"Path 1 Group","bm":0,"it":[{"ty":"sh","hd":false,"nm":"Path 1","d":1,"ks":{"a":0,"k":{"c":true,"i":[[0,0],[0,0],[0,-25.256],[0,0],[25.256,0],[0,0],[0,25.256],[0,0],[-25.256,0]],"o":[[0,0],[25.256,0],[0,0],[0,25.256],[0,0],[-25.256,0],[0,0],[0,-25.256],[0,0]],"v":[[363.107,178.201],[722.809,178.201],[768.539,223.931],[768.539,229.797],[722.809,275.527],[363.107,275.527],[317.377,229.797],[317.377,223.931],[363.107,178.201]]}}},{"ty":"gf","hd":false,"bm":0,"e":{"a":0,"k":[768.6223207839564,226.9473335769283]},"g":{"p":3,"k":{"a":0,"k":[0,0.914,0.898,1,0,0.922,0.91,1,1,1,1,1,0,1,0,1,1,1]}},"t":1,"a":{"a":0,"k":0},"h":{"a":0,"k":0},"o":{"a":0,"k":20},"r":1,"s":{"a":0,"k":[317.37701657338135,226.8640002407687]}},{"ty":"tr","nm":"Transform","a":{"a":0,"k":[317.377,178.201]},"o":{"a":0,"k":100},"p":{"a":0,"k":[317.377,178.201]},"r":{"a":0,"k":129},"s":{"a":0,"k":[100,100]},"sk":{"a":0,"k":0},"sa":{"a":0,"k":0}}],"np":0}]},{"ddd":0,"ind":49,"ty":4,"nm":"star0","hd":false,"sr":1,"ks":{"a":{"a":0,"k":[0,0]},"o":{"a":0,"k":100},"p":{"a":0,"k":[299.354,133.138]},"r":{"a":1,"k":[{"t":0,"s":[0],"i":{"x":0.5,"y":1},"o":{"x":0.12,"y":0.23}},{"t":120,"s":[360],"i":{"x":0,"y":0},"o":{"x":1,"y":1}}]},"s":{"a":0,"k":[100,100]},"sk":{"a":0,"k":0},"sa":{"a":0,"k":0}},"ao":0,"ip":0,"op":121,"st":0,"bm":0,"shapes":[{"ty":"gr","hd":false,"nm":"Layer 26 Group","bm":0,"it":[{"ty":"gr","hd":false,"nm":"Path 1 (2) Group","bm":0,"it":[{"ty":"sh","hd":false,"nm":"Path 1 (2)","d":1,"ks":{"a":0,"k":{"c":false,"i":[[0,0],[0.334,0.729],[4.821,-2.21],[0.973,-1.98],[1.921,1.213],[1.455,0.155],[0.567,-5.273],[-0.503,-1.38],[0.496,-0.904],[1.209,-0.267],[0.442,-4.1],[-3.748,-1.632],[-0.314,-0.981],[0.638,-1.059],[0.148,-1.388],[-5.273,-0.566],[-1.321,0.451],[-0.891,-0.515],[-0.241,-1.211],[-5.555,4.882],[-0.564,1.301],[-0.977,0.317],[-1.058,-0.628],[-2.869,1.318],[2.21,4.821],[-0.442,0.789],[-1.119,0.139],[2.709,5.905],[2.107,0.952],[0.304,0.968],[-0.612,1.032],[1.317,2.866],[4.821,-2.21],[0.822,0.428],[0.204,1.115]],"o":[[-0.145,-0.788],[-2.211,-4.82],[-2.007,0.916],[-1.005,2.041],[-1.239,-0.78],[-5.273,-0.566],[-0.158,1.46],[0.426,1.164],[-0.497,0.904],[-4.026,0.892],[-0.46,4.275],[1.132,0.493],[0.314,0.981],[-0.718,1.197],[-0.567,5.273],[1.388,0.153],[1.17,-0.398],[0.892,0.515],[1.45,7.252],[1.065,-0.936],[0.487,-1.129],[0.977,-0.318],[2.712,1.617],[4.82,-2.21],[-0.472,-1.027],[0.441,-0.79],[6.448,-0.795],[-0.959,-2.104],[-1.094,-0.497],[-0.304,-0.967],[1.613,-2.711],[-2.21,-4.821],[-1.033,0.474],[-0.82,-0.429],[0,0]],"v":[[311.293,104.893],[310.572,102.609],[297.841,97.882],[293.232,102.361],[287.612,103.945],[283.518,102.524],[272.944,111.046],[273.468,115.363],[273.182,118.627],[270.584,120.622],[263.107,128.975],[268.817,138.807],[270.98,141.257],[270.638,144.509],[269.323,148.432],[277.844,159.005],[281.957,158.553],[285.207,158.911],[287.142,161.545],[302.904,166.878],[305.378,163.48],[307.812,161.315],[311.055,161.638],[319.969,162.115],[324.696,149.384],[324.835,146.488],[327.226,144.852],[334.78,131.317],[330.024,126.577],[327.929,124.162],[328.266,120.985],[328.739,112.077],[316.008,107.35],[313.06,107.251],[311.293,104.893]]}}},{"ty":"sh","hd":false,"nm":"Path 1 (2)","d":1,"ks":{"a":0,"k":{"c":false,"i":[[0,0],[-0.77,0.353],[-2.671,-5.824],[1.948,-3.275],[-0.993,-0.45],[-1.161,-2.542],[5.825,-2.671],[1.181,-0.147],[-0.326,-0.709],[5.825,-2.671],[3.276,1.951],[0.444,-1.026],[5.179,0.556],[0.964,4.842],[1.062,-0.362],[1.735,0.186],[-0.685,6.371],[-0.845,1.402],[1.029,0.447],[-0.555,5.168],[-4.733,1.044],[0.387,1.057],[-0.191,1.765],[-6.371,-0.684],[-1.451,-0.916],[-0.48,0.974],[-2.426,1.107],[-2.671,-5.825],[-0.17,-0.931]],"o":[[0.153,0.834],[5.825,-2.67],[1.591,3.463],[-0.556,0.938],[2.545,1.152],[2.671,5.824],[-1.082,0.497],[-0.775,0.096],[2.67,5.825],[-3.465,1.591],[-0.961,-0.571],[-1.963,4.542],[-5.168,-0.556],[-0.219,-1.1],[-1.55,0.527],[-6.371,-0.685],[0.187,-1.735],[0.579,-0.961],[-4.526,-1.971],[0.547,-5.086],[1.099,-0.243],[-0.608,-1.668],[0.684,-6.371],[1.821,0.195],[0.917,0.58],[1.176,-2.393],[5.824,-2.67],[0.412,0.9],[0,0]],"v":[[313.26,104.533],[315.175,105.532],[330.557,111.243],[329.986,122.005],[330.85,124.755],[336.598,130.484],[330.887,145.866],[327.472,146.837],[326.514,148.551],[320.802,163.933],[310.034,163.358],[307.213,164.274],[295.322,171.202],[285.181,161.935],[282.602,160.447],[277.63,160.994],[267.334,148.219],[268.925,143.477],[268.018,140.641],[261.118,128.762],[270.153,118.669],[271.59,116.05],[270.956,110.832],[283.731,100.536],[288.68,102.254],[291.438,101.477],[297.008,96.064],[312.39,101.776],[313.26,104.533]]}}},{"ty":"gf","hd":false,"bm":0,"e":{"a":0,"k":[248.58333866400585,144.64146192540215]},"g":{"p":2,"k":{"a":0,"k":[0,1,1,1,1,1,1,1,0,1,1,0.17]}},"t":1,"a":{"a":0,"k":0},"h":{"a":0,"k":0},"o":{"a":0,"k":100},"r":1,"s":{"a":0,"k":[332.50000474232445,82.5581306565912]}},{"ty":"tr","nm":"Transform","a":{"a":0,"k":[0,0]},"o":{"a":0,"k":100},"p":{"a":0,"k":[0,0]},"r":{"a":0,"k":0},"s":{"a":0,"k":[100,100]},"sk":{"a":0,"k":0},"sa":{"a":0,"k":0}}],"np":0},{"ty":"tr","nm":"Transform","a":{"a":0,"k":[299.354,133.138]},"o":{"a":0,"k":100},"p":{"a":0,"k":[0,0]},"r":{"a":0,"k":0},"s":{"a":0,"k":[100,100]},"sk":{"a":0,"k":0},"sa":{"a":0,"k":0}}],"np":0},{"ty":"gr","hd":false,"nm":"Layer 27 Group","bm":0,"it":[{"ty":"gr","hd":false,"nm":"Path 1 Group","bm":0,"it":[{"ty":"sh","hd":false,"nm":"Path 1","d":1,"ks":{"a":0,"k":{"c":false,"i":[[0,0],[0.153,0.834],[0.403,0.88],[5.824,-2.67],[1.176,-2.393],[0.917,0.58],[1.759,0.186],[0.684,-6.371],[-0.608,-1.668],[1.099,-0.243],[0.547,-5.086],[-4.526,-1.971],[0.579,-0.961],[0.179,-1.678],[-6.371,-0.685],[-1.55,0.527],[-0.219,-1.1],[-5.168,-0.556],[-1.963,4.542],[-0.961,-0.571],[-3.465,1.591],[2.67,5.825],[-0.775,0.096],[-1.082,0.497],[2.671,5.824],[2.545,1.152],[-0.556,0.938],[1.591,3.463],[5.825,-2.67]],"o":[[-0.77,0.353],[-0.175,-0.951],[-2.671,-5.825],[-2.426,1.107],[-0.48,0.974],[-1.496,-0.944],[-6.371,-0.685],[-0.191,1.765],[0.387,1.057],[-4.733,1.044],[-0.555,5.168],[1.029,0.447],[-0.869,1.446],[-0.685,6.371],[1.735,0.186],[1.062,-0.362],[0.964,4.842],[5.179,0.556],[0.444,-1.026],[3.276,1.951],[5.825,-2.671],[-0.326,-0.709],[1.181,-0.147],[5.825,-2.671],[-1.161,-2.542],[-0.993,-0.45],[1.948,-3.275],[-2.671,-5.824],[0,0]],"v":[[315.175,105.532],[313.26,104.533],[312.39,101.776],[297.008,96.064],[291.438,101.477],[288.68,102.254],[283.731,100.536],[270.956,110.832],[271.59,116.05],[270.153,118.669],[261.118,128.762],[268.018,140.641],[268.925,143.477],[267.334,148.219],[277.63,160.994],[282.602,160.447],[285.181,161.935],[295.322,171.202],[307.213,164.274],[310.034,163.358],[320.802,163.933],[326.514,148.551],[327.472,146.837],[330.887,145.866],[336.598,130.484],[330.85,124.755],[329.986,122.005],[330.557,111.243],[315.175,105.532]]}}},{"ty":"fl","hd":false,"bm":0,"c":{"a":0,"k":[0.643,0.631,1]},"r":1,"o":{"a":0,"k":42}},{"ty":"tr","nm":"Transform","a":{"a":0,"k":[0,0]},"o":{"a":0,"k":100},"p":{"a":0,"k":[0,0]},"r":{"a":0,"k":0},"s":{"a":0,"k":[100,100]},"sk":{"a":0,"k":0},"sa":{"a":0,"k":0}}],"np":0},{"ty":"tr","nm":"Transform","a":{"a":0,"k":[299.354,133.138]},"o":{"a":0,"k":100},"p":{"a":0,"k":[0,0]},"r":{"a":0,"k":0},"s":{"a":0,"k":[100,100]},"sk":{"a":0,"k":0},"sa":{"a":0,"k":0}}],"np":0}]},{"ddd":0,"ind":54,"ty":4,"nm":"bar2","hd":false,"sr":1,"ks":{"a":{"a":0,"k":[0,0]},"o":{"a":1,"k":[{"t":0,"s":[30],"i":{"x":0.5,"y":1},"o":{"x":0.12,"y":0.23}},{"t":15.9,"s":[100],"i":{"x":0,"y":0},"o":{"x":1,"y":1}}]},"p":{"a":1,"k":[{"t":0,"s":[87.976,222.83],"i":{"x":0.5,"y":1},"o":{"x":0.12,"y":0.23},"ti":[0,0],"to":[0,0]},{"t":15.9,"s":[104.663,211.615],"i":{"x":0,"y":0},"o":{"x":1,"y":1}}]},"r":{"a":0,"k":0},"s":{"a":0,"k":[100,100]},"sk":{"a":0,"k":0},"sa":{"a":0,"k":0}},"ao":0,"ip":0,"op":121,"st":0,"bm":0,"shapes":[{"ty":"gr","hd":false,"nm":"Layer 30 Group","bm":0,"it":[{"ty":"gr","hd":false,"nm":"Path 1 Group","bm":0,"it":[{"ty":"sh","hd":false,"nm":"Path 1","d":1,"ks":{"a":0,"k":{"c":true,"i":[[0,0],[0,0],[0,-11.04],[0,0],[11.04,0],[0,0],[0,11.04],[0,0],[-11.04,0]],"o":[[0,0],[11.04,0],[0,0],[0,11.04],[0,0],[-11.04,0],[0,0],[0,-11.04],[0,0]],"v":[[177.692,177.882],[256.902,177.882],[276.892,197.872],[276.892,197.872],[256.902,217.862],[177.692,217.862],[157.702,197.872],[157.702,197.872],[177.692,177.882]]}}},{"ty":"gs","hd":false,"bm":0,"o":{"a":0,"k":100},"e":{"a":0,"k":[200.8973279481403,188.34734147744402]},"g":{"p":2,"k":{"a":0,"k":[0,1,1,1,1,1,1,1,0,1,1,0.12]}},"t":1,"a":{"a":0,"k":0},"h":{"a":0,"k":0},"s":{"a":0,"k":[153.93499708017174,179.23800686232664]},"lc":1,"lj":1,"ml":4,"w":{"a":0,"k":1.332}},{"ty":"tr","nm":"Transform","a":{"a":0,"k":[157.702,177.882]},"o":{"a":0,"k":100},"p":{"a":0,"k":[157.702,177.882]},"r":{"a":0,"k":129},"s":{"a":0,"k":[100,100]},"sk":{"a":0,"k":0},"sa":{"a":0,"k":0}}],"np":0},{"ty":"tr","nm":"Transform","a":{"a":0,"k":[104.663,211.616]},"o":{"a":0,"k":100},"p":{"a":0,"k":[-0.001,0.001]},"r":{"a":0,"k":0},"s":{"a":0,"k":[100,100]},"sk":{"a":0,"k":0},"sa":{"a":0,"k":0}}],"np":0},{"ty":"gr","hd":false,"nm":"Layer 31 Group","bm":0,"it":[{"ty":"gr","hd":false,"nm":"Path 1 Group","bm":0,"it":[{"ty":"sh","hd":false,"nm":"Path 1","d":1,"ks":{"a":0,"k":{"c":true,"i":[[0,0],[0,0],[0,-11.408],[0,0],[11.408,0],[0,0],[0,11.408],[0,0],[-11.408,0]],"o":[[0,0],[11.408,0],[0,0],[0,11.408],[0,0],[-11.408,0],[0,0],[0,-11.408],[0,0]],"v":[[179.295,177.783],[258.504,177.783],[279.16,198.439],[279.16,198.439],[258.504,219.095],[179.295,219.095],[158.639,198.439],[158.639,198.439],[179.295,177.783]]}}},{"ty":"gf","hd":false,"bm":0,"e":{"a":1,"k":[{"t":0,"s":[279.2433341828642,198.52232893687037],"i":{"x":0,"y":0},"o":{"x":1,"y":1}},{"t":31.2,"s":[279.2433341828642,198.52232893687037],"i":{"x":0,"y":0},"o":{"x":1,"y":1}}]},"g":{"p":2,"k":{"a":1,"k":[{"t":0,"s":[0,0.475,0.376,1,1,1,1,1,0,1,1,1],"i":{"x":0.75,"y":0.75},"o":{"x":0.25,"y":0.25}},{"t":31.2,"s":[0,0.184,0.039,1,1,1,1,1,0,1,1,1],"i":{"x":0,"y":0},"o":{"x":1,"y":1}}]}},"t":1,"a":{"a":0,"k":0},"h":{"a":0,"k":0},"o":{"a":0,"k":20},"r":1,"s":{"a":1,"k":[{"t":0,"s":[158.63900898776984,198.43899559940522],"i":{"x":0,"y":0},"o":{"x":1,"y":1}},{"t":31.2,"s":[158.63900898776984,198.43899559940522],"i":{"x":0,"y":0},"o":{"x":1,"y":1}}]}},{"ty":"tr","nm":"Transform","a":{"a":0,"k":[158.639,177.783]},"o":{"a":0,"k":100},"p":{"a":0,"k":[158.639,177.783]},"r":{"a":0,"k":129},"s":{"a":0,"k":[100,100]},"sk":{"a":0,"k":0},"sa":{"a":0,"k":0}}],"np":0},{"ty":"tr","nm":"Transform","a":{"a":0,"k":[104.663,211.615]},"o":{"a":0,"k":100},"p":{"a":0,"k":[0,0]},"r":{"a":0,"k":0},"s":{"a":0,"k":[100,100]},"sk":{"a":0,"k":0},"sa":{"a":0,"k":0}}],"np":0}]},{"ddd":0,"ind":59,"ty":4,"nm":"bar1","hd":false,"sr":1,"ks":{"a":{"a":0,"k":[0,0]},"o":{"a":1,"k":[{"t":0,"s":[0],"i":{"x":0.75,"y":0.75},"o":{"x":0.25,"y":0.25}},{"t":5.1,"s":[0],"i":{"x":0.5,"y":1},"o":{"x":0.12,"y":0.23}},{"t":29.1,"s":[75],"i":{"x":0,"y":0},"o":{"x":1,"y":1}}]},"p":{"a":1,"k":[{"t":0,"s":[-2.662,300.473],"i":{"x":0.5,"y":1},"o":{"x":0.12,"y":0.23},"ti":[0,0],"to":[0,0]},{"t":29.1,"s":[49.3,247.455],"i":{"x":0,"y":0},"o":{"x":1,"y":1}}]},"r":{"a":0,"k":0},"s":{"a":0,"k":[100,100]},"sk":{"a":0,"k":0},"sa":{"a":0,"k":0}},"ao":0,"ip":0,"op":121,"st":0,"bm":0,"shapes":[{"ty":"gr","hd":false,"nm":"Layer 32 Group","bm":0,"it":[{"ty":"gr","hd":false,"nm":"Path 1 Group","bm":0,"it":[{"ty":"sh","hd":false,"nm":"Path 1","d":1,"ks":{"a":0,"k":{"c":true,"i":[[0,0],[0,0],[0,-9.682],[0,0],[9.683,0],[0,0],[0,9.682],[0,0],[-9.683,0]],"o":[[0,0],[9.683,0],[0,0],[0,9.682],[0,0],[-9.683,0],[0,0],[0,-9.682],[0,0]],"v":[[113.349,217.87],[182.817,217.87],[200.349,235.401],[200.349,235.401],[182.817,252.933],[113.349,252.933],[95.817,235.401],[95.817,235.401],[113.349,217.87]]}}},{"ty":"gs","hd":false,"bm":0,"o":{"a":0,"k":100},"e":{"a":0,"k":[133.71033056182884,227.05833948393797]},"g":{"p":2,"k":{"a":0,"k":[0,1,1,1,1,1,1,1,0,1,1,0.12]}},"t":1,"a":{"a":0,"k":0},"h":{"a":0,"k":0},"s":{"a":0,"k":[92.51299989133324,219.05900606962715]},"lc":1,"lj":1,"ml":4,"w":{"a":0,"k":1.168}},{"ty":"tr","nm":"Transform","a":{"a":0,"k":[95.817,217.87]},"o":{"a":0,"k":100},"p":{"a":0,"k":[95.817,217.87]},"r":{"a":0,"k":129},"s":{"a":0,"k":[100,100]},"sk":{"a":0,"k":0},"sa":{"a":0,"k":0}}],"np":0},{"ty":"tr","nm":"Transform","a":{"a":0,"k":[49.3,247.455]},"o":{"a":0,"k":100},"p":{"a":0,"k":[0,0.001]},"r":{"a":0,"k":0},"s":{"a":0,"k":[100,100]},"sk":{"a":0,"k":0},"sa":{"a":0,"k":0}}],"np":0},{"ty":"gr","hd":false,"nm":"Layer 33 Group","bm":0,"it":[{"ty":"gr","hd":false,"nm":"Path 1 Group","bm":0,"it":[{"ty":"sh","hd":false,"nm":"Path 1","d":1,"ks":{"a":0,"k":{"c":true,"i":[[0,0],[0,0],[0,-10.005],[0,0],[10.005,0],[0,0],[0,10.005],[0,0],[-10.005,0]],"o":[[0,0],[10.005,0],[0,0],[0,10.005],[0,0],[-10.005,0],[0,0],[0,-10.005],[0,0]],"v":[[114.754,217.783],[184.222,217.783],[202.338,235.898],[202.338,235.898],[184.222,254.014],[114.754,254.014],[96.638,235.898],[96.638,235.898],[114.754,217.783]]}}},{"ty":"gf","hd":false,"bm":0,"e":{"a":0,"k":[202.42133706372954,235.98233658775376]},"g":{"p":2,"k":{"a":0,"k":[0,0.475,0.376,1,1,1,1,1,0,1,1,1]}},"t":1,"a":{"a":0,"k":0},"h":{"a":0,"k":0},"o":{"a":0,"k":20},"r":1,"s":{"a":0,"k":[96.63800171186502,235.89900325304652]}},{"ty":"tr","nm":"Transform","a":{"a":0,"k":[96.638,217.783]},"o":{"a":0,"k":100},"p":{"a":0,"k":[96.638,217.783]},"r":{"a":0,"k":129},"s":{"a":0,"k":[100,100]},"sk":{"a":0,"k":0},"sa":{"a":0,"k":0}}],"np":0},{"ty":"tr","nm":"Transform","a":{"a":0,"k":[49.3,247.455]},"o":{"a":0,"k":100},"p":{"a":0,"k":[0,0]},"r":{"a":0,"k":0},"s":{"a":0,"k":[100,100]},"sk":{"a":0,"k":0},"sa":{"a":0,"k":0}}],"np":0}]},{"ddd":0,"ind":64,"ty":4,"nm":"background","hd":false,"sr":1,"ks":{"a":{"a":0,"k":[245.5,98]},"o":{"a":0,"k":100},"p":{"a":0,"k":[245.5,98]},"r":{"a":0,"k":0},"s":{"a":0,"k":[100,100]},"sk":{"a":0,"k":0},"sa":{"a":0,"k":0}},"ao":0,"ip":0,"op":121,"st":0,"bm":0,"shapes":[{"ty":"gr","hd":false,"nm":"Path 1 Group","bm":0,"it":[{"ty":"sh","hd":false,"nm":"Path 1","d":1,"ks":{"a":0,"k":{"c":true,"i":[[0,0],[0,0],[0,0],[0,0]],"o":[[0,0],[0,0],[0,0],[0,0]],"v":[[0,0],[375,0],[375,315],[0,315]]}}},{"ty":"gf","hd":false,"bm":0,"e":{"a":1,"k":[{"t":0,"s":[187.58334451030575,315.0833132138756],"i":{"x":0,"y":0},"o":{"x":1,"y":1}},{"t":51.9,"s":[187.58334451030575,315.0833132138756],"i":{"x":0,"y":0},"o":{"x":1,"y":1}}]},"g":{"p":2,"k":{"a":1,"k":[{"t":0,"s":[0,1,1,1,1,0.329,0.318,1,0,0.52,1,1],"i":{"x":0.75,"y":0.75},"o":{"x":0.25,"y":0.25}},{"t":51.9,"s":[0,1,1,1,1,0.329,0.318,1,0,0.52,1,1],"i":{"x":0,"y":0},"o":{"x":1,"y":1}}]}},"t":1,"a":{"a":0,"k":0},"h":{"a":0,"k":0},"o":{"a":0,"k":100},"r":1,"s":{"a":1,"k":[{"t":0,"s":[187.50001117882678,-2.086162520509305e-9],"i":{"x":0,"y":0},"o":{"x":1,"y":1}},{"t":51.9,"s":[187.50001117882678,-2.086162520509305e-9],"i":{"x":0,"y":0},"o":{"x":1,"y":1}}]}},{"ty":"tr","nm":"Transform","a":{"a":0,"k":[0,0]},"o":{"a":0,"k":100},"p":{"a":0,"k":[0,0]},"r":{"a":0,"k":0},"s":{"a":0,"k":[100,100]},"sk":{"a":0,"k":0},"sa":{"a":0,"k":0}}],"np":0},{"ty":"gr","hd":false,"nm":"Path 1 Group","bm":0,"it":[{"ty":"sh","hd":false,"nm":"Path 1","d":1,"ks":{"a":0,"k":{"c":true,"i":[[0,0],[83.671,0],[0,83.671],[-83.671,0],[0,-83.671]],"o":[[0,83.671],[-83.671,0],[0,-83.671],[83.671,0],[0,0]],"v":[[491,37.5],[339.5,189],[188,37.5],[339.5,-114],[491,37.5]]}}},{"ty":"gf","hd":false,"bm":0,"e":{"a":0,"k":[339.5,180.33557625758897]},"g":{"p":2,"k":{"a":0,"k":[0,1,1,1,1,1,1,1,0,1,1,0]}},"t":2,"a":{"a":0,"k":0},"h":{"a":0,"k":0},"o":{"a":0,"k":100},"r":1,"s":{"a":0,"k":[339.5,37.5]}},{"ty":"tr","nm":"Transform","a":{"a":0,"k":[0,0]},"o":{"a":0,"k":100},"p":{"a":0,"k":[0,0]},"r":{"a":0,"k":0},"s":{"a":0,"k":[100,100]},"sk":{"a":0,"k":0},"sa":{"a":0,"k":0}}],"np":0},{"ty":"gr","hd":false,"nm":"Path 1 Group","bm":0,"it":[{"ty":"sh","hd":false,"nm":"Path 1","d":1,"ks":{"a":0,"k":{"c":true,"i":[[0,0],[83.671,0],[0,83.671],[-83.671,0],[0,-83.671]],"o":[[0,83.671],[-83.671,0],[0,-83.671],[83.671,0],[0,0]],"v":[[468,32.5],[316.5,184],[165,32.5],[316.5,-119],[468,32.5]]}}},{"ty":"gf","hd":false,"bm":0,"e":{"a":0,"k":[316.5,175.33557625758897]},"g":{"p":2,"k":{"a":0,"k":[0,1,1,1,1,1,1,1,0,1,1,0]}},"t":2,"a":{"a":0,"k":0},"h":{"a":0,"k":0},"o":{"a":0,"k":100},"r":1,"s":{"a":0,"k":[316.5,32.5]}},{"ty":"tr","nm":"Transform","a":{"a":0,"k":[0,0]},"o":{"a":0,"k":100},"p":{"a":0,"k":[0,0]},"r":{"a":0,"k":0},"s":{"a":0,"k":[100,100]},"sk":{"a":0,"k":0},"sa":{"a":0,"k":0}}],"np":0},{"ty":"gr","hd":false,"nm":"Path 1 Group","bm":0,"it":[{"ty":"sh","hd":false,"nm":"Path 1","d":1,"ks":{"a":0,"k":{"c":true,"i":[[0,0],[0,0],[0,0],[0,0]],"o":[[0,0],[0,0],[0,0],[0,0]],"v":[[0,0],[375,0],[375,280],[0,280]]}}},{"ty":"fl","hd":false,"bm":0,"c":{"a":0,"k":[0.973,0.976,0.988]},"r":1,"o":{"a":0,"k":100}},{"ty":"tr","nm":"Transform","a":{"a":0,"k":[0,0]},"o":{"a":0,"k":100},"p":{"a":0,"k":[0,0]},"r":{"a":0,"k":0},"s":{"a":0,"k":[100,100]},"sk":{"a":0,"k":0},"sa":{"a":0,"k":0}}],"np":0}]},{"ddd":0,"ind":69,"ty":4,"nm":"Screen","hd":false,"sr":1,"ks":{"a":{"a":0,"k":[187.5,140]},"o":{"a":0,"k":100},"p":{"a":0,"k":[250,250]},"r":{"a":0,"k":0},"s":{"a":0,"k":[100,100]},"sk":{"a":0,"k":0},"sa":{"a":0,"k":0}},"ao":0,"ip":0,"op":121,"st":0,"bm":0,"shapes":[{"ty":"gr","hd":false,"nm":"Screen Group","bm":0,"it":[{"ty":"rc","hd":false,"nm":"Screen","d":1,"p":{"a":0,"k":[187.5,140]},"r":{"a":0,"k":0},"s":{"a":0,"k":[375,280]}},{"ty":"fl","hd":false,"bm":0,"c":{"a":0,"k":[1,1,1]},"r":1,"o":{"a":0,"k":100}},{"ty":"tr","nm":"Transform","a":{"a":0,"k":[0,0]},"o":{"a":0,"k":100},"p":{"a":0,"k":[0,0]},"r":{"a":0,"k":0},"s":{"a":0,"k":[100,100]},"sk":{"a":0,"k":0},"sa":{"a":0,"k":0}}],"np":0}]}],"meta":{"g":"@phase-software/lottie-exporter 0.7.0"},"nm":"","op":120,"v":"5.6.0","w":375}