{"assets":[{"id":"el-632-HUml","layers":[{"ddd":0,"ind":1,"ty":4,"nm":"Layer 1","hd":false,"sr":1,"ks":{"a":{"a":0,"k":[226,10.5]},"o":{"a":0,"k":100},"p":{"a":0,"k":[226,10.5]},"r":{"a":0,"k":0},"s":{"a":0,"k":[100,100]},"sk":{"a":0,"k":0},"sa":{"a":0,"k":0}},"ao":0,"ip":0,"op":121,"st":0,"bm":0,"shapes":[{"ty":"gr","hd":false,"nm":"Path 1 Group","bm":0,"it":[{"ty":"sh","hd":false,"nm":"Path 1","d":1,"ks":{"a":0,"k":{"c":false,"i":[[0,0],[0,0],[0,0]],"o":[[0,0],[0,0],[0,0]],"v":[[223.5,5.5],[228.5,10.5],[223.5,15.5]]}}},{"ty":"st","hd":false,"bm":0,"c":{"a":0,"k":[0.243,0.247,0.271]},"lc":2,"lj":2,"ml":4,"o":{"a":0,"k":100},"w":{"a":0,"k":1.511}},{"ty":"tr","nm":"Transform","a":{"a":0,"k":[0,0]},"o":{"a":0,"k":100},"p":{"a":0,"k":[0,0]},"r":{"a":0,"k":0},"s":{"a":0,"k":[100,100]},"sk":{"a":0,"k":0},"sa":{"a":0,"k":0}}],"np":0}]},{"ddd":0,"ind":3,"ty":4,"nm":"Layer 2","hd":false,"sr":1,"ks":{"a":{"a":0,"k":[108.259,10.689]},"o":{"a":0,"k":100},"p":{"a":0,"k":[108.259,10.689]},"r":{"a":0,"k":0},"s":{"a":0,"k":[100,100]},"sk":{"a":0,"k":0},"sa":{"a":0,"k":0}},"ao":0,"ip":0,"op":121,"st":0,"bm":0,"shapes":[{"ty":"gr","hd":false,"nm":"Path 1 (44) Group","bm":0,"it":[{"ty":"sh","hd":false,"nm":"Path 1 (44)","d":1,"ks":{"a":0,"k":{"c":true,"i":[[0,0],[0,0],[0,0],[0,0],[-0.58,0.06],[0,0],[2.314,-0.008],[0,0],[-0.527,0],[0,0],[0,0],[0,0]],"o":[[0,0],[0,0],[0,0],[0.582,-0.043],[0,0],[-2.688,0.41],[0,0],[0.476,0],[0,0],[0,0],[0,0],[0,0]],"v":[[8.203,5.058],[8.203,6.39],[7.017,6.39],[7.017,10.015],[8.76,9.861],[8.862,11.062],[0.835,11.532],[0.659,10.184],[2.168,10.176],[2.168,6.391],[1.011,6.391],[1.011,5.058]]}}},{"ty":"sh","hd":false,"nm":"Path 1 (44)","d":1,"ks":{"a":0,"k":{"c":true,"i":[[0,0],[0,0],[0,0],[0,0],[0,0],[0,0]],"o":[[0,0],[0,0],[0,0],[0,0],[0,0],[0,0]],"v":[[2.432,14.023],[2.432,12.704],[11.47,12.704],[11.47,17.304],[9.83,17.304],[9.83,14.023]]}}},{"ty":"sh","hd":false,"nm":"Path 1 (44)","d":1,"ks":{"a":0,"k":{"c":true,"i":[[0,0],[-0.579,0.021],[0,0],[0,0]],"o":[[0.572,-0.007],[0,0],[0,0],[0,0]],"v":[[3.735,10.148],[5.464,10.097],[5.464,6.39],[3.735,6.39]]}}},{"ty":"sh","hd":false,"nm":"Path 1 (44)","d":1,"ks":{"a":0,"k":{"c":true,"i":[[0,0],[0,0],[0,0],[0,0]],"o":[[0,0],[0,0],[0,0],[0,0]],"v":[[9.829,12.148],[9.829,4.062],[11.469,4.062],[11.469,12.148]]}}},{"ty":"sh","hd":false,"nm":"Path 1 (44)","d":1,"ks":{"a":0,"k":{"c":true,"i":[[0,0],[0,0],[0,0],[0,0],[0,0],[0,0],[0,0],[0,0],[0,0],[0,0],[0,0],[0,0]],"o":[[0,0],[0,0],[0,0],[0,0],[0,0],[0,0],[0,0],[0,0],[0,0],[0,0],[0,0],[0,0]],"v":[[24.36,4.442],[24.36,5.672],[22.544,5.672],[22.544,7.68],[24.287,7.68],[24.287,8.91],[14.561,8.91],[14.561,7.68],[16.304,7.68],[16.304,5.673],[14.487,5.673],[14.487,4.443]]}}},{"ty":"sh","hd":false,"nm":"Path 1 (44)","d":1,"ks":{"a":0,"k":{"c":true,"i":[[0,0],[0,0],[0,0],[0,0]],"o":[[0,0],[0,0],[0,0],[0,0]],"v":[[13.403,11.034],[13.403,9.745],[25.473,9.745],[25.473,11.035]]}}},{"ty":"sh","hd":false,"nm":"Path 1 (44)","d":1,"ks":{"a":0,"k":{"c":true,"i":[[0,0],[0,0],[0,0],[0,0],[0,0],[0,0],[0,0],[0,0],[0,0],[0,0],[0,0],[0,0]],"o":[[0,0],[0,0],[0,0],[0,0],[0,0],[0,0],[0,0],[0,0],[0,0],[0,0],[0,0],[0,0]],"v":[[14.824,13.114],[14.824,11.928],[23.964,11.928],[23.964,15.078],[16.436,15.078],[16.436,15.971],[24.331,15.971],[24.331,17.186],[14.84,17.186],[14.84,13.95],[22.37,13.95],[22.37,13.115]]}}},{"ty":"sh","hd":false,"nm":"Path 1 (44)","d":1,"ks":{"a":0,"k":{"c":true,"i":[[0,0],[0,0],[0,0],[0,0]],"o":[[0,0],[0,0],[0,0],[0,0]],"v":[[17.93,7.68],[20.903,7.68],[20.903,5.673],[17.93,5.673]]}}},{"ty":"sh","hd":false,"nm":"Path 1 (44)","d":1,"ks":{"a":0,"k":{"c":true,"i":[[0,0],[0,0],[0,0],[0,0]],"o":[[0,0],[0,0],[0,0],[0,0]],"v":[[37.383,4.062],[37.383,17.318],[35.743,17.318],[35.743,4.062]]}}},{"ty":"sh","hd":false,"nm":"Path 1 (44)","d":1,"ks":{"a":0,"k":{"c":false,"i":[[0,0],[-2.007,0],[-0.007,-2.856],[1.985,0],[-0.007,2.878]],"o":[[-0.007,-2.857],[1.985,0],[-0.007,2.879],[-2.007,0],[0,0]],"v":[[26.792,9.702],[30.249,5.028],[33.706,9.701],[30.249,14.389],[26.792,9.701]]}}},{"ty":"sh","hd":false,"nm":"Path 1 (44)","d":1,"ks":{"a":0,"k":{"c":false,"i":[[0,0],[-1.12,-0.008],[0,2.036],[1.113,0],[0,-2.021]],"o":[[0,2.035],[1.113,-0.008],[0,-2.021],[-1.12,0],[0,0]],"v":[[28.359,9.701],[30.249,12.923],[32.124,9.7],[30.249,6.492],[28.359,9.7]]}}},{"ty":"sh","hd":false,"nm":"Path 1 (44)","d":1,"ks":{"a":0,"k":{"c":true,"i":[[0,0],[0,0],[0,0],[-0.007,-2.036],[2.446,0],[0,0],[0,0]],"o":[[0,0],[0,0],[2.432,0],[-0.007,2.029],[0,0],[0,0],[0,0]],"v":[[43.433,16],[43.433,5.395],[47.417,5.395],[51.152,8.91],[47.388,12.411],[45.337,12.411],[45.337,16]]}}},{"ty":"sh","hd":false,"nm":"Path 1 (44)","d":1,"ks":{"a":0,"k":{"c":true,"i":[[0,0],[0,0],[0,1.121],[1.436,0],[0,0]],"o":[[0,0],[1.436,-0.008],[0,-1.135],[0,0],[0,0]],"v":[[45.337,10.844],[47.124,10.844],[49.204,8.91],[47.124,6.991],[45.337,6.991]]}}},{"ty":"sh","hd":false,"nm":"Path 1 (44)","d":1,"ks":{"a":0,"k":{"c":true,"i":[[0,0],[0,0],[0,0],[0,0]],"o":[[0,0],[0,0],[0,0],[0,0]],"v":[[54.595,5.394],[54.595,16],[52.69,16],[52.69,5.395]]}}},{"ty":"sh","hd":false,"nm":"Path 1 (44)","d":1,"ks":{"a":0,"k":{"c":true,"i":[[0,0],[1.289,0],[-0.007,-2.402],[-1.729,0],[-0.257,1.246],[0,0],[2.513,0],[-0.008,3.421],[-2.776,0],[-0.33,-2.358]],"o":[[-0.227,-1.275],[-1.736,0],[-0.007,2.44],[1.26,0],[0,0],[-0.293,2.037],[-2.798,0],[-0.008,-3.427],[2.344,0],[0,0]],"v":[[63.72,8.97],[61.186,6.963],[58.226,10.698],[61.186,14.434],[63.72,12.485],[65.639,12.485],[61.156,16.147],[56.308,10.698],[61.156,5.249],[65.639,8.969]]}}},{"ty":"sh","hd":false,"nm":"Path 1 (44)","d":1,"ks":{"a":0,"k":{"c":true,"i":[[0,0],[0,0],[0,0],[0,0],[0,0],[0,0],[0,0],[0,0],[0,0],[0,0],[0,0],[0,0],[0,0]],"o":[[0,0],[0,0],[0,0],[0,0],[0,0],[0,0],[0,0],[0,0],[0,0],[0,0],[0,0],[0,0],[0,0]],"v":[[67.28,16],[67.28,5.395],[69.184,5.395],[69.184,10.273],[69.33,10.273],[73.476,5.395],[75.805,5.395],[71.703,10.155],[75.85,16],[73.55,16],[70.371,11.444],[69.185,12.836],[69.185,16]]}}},{"ty":"sh","hd":false,"nm":"Path 1 (44)","d":1,"ks":{"a":0,"k":{"c":true,"i":[[0,0],[0,0],[0,0],[0,0]],"o":[[0,0],[0,0],[0,0],[0,0]],"v":[[79.203,5.395],[79.042,12.88],[77.387,12.88],[77.211,5.395]]}}},{"ty":"sh","hd":false,"nm":"Path 1 (44)","d":1,"ks":{"a":0,"k":{"c":false,"i":[[0,0],[-0.63,0.007],[0,-0.616],[0.608,0],[-0.001,0.632]],"o":[[-0.007,-0.616],[0.608,0.007],[0,0.63],[-0.632,0.002],[0,0]],"v":[[77.079,14.975],[78.222,13.847],[79.35,14.975],[78.222,16.117],[77.079,14.975]]}}},{"ty":"sh","hd":false,"nm":"Path 1 (44)","d":1,"ks":{"a":0,"k":{"c":true,"i":[[0,0],[0,0],[0,0],[0,0],[0,0],[0,0],[0,0],[0,0]],"o":[[0,0],[0,0],[0,0],[0,0],[0,0],[0,0],[0,0],[0,0]],"v":[[91.274,4.076],[91.274,8.236],[93.12,8.236],[93.12,9.584],[91.274,9.584],[91.274,13.964],[89.648,13.964],[89.648,4.076]]}}},{"ty":"sh","hd":false,"nm":"Path 1 (44)","d":1,"ks":{"a":0,"k":{"c":true,"i":[[0,0],[0,0],[0,0],[0,0],[0,0],[0,0],[0,0],[0,0]],"o":[[0,0],[0,0],[0,0],[0,0],[0,0],[0,0],[0,0],[0,0]],"v":[[80.844,6.845],[80.844,5.54],[83.964,5.54],[83.964,4.06],[85.591,4.06],[85.591,5.54],[88.696,5.54],[88.696,6.844]]}}},{"ty":"sh","hd":false,"nm":"Path 1 (44)","d":1,"ks":{"a":0,"k":{"c":false,"i":[[0,0],[-1.926,0],[-0.008,-1.524],[1.911,0],[0,1.516]],"o":[[0,-1.524],[1.912,0],[-0.007,1.516],[-1.927,0],[0,0]],"v":[[81.519,9.921],[84.77,7.387],[88.008,9.921],[84.771,12.426],[81.519,9.921]]}}},{"ty":"sh","hd":false,"nm":"Path 1 (44)","d":1,"ks":{"a":0,"k":{"c":true,"i":[[0,0],[0,0],[0,0],[0,0],[0,0],[0,0]],"o":[[0,0],[0,0],[0,0],[0,0],[0,0],[0,0]],"v":[[82.793,17.04],[82.793,13.188],[84.419,13.188],[84.419,15.722],[91.802,15.722],[91.802,17.04]]}}},{"ty":"sh","hd":false,"nm":"Path 1 (44)","d":1,"ks":{"a":0,"k":{"c":false,"i":[[0,0],[-1.004,0.007],[0,0.798],[1.003,0],[-0.008,-0.805]],"o":[[-0.008,0.8],[1.003,0.007],[0,-0.806],[-1.004,0],[0,0]],"v":[[83.101,9.92],[84.771,11.166],[86.455,9.921],[84.771,8.646],[83.101,9.921]]}}},{"ty":"sh","hd":false,"nm":"Path 1 (44)","d":1,"ks":{"a":0,"k":{"c":false,"i":[[0,0],[-0.008,3.472],[-2.542,0],[0,-3.458],[2.549,0]],"o":[[-2.556,0],[-0.008,-3.457],[2.542,0],[0,3.478],[0,0]],"v":[[101.704,16.148],[97.632,10.698],[101.704,5.249],[105.776,10.699],[101.704,16.147]]}}},{"ty":"sh","hd":false,"nm":"Path 1 (44)","d":1,"ks":{"a":0,"k":{"c":false,"i":[[0,0],[-1.333,-0.007],[0,2.549],[1.326,0.007],[0.007,-2.527]],"o":[[0,2.55],[1.326,-0.008],[-0.007,-2.527],[-1.326,0.007],[0,0]],"v":[[99.551,10.697],[101.704,14.55],[103.857,10.697],[101.704,6.83],[99.551,10.697]]}}},{"ty":"sh","hd":false,"nm":"Path 1 (44)","d":1,"ks":{"a":0,"k":{"c":true,"i":[[0,0],[0,0],[0,0],[0,0],[0,0],[0,0],[0,0],[0,0]],"o":[[0,0],[0,0],[0,0],[0,0],[0,0],[0,0],[0,0],[0,0]],"v":[[118.037,4.077],[118.037,14.096],[116.396,14.096],[116.396,12.938],[113.804,12.938],[113.804,11.796],[116.396,11.796],[116.396,4.076]]}}},{"ty":"sh","hd":false,"nm":"Path 1 (44)","d":1,"ks":{"a":0,"k":{"c":true,"i":[[0,0],[-2.812,0.359],[0,0],[1.121,-0.08],[0,0],[0,0],[0,0],[1.153,0.005]],"o":[[2.439,-0.014],[0,0],[-1.091,0.183],[0,0],[0,0],[0,0],[-1.152,0.043],[0,0]],"v":[[106.875,10.023],[115.415,9.628],[115.503,10.8],[112.163,11.18],[112.163,13.73],[110.537,13.73],[110.537,11.269],[107.08,11.327]]}}},{"ty":"sh","hd":false,"nm":"Path 1 (44)","d":1,"ks":{"a":0,"k":{"c":false,"i":[[0,0],[-1.963,-0.007],[-0.014,-1.399],[1.927,-0.008],[0,1.421]],"o":[[0,-1.399],[1.927,-0.008],[-0.014,1.421],[-1.963,-0.008],[0,0]],"v":[[107.886,6.903],[111.196,4.56],[114.492,6.903],[111.196,9.233],[107.886,6.903]]}}},{"ty":"sh","hd":false,"nm":"Path 1 (44)","d":1,"ks":{"a":0,"k":{"c":true,"i":[[0,0],[0,0],[0,0],[0,0],[0,0],[0,0]],"o":[[0,0],[0,0],[0,0],[0,0],[0,0],[0,0]],"v":[[108.633,17.04],[108.633,13.129],[110.259,13.129],[110.259,15.722],[118.345,15.722],[118.345,17.04]]}}},{"ty":"sh","hd":false,"nm":"Path 1 (44)","d":1,"ks":{"a":0,"k":{"c":false,"i":[[0,0],[-1.062,-0.007],[-0.007,0.718],[1.011,-0.008],[0,-0.717]],"o":[[0,0.718],[1.011,-0.007],[-0.007,-0.717],[-1.062,-0.008],[0,0]],"v":[[109.424,6.903],[111.196,8.046],[112.939,6.903],[111.196,5.761],[109.424,6.903]]}}},{"ty":"sh","hd":false,"nm":"Path 1 (44)","d":1,"ks":{"a":0,"k":{"c":true,"i":[[0,0],[0,0],[0.285,-1.413],[0,0],[0,0],[0,0],[0,0],[0,0],[-0.044,0.41],[0,0],[0,0],[0,0],[0,0.307],[0,0],[0,0]],"o":[[0,0],[0.007,1.032],[0,0],[0,0],[0,0],[0,0],[0,0],[0.088,-0.468],[0,0],[0,0],[0,0],[0.014,-0.322],[0,0],[0,0],[0,0]],"v":[[134.077,4.603],[134.077,5.703],[133.799,9.276],[135.498,9.276],[135.498,10.58],[123.486,10.58],[123.486,9.276],[132.18,9.276],[132.371,7.966],[124.805,8.28],[124.614,7.02],[132.437,6.83],[132.451,5.893],[124.951,5.893],[124.951,4.603]]}}},{"ty":"sh","hd":false,"nm":"Path 1 (44)","d":1,"ks":{"a":0,"k":{"c":true,"i":[[0,0],[0,0],[0,0],[0,0],[0,0],[0,0],[0,0],[0,0],[0,0],[0,0],[0,0],[0,0]],"o":[[0,0],[0,0],[0,0],[0,0],[0,0],[0,0],[0,0],[0,0],[0,0],[0,0],[0,0],[0,0]],"v":[[124.819,12.777],[124.819,11.532],[134.15,11.532],[134.15,14.872],[126.46,14.872],[126.46,15.868],[134.619,15.868],[134.619,17.143],[124.849,17.143],[124.849,13.685],[132.524,13.685],[132.524,12.777]]}}},{"ty":"sh","hd":false,"nm":"Path 1 (44)","d":1,"ks":{"a":0,"k":{"c":true,"i":[[0,0],[0,0],[0,0],[0,0],[-1.479,0.242],[0,0],[1.64,-0.007],[0,0],[0,0],[0,0],[0,0],[0,0],[0,0]],"o":[[0,0],[0,0],[0,0],[1.34,-0.015],[0,0],[-1.788,0.3],[0,0],[0,0],[0,0],[0,0],[0,0],[0,0],[0,0]],"v":[[141.812,5.409],[141.812,10.346],[138.384,10.346],[138.384,12.924],[142.485,12.616],[142.603,13.935],[137.725,14.286],[136.816,14.286],[136.816,9.027],[140.244,9.027],[140.244,6.727],[136.802,6.727],[136.802,5.41]]}}},{"ty":"sh","hd":false,"nm":"Path 1 (44)","d":1,"ks":{"a":0,"k":{"c":true,"i":[[0,0],[0,0],[0,0],[0,0],[0,0],[0,0],[0,0],[0,0],[0,0],[0,0],[0,0],[0,0]],"o":[[0,0],[0,0],[0,0],[0,0],[0,0],[0,0],[0,0],[0,0],[0,0],[0,0],[0,0],[0,0]],"v":[[143.276,16.629],[143.276,4.312],[144.771,4.312],[144.771,9.146],[146.265,9.146],[146.265,4.062],[147.817,4.062],[147.817,17.304],[146.265,17.304],[146.265,10.463],[144.771,10.463],[144.771,16.63]]}}},{"ty":"sh","hd":false,"nm":"Path 1 (44)","d":1,"ks":{"a":0,"k":{"c":true,"i":[[0,0],[-2.776,-0.484],[0,0],[0.864,1.78],[2.212,-0.47],[0,0],[-0.007,2.036],[0,0],[0,0]],"o":[[0,2.043],[0,0],[-2.22,-0.461],[-0.872,1.765],[0,0],[2.732,-0.498],[0,0],[0,0],[0,0]],"v":[[156.226,5.878],[161.001,10.463],[160.269,11.825],[155.369,8.236],[150.469,11.826],[149.751,10.463],[154.497,5.878],[154.497,4.896],[156.226,4.896]]}}},{"ty":"sh","hd":false,"nm":"Path 1 (44)","d":1,"ks":{"a":0,"k":{"c":true,"i":[[0,0],[0,0],[0,0],[0,0]],"o":[[0,0],[0,0],[0,0],[0,0]],"v":[[149.385,15.619],[149.385,14.271],[161.484,14.271],[161.484,15.619]]}}},{"ty":"sh","hd":false,"nm":"Path 1 (44)","d":1,"ks":{"a":0,"k":{"c":true,"i":[[0,0],[0,0],[0,0],[0,0],[0,0],[0,0],[0,0],[0,0],[0,0],[0,0],[0,0],[0,0],[0,0],[0,0],[0,0],[0,0]],"o":[[0,0],[0,0],[0,0],[0,0],[0,0],[0,0],[0,0],[0,0],[0,0],[0,0],[0,0],[0,0],[0,0],[0,0],[0,0],[0,0]],"v":[[178.008,14.374],[178.008,15.707],[165.908,15.707],[165.908,14.374],[171.123,14.374],[171.123,11.796],[167.241,11.796],[167.241,4.94],[168.867,4.94],[168.867,7.108],[175.005,7.108],[175.005,4.94],[176.631,4.94],[176.631,11.796],[172.734,11.796],[172.734,14.374]]}}},{"ty":"sh","hd":false,"nm":"Path 1 (44)","d":1,"ks":{"a":0,"k":{"c":true,"i":[[0,0],[0,0],[0,0],[0,0]],"o":[[0,0],[0,0],[0,0],[0,0]],"v":[[168.867,10.477],[175.005,10.477],[175.005,8.413],[168.867,8.413]]}}},{"ty":"sh","hd":false,"nm":"Path 1 (44)","d":1,"ks":{"a":0,"k":{"c":true,"i":[[0,0],[0,0],[0,0],[0,0],[0,0],[0,0],[0,0],[0,0]],"o":[[0,0],[0,0],[0,0],[0,0],[0,0],[0,0],[0,0],[0,0]],"v":[[189.961,4.062],[189.961,17.318],[188.335,17.318],[188.335,10.272],[186.064,10.272],[186.064,8.94],[188.335,8.94],[188.335,4.062]]}}},{"ty":"sh","hd":false,"nm":"Path 1 (44)","d":1,"ks":{"a":0,"k":{"c":true,"i":[[0,0],[0,0],[0,0],[0,0],[0,0],[0,0],[-1.78,0.322],[0,0],[2.278,-0.007],[0,0],[0,0],[0,0],[0,0]],"o":[[0,0],[0,0],[0,0],[0,0],[0,0],[1.97,-0.008],[0,0],[-1.971,0.344],[0,0],[0,0],[0,0],[0,0],[0,0]],"v":[[179.312,6.537],[179.312,5.22],[185.303,5.22],[185.303,10.068],[180.967,10.068],[180.967,12.852],[186.299,12.456],[186.431,13.789],[180.41,14.214],[179.355,14.214],[179.355,8.749],[183.706,8.749],[183.706,6.537]]}}},{"ty":"sh","hd":false,"nm":"Path 1 (44)","d":1,"ks":{"a":0,"k":{"c":true,"i":[[0,0],[0,0],[0,0],[0,0],[0,0],[0,0],[0,0],[0,0]],"o":[[0,0],[0,0],[0,0],[0,0],[0,0],[0,0],[0,0],[0,0]],"v":[[202.207,4.062],[202.207,9.232],[204.17,9.232],[204.17,10.595],[202.207,10.595],[202.207,17.275],[200.581,17.275],[200.581,4.061]]}}},{"ty":"sh","hd":false,"nm":"Path 1 (44)","d":1,"ks":{"a":0,"k":{"c":true,"i":[[0,0],[-0.322,3.018],[0,0],[0,0],[0,0],[4.401,-2.168]],"o":[[3.222,-1.611],[0,0],[0,0],[0,0],[-0.007,3.89],[0,0]],"v":[[191.763,13.656],[197.051,6.786],[192.48,6.786],[192.48,5.438],[198.706,5.438],[192.686,14.916]]}}},{"ty":"sh","hd":false,"nm":"Path 1 (44)","d":1,"ks":{"a":0,"k":{"c":true,"i":[[0,0],[0,0],[0,0],[0,0]],"o":[[0,0],[0,0],[0,0],[0,0]],"v":[[215.859,4.062],[215.859,17.304],[214.219,17.304],[214.219,4.062]]}}},{"ty":"sh","hd":false,"nm":"Path 1 (44)","d":1,"ks":{"a":0,"k":{"c":true,"i":[[0,0],[-0.293,3.011],[0,0],[0,0],[0,0],[4.637,-2.205]],"o":[[3.471,-1.648],[0,0],[0,0],[0,0],[0,3.94],[0,0]],"v":[[204.888,13.656],[210.249,6.756],[205.562,6.756],[205.562,5.469],[211.904,5.469],[205.737,14.961]]}}},{"ty":"fl","hd":false,"bm":0,"c":{"a":0,"k":[0.243,0.247,0.271]},"r":1,"o":{"a":0,"k":100}},{"ty":"tr","nm":"Transform","a":{"a":0,"k":[0,0]},"o":{"a":0,"k":100},"p":{"a":0,"k":[0,0]},"r":{"a":0,"k":0},"s":{"a":0,"k":[100,100]},"sk":{"a":0,"k":0},"sa":{"a":0,"k":0}}],"np":0}]}]},{"id":"el-616-HUml","layers":[{"ddd":0,"ind":6,"ty":4,"nm":"Layer 1","hd":false,"sr":1,"ks":{"a":{"a":0,"k":[124.298,26.383]},"o":{"a":0,"k":100},"p":{"a":0,"k":[124.298,26.383]},"r":{"a":0,"k":0},"s":{"a":0,"k":[100,100]},"sk":{"a":0,"k":0},"sa":{"a":0,"k":0}},"ao":0,"ip":0,"op":121,"st":0,"bm":0,"shapes":[{"ty":"gr","hd":false,"nm":"Path 1 (10) Group","bm":0,"it":[{"ty":"sh","hd":false,"nm":"Path 1 (10)","d":1,"ks":{"a":0,"k":{"c":true,"i":[[0,0],[0,0],[0,0],[0,0],[0,0],[0,0],[0,0],[0,0]],"o":[[0,0],[0,0],[0,0],[0,0],[0,0],[0,0],[0,0],[0,0]],"v":[[7.928,34.445],[7.928,50],[4.684,50],[4.684,37.518],[4.598,37.518],[1.03,39.752],[1.03,36.894],[4.876,34.445]]}}},{"ty":"sh","hd":false,"nm":"Path 1 (10)","d":1,"ks":{"a":0,"k":{"c":false,"i":[[0,0],[0,5.092],[-3.878,0],[0,-5.082],[3.889,0]],"o":[[-3.9,0],[0,-5.081],[3.878,0],[0,5.113],[0,0]],"v":[[17.574,50.215],[11.322,42.223],[17.574,34.231],[23.826,42.223],[17.574,50.215]]}}},{"ty":"sh","hd":false,"nm":"Path 1 (10)","d":1,"ks":{"a":0,"k":{"c":false,"i":[[0,0],[-1.804,0],[0.01,3.588],[1.794,0.01],[0,-3.556]],"o":[[-0.022,3.587],[1.804,0],[0.01,-3.556],[-1.794,0.01],[0,0]],"v":[[14.631,42.223],[17.574,47.551],[20.518,42.223],[17.574,36.873],[14.631,42.223]]}}},{"ty":"sh","hd":false,"nm":"Path 1 (10)","d":1,"ks":{"a":0,"k":{"c":true,"i":[[0,0],[0,0],[0,0],[0,0]],"o":[[0,0],[0,0],[0,0],[0,0]],"v":[[32.807,33.715],[27.779,52.342],[25.051,52.342],[30.057,33.715]]}}},{"ty":"sh","hd":false,"nm":"Path 1 (10)","d":1,"ks":{"a":0,"k":{"c":true,"i":[[0,0],[0,0],[0,0],[0,0],[0,0],[0,0],[0,0],[0,0]],"o":[[0,0],[0,0],[0,0],[0,0],[0,0],[0,0],[0,0],[0,0]],"v":[[40.927,34.445],[40.927,50],[37.684,50],[37.684,37.518],[37.598,37.518],[34.031,39.752],[34.031,36.894],[37.877,34.445]]}}},{"ty":"sh","hd":false,"nm":"Path 1 (10)","d":1,"ks":{"a":0,"k":{"c":true,"i":[[0,0],[-1.01,0.011],[-1.772,0],[-0.71,0.784],[0,0],[1.01,0],[1.762,0.011],[0.71,-0.774]],"o":[[0.731,-0.773],[1.761,0.01],[0.999,0],[0,0],[-0.73,0.774],[-1.761,0],[-0.999,0.01],[0,0]],"v":[[45.353,43.103],[48.018,41.922],[53.045,43.147],[55.645,41.965],[55.645,44.585],[52.98,45.768],[47.953,44.543],[45.353,45.725]]}}},{"ty":"sh","hd":false,"nm":"Path 1 (10)","d":1,"ks":{"a":0,"k":{"c":true,"i":[[0,0],[0,0],[0,0],[0,0],[0,0],[0,0],[0,0],[0,0]],"o":[[0,0],[0,0],[0,0],[0,0],[0,0],[0,0],[0,0],[0,0]],"v":[[65.613,34.445],[65.613,50],[62.37,50],[62.37,37.518],[62.284,37.518],[58.718,39.752],[58.718,36.894],[62.564,34.445]]}}},{"ty":"sh","hd":false,"nm":"Path 1 (10)","d":1,"ks":{"a":0,"k":{"c":true,"i":[[0,0],[0,0],[0,0],[0,0],[0,0],[0,0],[0,0],[0,0]],"o":[[0,0],[0,0],[0,0],[0,0],[0,0],[0,0],[0,0],[0,0]],"v":[[75.926,34.445],[75.926,50],[72.682,50],[72.682,37.518],[72.596,37.518],[69.029,39.752],[69.029,36.894],[72.875,34.445]]}}},{"ty":"sh","hd":false,"nm":"Path 1 (10)","d":1,"ks":{"a":0,"k":{"c":true,"i":[[0,0],[0,0],[0,0],[0,0]],"o":[[0,0],[0,0],[0,0],[0,0]],"v":[[86.281,33.715],[81.254,52.342],[78.525,52.342],[83.531,33.715]]}}},{"ty":"sh","hd":false,"nm":"Path 1 (10)","d":1,"ks":{"a":0,"k":{"c":false,"i":[[0,0],[0.065,2.718],[0,0],[-1.503,-0.011],[0.011,1.257],[1.826,0.01],[0,0],[0,0],[0,0],[0.01,1.224],[1.375,-0.012],[0.054,-1.193],[0,0],[-3.19,0],[0.01,-2.46],[1.74,-0.311],[0,0],[0.021,-1.945],[3.513,0]],"o":[[-3.416,0],[0,0],[0.054,1.16],[1.547,-0.011],[0.01,-1.268],[0,0],[0,0],[0,0],[1.536,0],[0.01,-1.193],[-1.375,-0.011],[0,0],[0.053,-2.675],[3.244,0],[0.01,1.74],[0,0],[2.288,0.279],[0.021,2.664],[0,0]],"v":[[93.457,50.215],[87.527,45.617],[90.793,45.617],[93.478,47.551],[96.121,45.424],[93.178,43.254],[91.738,43.254],[91.738,40.869],[93.178,40.869],[95.778,38.807],[93.5,36.809],[90.943,38.764],[87.85,38.764],[93.5,34.23],[98.893,38.613],[95.949,41.9],[95.949,42.03],[99.473,45.639],[93.457,50.215]]}}},{"ty":"fl","hd":false,"bm":0,"c":{"a":0,"k":[0.329,0.318,1]},"r":1,"o":{"a":0,"k":100}},{"ty":"tr","nm":"Transform","a":{"a":0,"k":[0,0]},"o":{"a":0,"k":100},"p":{"a":0,"k":[0,0]},"r":{"a":0,"k":0},"s":{"a":0,"k":[100,100]},"sk":{"a":0,"k":0},"sa":{"a":0,"k":0}}],"np":0},{"ty":"gr","hd":false,"nm":"Path 1 (47) Group","bm":0,"it":[{"ty":"sh","hd":false,"nm":"Path 1 (47)","d":1,"ks":{"a":0,"k":{"c":true,"i":[[0,0],[-3.255,-1.408],[0,0],[0.817,2.417],[2.234,-1.096],[0,0],[-0.022,3.673],[0,0],[0,0]],"o":[[0.011,3.673],[0,0],[-2.17,-1.053],[-0.838,2.568],[0,0],[3.352,-1.514],[0,0],[0,0],[0,0]],"v":[[7.97,4.852],[12.719,13.51],[11.043,15.7],[6.596,10.275],[2.02,16.044],[0.3,13.81],[5.2,4.852],[5.2,1.93],[7.97,1.93]]}}},{"ty":"sh","hd":false,"nm":"Path 1 (47)","d":1,"ks":{"a":0,"k":{"c":true,"i":[[0,0],[0,0],[0,0],[0,0],[0,0],[0,0],[0,0],[0,0]],"o":[[0,0],[0,0],[0,0],[0,0],[0,0],[0,0],[0,0],[0,0]],"v":[[10.527,8.783],[10.527,6.57],[14.373,6.57],[14.373,0.426],[17.08,0.426],[17.08,20.02],[14.373,20.02],[14.373,8.783]]}}},{"ty":"sh","hd":false,"nm":"Path 1 (47)","d":1,"ks":{"a":0,"k":{"c":true,"i":[[0,0],[0,0],[0,0],[0,0]],"o":[[0,0],[0,0],[0,0],[0,0]],"v":[[35.965,0.426],[35.965,20.02],[33.193,20.02],[33.193,0.425]]}}},{"ty":"sh","hd":false,"nm":"Path 1 (47)","d":1,"ks":{"a":0,"k":{"c":true,"i":[[0,0],[0,0],[0,0],[0,0],[0,0],[0,0],[0,0],[0,0]],"o":[[0,0],[0,0],[0,0],[0,0],[0,0],[0,0],[0,0],[0,0]],"v":[[20.56,15.443],[20.56,1.973],[23.31,1.973],[23.31,6.743],[27.522,6.743],[27.522,1.973],[30.229,1.973],[30.229,15.443]]}}},{"ty":"sh","hd":false,"nm":"Path 1 (47)","d":1,"ks":{"a":0,"k":{"c":true,"i":[[0,0],[0,0],[0,0],[0,0]],"o":[[0,0],[0,0],[0,0],[0,0]],"v":[[23.31,13.23],[27.522,13.23],[27.522,8.87],[23.31,8.87]]}}},{"ty":"sh","hd":false,"nm":"Path 1 (47)","d":1,"ks":{"a":0,"k":{"c":true,"i":[[0,0],[-4.425,-0.752],[0,0],[1.268,2.503],[3.384,-0.688],[0,0],[-0.022,2.836],[0,0],[0,0]],"o":[[-0.01,2.868],[0,0],[-3.416,-0.677],[-1.289,2.482],[0,0],[4.35,-0.774],[0,0],[0,0],[0,0]],"v":[[48.899,3.004],[55.86,9.686],[54.657,11.963],[47.449,6.86],[40.241,11.963],[39.06,9.686],[45.978,3.004],[45.978,1.586],[48.899,1.586]]}}},{"ty":"sh","hd":false,"nm":"Path 1 (47)","d":1,"ks":{"a":0,"k":{"c":true,"i":[[0,0],[0,0],[0,0],[0,0]],"o":[[0,0],[0,0],[0,0],[0,0]],"v":[[38.608,17.57],[38.608,15.315],[56.504,15.315],[56.504,17.57]]}}},{"ty":"sh","hd":false,"nm":"Path 1 (47)","d":1,"ks":{"a":0,"k":{"c":true,"i":[[0,0],[0,0],[0,0],[0,0],[0,0],[0,0],[0,0],[0,0],[0,0],[0,0],[0,0],[0,0],[0,0],[0,0],[0,0],[0,0]],"o":[[0,0],[0,0],[0,0],[0,0],[0,0],[0,0],[0,0],[0,0],[0,0],[0,0],[0,0],[0,0],[0,0],[0,0],[0,0],[0,0]],"v":[[65.828,2.188],[65.828,6.72],[68.535,6.72],[68.535,2.188],[71.027,2.188],[71.027,7.558],[72.982,7.558],[72.982,0.749],[75.561,0.749],[75.561,19.119],[72.982,19.119],[72.982,9.792],[71.027,9.792],[71.027,15.335],[63.25,15.335],[63.25,2.188]]}}},{"ty":"sh","hd":false,"nm":"Path 1 (47)","d":1,"ks":{"a":0,"k":{"c":true,"i":[[0,0],[0,0],[0,0],[0,0]],"o":[[0,0],[0,0],[0,0],[0,0]],"v":[[65.828,13.102],[68.535,13.102],[68.535,8.89],[65.828,8.89]]}}},{"ty":"sh","hd":false,"nm":"Path 1 (47)","d":1,"ks":{"a":0,"k":{"c":true,"i":[[0,0],[0,0],[0,0],[0,0]],"o":[[0,0],[0,0],[0,0],[0,0]],"v":[[77.022,19.977],[77.022,0.426],[79.642,0.426],[79.642,19.976]]}}},{"ty":"sh","hd":false,"nm":"Path 1 (47)","d":1,"ks":{"a":0,"k":{"c":true,"i":[[0,0],[0,0],[0,0],[0,0],[0,0],[0,0],[0,0],[0,0],[-2.61,0.409],[0,0],[3.416,0],[0,0],[0,0]],"o":[[0,0],[0,0],[0,0],[0,0],[0,0],[0,0],[0,0],[2.793,-0.032],[0,0],[-2.986,0.451],[0,0],[0,0],[0,0]],"v":[[91.738,2.037],[91.738,4.271],[85.25,4.271],[85.25,7.494],[91.459,7.494],[91.459,9.643],[85.25,9.643],[85.25,13.338],[92.941,12.779],[93.199,14.992],[84.133,15.529],[82.479,15.529],[82.479,2.037]]}}},{"ty":"sh","hd":false,"nm":"Path 1 (47)","d":1,"ks":{"a":0,"k":{"c":true,"i":[[0,0],[0,0],[0,0],[0,0],[0,0],[0,0],[0,0],[0,0]],"o":[[0,0],[0,0],[0,0],[0,0],[0,0],[0,0],[0,0],[0,0]],"v":[[94.381,19.977],[94.381,0.426],[97.131,0.426],[97.131,7.838],[100.01,7.838],[100.01,10.137],[97.13,10.137],[97.13,19.977]]}}},{"ty":"sh","hd":false,"nm":"Path 1 (47)","d":1,"ks":{"a":0,"k":{"c":false,"i":[[0,0],[-0.011,-3.223],[3.512,-0.387],[0,0],[0,0],[0,0],[0,0],[0,0],[0,0],[0,0],[0,2.944],[-4.2,0]],"o":[[4.2,0],[-0.011,2.953],[0,0],[0,0],[0,0],[0,0],[0,0],[0,0],[0,0],[-3.491,-0.398],[0,-3.222],[0,0]],"v":[[114.705,1.436],[122.074,6.786],[116.059,12.103],[116.059,15.443],[123.686,15.443],[123.686,17.7],[105.789,17.7],[105.789,15.444],[113.33,15.444],[113.33,12.104],[107.357,6.786],[114.705,1.436]]}}},{"ty":"sh","hd":false,"nm":"Path 1 (47)","d":1,"ks":{"a":0,"k":{"c":false,"i":[[0,0],[-2.739,-0.011],[-0.011,2.063],[2.75,-0.011],[0,-1.955]],"o":[[0,2.062],[2.75,-0.01],[-0.011,-1.955],[-2.739,-0.01],[0,0]],"v":[[110.064,6.786],[114.705,10.008],[119.367,6.785],[114.705,3.627],[110.064,6.785]]}}},{"ty":"sh","hd":false,"nm":"Path 1 (47)","d":1,"ks":{"a":0,"k":{"c":true,"i":[[0,0],[0,0],[0,0],[0,0],[0,0],[0,0],[0,0],[0,0],[0,0],[0,0],[0,0],[0,0]],"o":[[0,0],[0,0],[0,0],[0,0],[0,0],[0,0],[0,0],[0,0],[0,0],[0,0],[0,0],[0,0]],"v":[[141.045,1.241],[141.045,3.39],[138.488,3.39],[138.488,6.784],[140.916,6.784],[140.916,8.954],[126.5,8.954],[126.5,6.784],[128.906,6.784],[128.906,3.391],[126.371,3.391],[126.371,1.242]]}}},{"ty":"sh","hd":false,"nm":"Path 1 (47)","d":1,"ks":{"a":0,"k":{"c":true,"i":[[0,0],[0,0],[0,0],[0,0]],"o":[[0,0],[0,0],[0,0],[0,0]],"v":[[124.803,12.671],[124.803,10.522],[142.635,10.522],[142.635,12.671]]}}},{"ty":"sh","hd":false,"nm":"Path 1 (47)","d":1,"ks":{"a":0,"k":{"c":true,"i":[[0,0],[0,0],[0,0],[0,0],[0,0],[0,0]],"o":[[0,0],[0,0],[0,0],[0,0],[0,0],[0,0]],"v":[[126.951,19.631],[126.951,14.003],[129.701,14.003],[129.701,17.44],[140.615,17.44],[140.615,19.632]]}}},{"ty":"sh","hd":false,"nm":"Path 1 (47)","d":1,"ks":{"a":0,"k":{"c":true,"i":[[0,0],[0,0],[0,0],[0,0]],"o":[[0,0],[0,0],[0,0],[0,0]],"v":[[131.656,6.784],[135.738,6.784],[135.738,3.391],[131.656,3.391]]}}},{"ty":"sh","hd":false,"nm":"Path 1 (47)","d":1,"ks":{"a":0,"k":{"c":true,"i":[[0,0],[0,0],[0,0],[0,0]],"o":[[0,0],[0,0],[0,0],[0,0]],"v":[[165.322,0.424],[165.322,19.976],[162.551,19.976],[162.551,0.426]]}}},{"ty":"sh","hd":false,"nm":"Path 1 (47)","d":1,"ks":{"a":0,"k":{"c":true,"i":[[0,0],[-0.44,4.34],[0,0],[0,0],[0,0],[6.982,-3.298]],"o":[[5.049,-2.385],[0,0],[0,0],[0,0],[-0.011,5.93],[0,0]],"v":[[148.951,14.433],[156.664,4.614],[150.004,4.614],[150.004,2.467],[159.457,2.467],[150.391,16.625]]}}},{"ty":"sh","hd":false,"nm":"Path 1 (47)","d":1,"ks":{"a":0,"k":{"c":true,"i":[[0,0],[0,0],[-2.31,0.354],[0,0],[3.008,0.011],[0,0],[0,0]],"o":[[0,0],[2.363,-0.032],[0,0],[-2.761,0.494],[0,0],[0,0],[0,0]],"v":[[171.789,1.263],[171.789,9.158],[178.557,8.632],[178.836,10.78],[170.586,11.382],[169.018,11.382],[169.018,1.263]]}}},{"ty":"sh","hd":false,"nm":"Path 1 (47)","d":1,"ks":{"a":0,"k":{"c":true,"i":[[0,0],[0,0],[0,0],[0,0]],"o":[[0,0],[0,0],[0,0],[0,0]],"v":[[171.359,19.761],[171.359,12.65],[184.379,12.65],[184.379,19.762]]}}},{"ty":"sh","hd":false,"nm":"Path 1 (47)","d":1,"ks":{"a":0,"k":{"c":true,"i":[[0,0],[0,0],[0,0],[0,0]],"o":[[0,0],[0,0],[0,0],[0,0]],"v":[[174.045,17.569],[181.672,17.569],[181.672,14.819],[174.045,14.819]]}}},{"ty":"sh","hd":false,"nm":"Path 1 (47)","d":1,"ks":{"a":0,"k":{"c":true,"i":[[0,0],[0,0],[0,0],[0,0],[0,0],[0,0],[0,0],[0,0],[0,0],[0,0],[0,0],[0,0]],"o":[[0,0],[0,0],[0,0],[0,0],[0,0],[0,0],[0,0],[0,0],[0,0],[0,0],[0,0],[0,0]],"v":[[176.859,7.687],[176.859,5.624],[181.65,5.624],[181.65,4.271],[176.859,4.271],[176.859,2.231],[181.65,2.231],[181.65,0.425],[184.379,0.425],[184.379,11.855],[181.65,11.855],[181.65,7.687]]}}},{"ty":"sh","hd":false,"nm":"Path 1 (47)","d":1,"ks":{"a":0,"k":{"c":true,"i":[[0,0],[0,0],[0,0],[0,0]],"o":[[0,0],[0,0],[0,0],[0,0]],"v":[[122.611,32.425],[122.611,51.975],[119.84,51.975],[119.84,32.425]]}}},{"ty":"sh","hd":false,"nm":"Path 1 (47)","d":1,"ks":{"a":0,"k":{"c":true,"i":[[0,0],[-0.44,4.34],[0,0],[0,0],[0,0],[6.982,-3.298]],"o":[[5.049,-2.385],[0,0],[0,0],[0,0],[-0.011,5.93],[0,0]],"v":[[106.24,46.434],[113.953,36.615],[107.293,36.615],[107.293,34.467],[116.746,34.467],[107.68,48.625]]}}},{"ty":"sh","hd":false,"nm":"Path 1 (47)","d":1,"ks":{"a":0,"k":{"c":true,"i":[[0,0],[0,0],[0,0],[0,0],[0,0],[0,0],[0,0],[0,0]],"o":[[0,0],[0,0],[0,0],[0,0],[0,0],[0,0],[0,0],[0,0]],"v":[[140.701,32.426],[140.701,37.904],[143.344,37.904],[143.344,40.16],[140.701,40.16],[140.701,46.434],[137.93,46.434],[137.93,32.426]]}}},{"ty":"sh","hd":false,"nm":"Path 1 (47)","d":1,"ks":{"a":0,"k":{"c":true,"i":[[0,0],[-0.429,2.75],[0,0],[0,0],[0,0],[5.865,-1.655]],"o":[[4.382,-1.214],[0,0],[0,0],[0,0],[-0.011,5.285],[0,0]],"v":[[125.061,42.352],[132.354,36.122],[125.92,36.122],[125.92,33.887],[135.373,33.887],[126.199,44.522]]}}},{"ty":"sh","hd":false,"nm":"Path 1 (47)","d":1,"ks":{"a":0,"k":{"c":true,"i":[[0,0],[0,0],[0,0],[0,0],[0,0],[0,0]],"o":[[0,0],[0,0],[0,0],[0,0],[0,0],[0,0]],"v":[[127.982,51.632],[127.982,44.994],[130.754,44.994],[130.754,49.441],[141.367,49.441],[141.367,51.633]]}}},{"ty":"sh","hd":false,"nm":"Path 1 (47)","d":1,"ks":{"a":0,"k":{"c":true,"i":[[0,0],[0,0],[0,0],[0,0],[0,0],[0,0],[0,0],[0,0]],"o":[[0,0],[0,0],[0,0],[0,0],[0,0],[0,0],[0,0],[0,0]],"v":[[164.785,32.447],[164.785,38.441],[167.428,38.441],[167.428,40.676],[164.785,40.676],[164.785,47.036],[162.035,47.036],[162.035,32.446]]}}},{"ty":"sh","hd":false,"nm":"Path 1 (47)","d":1,"ks":{"a":0,"k":{"c":true,"i":[[0,0],[0,0],[0,0],[0,0],[0,0],[0,0],[0,0],[0,0]],"o":[[0,0],[0,0],[0,0],[0,0],[0,0],[0,0],[0,0],[0,0]],"v":[[149.273,36.658],[149.273,34.488],[153.721,34.488],[153.721,32.404],[156.449,32.404],[156.449,34.488],[160.875,34.488],[160.875,36.658]]}}},{"ty":"sh","hd":false,"nm":"Path 1 (47)","d":1,"ks":{"a":0,"k":{"c":false,"i":[[0,0],[-2.846,0],[0,-2.267],[2.836,0],[0,2.256]],"o":[[0,-2.267],[2.836,0],[0,2.256],[-2.846,0],[0,0]],"v":[[150.219,41.127],[155.074,37.346],[159.887,41.127],[155.074,44.865],[150.219,41.127]]}}},{"ty":"sh","hd":false,"nm":"Path 1 (47)","d":1,"ks":{"a":0,"k":{"c":true,"i":[[0,0],[0,0],[0,0],[0,0],[0,0],[0,0]],"o":[[0,0],[0,0],[0,0],[0,0],[0,0],[0,0]],"v":[[152.109,51.633],[152.109,45.918],[154.838,45.918],[154.838,49.441],[165.494,49.441],[165.494,51.633]]}}},{"ty":"sh","hd":false,"nm":"Path 1 (47)","d":1,"ks":{"a":0,"k":{"c":false,"i":[[0,0],[-1.31,0],[0,1.074],[1.322,0.01],[-0.01,-1.085]],"o":[[-0.01,1.074],[1.322,0],[0,-1.085],[-1.31,0.01],[0,0]],"v":[[152.904,41.127],[155.074,42.781],[157.287,41.127],[155.074,39.43],[152.904,41.127]]}}},{"ty":"sh","hd":false,"nm":"Path 1 (47)","d":1,"ks":{"a":0,"k":{"c":true,"i":[[0,0],[0,0],[0,0],[0,0],[0,0],[0,0],[0,0],[0,0]],"o":[[0,0],[0,0],[0,0],[0,0],[0,0],[0,0],[0,0],[0,0]],"v":[[184.766,32.426],[184.766,44.027],[182.037,44.027],[182.037,39.408],[178.986,39.408],[178.986,37.195],[182.037,37.195],[182.037,32.425]]}}},{"ty":"sh","hd":false,"nm":"Path 1 (47)","d":1,"ks":{"a":0,"k":{"c":true,"i":[[0,0],[-0.065,2.449],[0,0],[0,0],[0,0],[0,0],[0,0],[-3.04,-1.01],[0,0],[0.849,1.751],[2.32,-0.795]],"o":[[3.201,-1.074],[0,0],[0,0],[0,0],[0,0],[0,0],[0.053,2.277],[0,0],[-2.148,-0.698],[-0.859,1.987],[0,0]],"v":[[168.158,41.879],[172.885,35.799],[168.953,35.799],[168.953,33.607],[179.566,33.607],[179.566,35.8],[175.678,35.8],[180.168,41.386],[178.814,43.534],[174.324,39.667],[169.576,44.05]]}}},{"ty":"sh","hd":false,"nm":"Path 1 (47)","d":1,"ks":{"a":0,"k":{"c":false,"i":[[0,0],[-4.168,0.011],[-0.011,-2.374],[4.179,0],[0,2.374]],"o":[[0,-2.375],[4.179,0.01],[-0.011,2.374],[-4.168,0],[0,0]],"v":[[171.359,48.239],[178.084,44.457],[184.83,48.238],[178.084,51.998],[171.359,48.238]]}}},{"ty":"sh","hd":false,"nm":"Path 1 (47)","d":1,"ks":{"a":0,"k":{"c":false,"i":[[0,0],[-2.589,0],[-0.011,1.117],[2.6,-0.011],[0,-1.128]],"o":[[0,1.117],[2.6,0],[-0.011,-1.128],[-2.589,-0.011],[0,0]],"v":[[174.088,48.238],[178.084,49.913],[182.102,48.237],[178.084,46.562],[174.088,48.237]]}}},{"ty":"sh","hd":false,"nm":"Path 1 (47)","d":1,"ks":{"a":0,"k":{"c":true,"i":[[0,0],[0,0],[0,0],[0,0]],"o":[[0,0],[0,0],[0,0],[0,0]],"v":[[208.742,32.424],[208.742,52.02],[205.971,52.02],[205.971,32.426]]}}},{"ty":"sh","hd":false,"nm":"Path 1 (47)","d":1,"ks":{"a":0,"k":{"c":false,"i":[[0,0],[-3.008,0],[0,-4.264],[2.943,0],[-0.011,4.297]],"o":[[-0.011,-4.265],[2.943,0],[0,4.298],[-3.008,0],[0,0]],"v":[[192.951,40.76],[198.129,33.799],[203.264,40.759],[198.129,47.742],[192.951,40.76]]}}},{"ty":"sh","hd":false,"nm":"Path 1 (47)","d":1,"ks":{"a":0,"k":{"c":false,"i":[[0,0],[-1.525,0.01],[-0.011,2.91],[1.482,0],[-0.011,-2.9]],"o":[[-0.011,2.91],[1.482,0.01],[-0.011,-2.9],[-1.525,0],[0,0]],"v":[[195.594,40.76],[198.129,45.25],[200.621,40.76],[198.129,36.27],[195.594,40.76]]}}},{"ty":"sh","hd":false,"nm":"Path 1 (47)","d":1,"ks":{"a":0,"k":{"c":true,"i":[[0,0],[0,0],[0,0],[0,0]],"o":[[0,0],[0,0],[0,0],[0,0]],"v":[[228.186,32.424],[228.186,47.205],[225.586,47.205],[225.586,32.426]]}}},{"ty":"sh","hd":false,"nm":"Path 1 (47)","d":1,"ks":{"a":0,"k":{"c":true,"i":[[0,0],[0,0],[0,0],[0,0],[0,0],[0,0],[0,0],[0,0],[0,0],[0,0],[0,0],[0,0],[0,0],[0,0],[0,0],[0,0]],"o":[[0,0],[0,0],[0,0],[0,0],[0,0],[0,0],[0,0],[0,0],[0,0],[0,0],[0,0],[0,0],[0,0],[0,0],[0,0],[0,0]],"v":[[212.072,43.81],[212.072,33.93],[214.672,33.93],[214.672,36.916],[217.336,36.916],[217.336,33.93],[219.871,33.93],[219.871,37.84],[221.633,37.84],[221.633,32.727],[224.211,32.727],[224.211,46.584],[221.633,46.584],[221.633,40.031],[219.871,40.031],[219.871,43.813]]}}},{"ty":"sh","hd":false,"nm":"Path 1 (47)","d":1,"ks":{"a":0,"k":{"c":true,"i":[[0,0],[0,0],[0,0],[0,0]],"o":[[0,0],[0,0],[0,0],[0,0]],"v":[[214.672,41.598],[217.336,41.598],[217.336,39],[214.672,39]]}}},{"ty":"sh","hd":false,"nm":"Path 1 (47)","d":1,"ks":{"a":0,"k":{"c":true,"i":[[0,0],[0,0],[0,0],[0,0],[0,0],[0,0]],"o":[[0,0],[0,0],[0,0],[0,0],[0,0],[0,0]],"v":[[214.93,51.631],[214.93,45.25],[217.68,45.25],[217.68,49.44],[228.68,49.44],[228.68,51.63]]}}},{"ty":"sh","hd":false,"nm":"Path 1 (47)","d":1,"ks":{"a":0,"k":{"c":true,"i":[[0,0],[0,0],[0,0],[0,0],[0,0],[0,0],[0,0],[0,0],[0,0],[0,0],[0,0],[0,0]],"o":[[0,0],[0,0],[0,0],[0,0],[0,0],[0,0],[0,0],[0,0],[0,0],[0,0],[0,0],[0,0]],"v":[[246.34,42.521],[246.34,44.691],[232.504,44.691],[232.504,33.865],[246.189,33.865],[246.189,36.078],[235.297,36.078],[235.297,38.141],[245.738,38.141],[245.738,40.289],[235.297,40.289],[235.297,42.523]]}}},{"ty":"sh","hd":false,"nm":"Path 1 (47)","d":1,"ks":{"a":0,"k":{"c":true,"i":[[0,0],[0,0],[0,0],[0,0]],"o":[[0,0],[0,0],[0,0],[0,0]],"v":[[230.398,49.7],[230.398,47.466],[248.295,47.466],[248.295,49.7]]}}},{"ty":"fl","hd":false,"bm":0,"c":{"a":0,"k":[0.133,0.133,0.141]},"r":1,"o":{"a":0,"k":100}},{"ty":"tr","nm":"Transform","a":{"a":0,"k":[0,0]},"o":{"a":0,"k":100},"p":{"a":0,"k":[0,0]},"r":{"a":0,"k":0},"s":{"a":0,"k":[100,100]},"sk":{"a":0,"k":0},"sa":{"a":0,"k":0}}],"np":0}]}]}],"ddd":0,"fr":30,"h":280,"ip":0,"layers":[{"ddd":0,"ind":5,"ty":0,"nm":"Import from Figma","hd":false,"sr":1,"ks":{"a":{"a":0,"k":[117,10.5]},"o":{"a":0,"k":100},"p":{"a":0,"k":[137,113.5]},"r":{"a":0,"k":0},"s":{"a":0,"k":[100,100]},"sk":{"a":0,"k":0},"sa":{"a":0,"k":0}},"ao":0,"ip":0,"op":121,"st":0,"bm":0,"h":21,"refId":"el-632-HUml","w":234},{"ddd":0,"ind":9,"ty":0,"nm":"Import from Figma","hd":false,"sr":1,"ks":{"a":{"a":0,"k":[124.5,26.5]},"o":{"a":0,"k":100},"p":{"a":0,"k":[144.5,53.5]},"r":{"a":0,"k":0},"s":{"a":0,"k":[100,100]},"sk":{"a":0,"k":0},"sa":{"a":0,"k":0}},"ao":0,"ip":0,"op":121,"st":0,"bm":0,"h":53,"refId":"el-616-HUml","w":249},{"ddd":0,"ind":10,"ty":4,"nm":"subtitle","hd":true,"sr":1,"ks":{"a":{"a":0,"k":[114.493,109.044]},"o":{"a":0,"k":100},"p":{"a":0,"k":[114.493,109.044]},"r":{"a":0,"k":0},"s":{"a":0,"k":[100,100]},"sk":{"a":0,"k":0},"sa":{"a":0,"k":0}},"ao":0,"ip":0,"op":121,"st":0,"bm":0,"shapes":[{"ty":"gr","hd":true,"nm":"Path 1 (44) Group","bm":0,"it":[{"ty":"sh","hd":true,"nm":"Path 1 (44)","d":1,"ks":{"a":0,"k":{"c":true,"i":[[0,0],[0,0],[0,0],[0,0],[-0.527,0.055],[0,0],[2.161,-0.007],[0,0],[-0.492,0],[0,0],[0,0],[0,0]],"o":[[0,0],[0,0],[0,0],[0.553,-0.041],[0,0],[-2.51,0.382],[0,0],[0.445,0],[0,0],[0,0],[0,0],[0,0]],"v":[[27.656,103.787],[27.656,105.031],[26.55,105.031],[26.55,108.415],[28.177,108.271],[28.273,109.393],[20.78,109.83],[20.616,108.572],[22.024,108.565],[22.024,105.031],[20.944,105.031],[20.944,103.787]]}}},{"ty":"sh","hd":true,"nm":"Path 1 (44)","d":1,"ks":{"a":0,"k":{"c":true,"i":[[0,0],[0,0],[0,0],[0,0],[0,0],[0,0]],"o":[[0,0],[0,0],[0,0],[0,0],[0,0],[0,0]],"v":[[22.27,112.154],[22.27,110.924],[30.705,110.924],[30.705,115.217],[29.174,115.217],[29.174,112.154]]}}},{"ty":"sh","hd":true,"nm":"Path 1 (44)","d":1,"ks":{"a":0,"k":{"c":true,"i":[[0,0],[-0.538,0.023],[0,0],[0,0]],"o":[[0.538,-0.009],[0,0],[0,0],[0,0]],"v":[[23.486,108.538],[25.1,108.49],[25.1,105.031],[23.486,105.031]]}}},{"ty":"sh","hd":true,"nm":"Path 1 (44)","d":1,"ks":{"a":0,"k":{"c":true,"i":[[0,0],[0,0],[0,0],[0,0]],"o":[[0,0],[0,0],[0,0],[0,0]],"v":[[29.174,110.404],[29.174,102.857],[30.705,102.857],[30.705,110.404]]}}},{"ty":"sh","hd":true,"nm":"Path 1 (44)","d":1,"ks":{"a":0,"k":{"c":true,"i":[[0,0],[0,0],[0,0],[0,0],[0,0],[0,0],[0,0],[0,0],[0,0],[0,0],[0,0],[0,0]],"o":[[0,0],[0,0],[0,0],[0,0],[0,0],[0,0],[0,0],[0,0],[0,0],[0,0],[0,0],[0,0]],"v":[[42.736,103.213],[42.736,104.361],[41.041,104.361],[41.041,106.234],[42.668,106.234],[42.668,107.383],[33.59,107.383],[33.59,106.234],[35.217,106.234],[35.217,104.361],[33.522,104.361],[33.522,103.213]]}}},{"ty":"sh","hd":true,"nm":"Path 1 (44)","d":1,"ks":{"a":0,"k":{"c":true,"i":[[0,0],[0,0],[0,0],[0,0]],"o":[[0,0],[0,0],[0,0],[0,0]],"v":[[32.51,109.365],[32.51,108.162],[43.775,108.162],[43.775,109.365]]}}},{"ty":"sh","hd":true,"nm":"Path 1 (44)","d":1,"ks":{"a":0,"k":{"c":true,"i":[[0,0],[0,0],[0,0],[0,0],[0,0],[0,0],[0,0],[0,0],[0,0],[0,0],[0,0],[0,0]],"o":[[0,0],[0,0],[0,0],[0,0],[0,0],[0,0],[0,0],[0,0],[0,0],[0,0],[0,0],[0,0]],"v":[[33.836,111.307],[33.836,110.199],[42.367,110.199],[42.367,113.139],[35.34,113.139],[35.34,113.973],[42.709,113.973],[42.709,115.107],[33.849,115.107],[33.849,112.086],[40.877,112.086],[40.877,111.307]]}}},{"ty":"sh","hd":true,"nm":"Path 1 (44)","d":1,"ks":{"a":0,"k":{"c":true,"i":[[0,0],[0,0],[0,0],[0,0]],"o":[[0,0],[0,0],[0,0],[0,0]],"v":[[36.734,106.234],[39.51,106.234],[39.51,104.361],[36.734,104.361]]}}},{"ty":"sh","hd":true,"nm":"Path 1 (44)","d":1,"ks":{"a":0,"k":{"c":true,"i":[[0,0],[0,0],[0,0],[0,0]],"o":[[0,0],[0,0],[0,0],[0,0]],"v":[[54.891,102.857],[54.891,115.23],[53.359,115.23],[53.359,102.857]]}}},{"ty":"sh","hd":true,"nm":"Path 1 (44)","d":1,"ks":{"a":0,"k":{"c":false,"i":[[0,0],[-1.873,0],[-0.007,-2.666],[1.853,0],[-0.007,2.687]],"o":[[-0.007,-2.666],[1.853,0],[-0.007,2.687],[-1.873,0],[0,0]],"v":[[45.006,108.121],[48.232,103.76],[51.459,108.121],[48.232,112.496],[45.006,108.121]]}}},{"ty":"sh","hd":true,"nm":"Path 1 (44)","d":1,"ks":{"a":0,"k":{"c":false,"i":[[0,0],[-1.045,-0.007],[0,1.9],[1.04,0],[0,-1.887]],"o":[[0,1.9],[1.04,-0.007],[0,-1.887],[-1.045,0],[0,0]],"v":[[46.469,108.121],[48.232,111.129],[49.982,108.121],[48.232,105.127],[46.469,108.121]]}}},{"ty":"sh","hd":true,"nm":"Path 1 (44)","d":1,"ks":{"a":0,"k":{"c":true,"i":[[0,0],[0,0],[0,0],[-0.006,-1.901],[2.284,0],[0,0],[0,0]],"o":[[0,0],[0,0],[2.27,0],[-0.007,1.893],[0,0],[0,0],[0,0]],"v":[[60.537,114],[60.537,104.102],[64.256,104.102],[67.742,107.383],[64.228,110.65],[62.315,110.65],[62.315,114]]}}},{"ty":"sh","hd":true,"nm":"Path 1 (44)","d":1,"ks":{"a":0,"k":{"c":true,"i":[[0,0],[0,0],[0,1.046],[1.34,0],[0,0]],"o":[[0,0],[1.34,-0.007],[0,-1.06],[0,0],[0,0]],"v":[[62.315,109.188],[63.982,109.188],[65.924,107.383],[63.982,105.592],[62.315,105.592]]}}},{"ty":"sh","hd":true,"nm":"Path 1 (44)","d":1,"ks":{"a":0,"k":{"c":true,"i":[[0,0],[0,0],[0,0],[0,0]],"o":[[0,0],[0,0],[0,0],[0,0]],"v":[[70.955,104.102],[70.955,114],[69.178,114],[69.178,104.102]]}}},{"ty":"sh","hd":true,"nm":"Path 1 (44)","d":1,"ks":{"a":0,"k":{"c":true,"i":[[0,0],[1.204,0],[-0.007,-2.242],[-1.613,0],[-0.24,1.162],[0,0],[2.345,0],[-0.007,3.192],[-2.591,0],[-0.308,-2.202]],"o":[[-0.212,-1.19],[-1.62,0],[-0.007,2.276],[1.176,0],[0,0],[-0.273,1.9],[-2.611,0],[-0.007,-3.199],[2.188,0],[0,0]],"v":[[79.473,107.438],[77.107,105.564],[74.346,109.051],[77.107,112.537],[79.473,110.719],[81.263,110.719],[77.08,114.137],[72.555,109.051],[77.08,103.965],[81.264,107.438]]}}},{"ty":"sh","hd":true,"nm":"Path 1 (44)","d":1,"ks":{"a":0,"k":{"c":true,"i":[[0,0],[0,0],[0,0],[0,0],[0,0],[0,0],[0,0],[0,0],[0,0],[0,0],[0,0],[0,0],[0,0]],"o":[[0,0],[0,0],[0,0],[0,0],[0,0],[0,0],[0,0],[0,0],[0,0],[0,0],[0,0],[0,0],[0,0]],"v":[[82.795,114],[82.795,104.102],[84.572,104.102],[84.572,108.654],[84.709,108.654],[88.579,104.102],[90.752,104.102],[86.924,108.545],[90.793,114],[88.646,114],[85.68,109.748],[84.572,111.047],[84.572,114]]}}},{"ty":"sh","hd":true,"nm":"Path 1 (44)","d":1,"ks":{"a":0,"k":{"c":true,"i":[[0,0],[0,0],[0,0],[0,0]],"o":[[0,0],[0,0],[0,0],[0,0]],"v":[[93.924,104.102],[93.774,111.088],[92.228,111.088],[92.065,104.102]]}}},{"ty":"sh","hd":true,"nm":"Path 1 (44)","d":1,"ks":{"a":0,"k":{"c":false,"i":[[0,0],[-0.588,0.007],[-0.009,-0.578],[0.583,-0.009],[-0.002,0.59]],"o":[[-0.006,-0.574],[0.578,0.009],[-0.002,0.583],[-0.59,0.002],[0,0]],"v":[[91.941,113.043],[93.008,111.99],[94.061,113.043],[93.008,114.109],[91.941,113.043]]}}},{"ty":"sh","hd":true,"nm":"Path 1 (44)","d":1,"ks":{"a":0,"k":{"c":true,"i":[[0,0],[0,0],[0,0],[0,0],[0,0],[0,0],[0,0],[0,0]],"o":[[0,0],[0,0],[0,0],[0,0],[0,0],[0,0],[0,0],[0,0]],"v":[[105.189,102.871],[105.189,106.754],[106.912,106.754],[106.912,108.012],[105.189,108.012],[105.189,112.1],[103.672,112.1],[103.672,102.871]]}}},{"ty":"sh","hd":true,"nm":"Path 1 (44)","d":1,"ks":{"a":0,"k":{"c":true,"i":[[0,0],[0,0],[0,0],[0,0],[0,0],[0,0],[0,0],[0,0]],"o":[[0,0],[0,0],[0,0],[0,0],[0,0],[0,0],[0,0],[0,0]],"v":[[95.455,105.455],[95.455,104.238],[98.367,104.238],[98.367,102.857],[99.885,102.857],[99.885,104.238],[102.783,104.238],[102.783,105.455]]}}},{"ty":"sh","hd":true,"nm":"Path 1 (44)","d":1,"ks":{"a":0,"k":{"c":false,"i":[[0,0],[-1.798,0],[-0.007,-1.422],[1.784,0],[0,1.415]],"o":[[0,-1.422],[1.784,0],[-0.007,1.415],[-1.798,0],[0,0]],"v":[[96.084,108.326],[99.119,105.961],[102.141,108.326],[99.119,110.664],[96.084,108.326]]}}},{"ty":"sh","hd":true,"nm":"Path 1 (44)","d":1,"ks":{"a":0,"k":{"c":true,"i":[[0,0],[0,0],[0,0],[0,0],[0,0],[0,0]],"o":[[0,0],[0,0],[0,0],[0,0],[0,0],[0,0]],"v":[[97.274,114.971],[97.274,111.375],[98.791,111.375],[98.791,113.74],[105.682,113.74],[105.682,114.971]]}}},{"ty":"sh","hd":true,"nm":"Path 1 (44)","d":1,"ks":{"a":0,"k":{"c":false,"i":[[0,0],[-0.936,0.007],[0,0.745],[0.937,0],[-0.007,-0.752]],"o":[[-0.007,0.745],[0.937,0.007],[0,-0.752],[-0.936,0],[0,0]],"v":[[97.561,108.326],[99.119,109.488],[100.691,108.326],[99.119,107.137],[97.561,108.326]]}}},{"ty":"sh","hd":true,"nm":"Path 1 (44)","d":1,"ks":{"a":0,"k":{"c":true,"i":[[0,0],[0,0],[0,0],[0,0],[0,0],[0,0],[0,0],[0,0]],"o":[[0,0],[0,0],[0,0],[0,0],[0,0],[0,0],[0,0],[0,0]],"v":[[111.643,114],[115.936,105.66],[115.936,105.592],[110.959,105.592],[110.959,104.102],[117.781,104.102],[117.781,105.619],[113.488,114]]}}},{"ty":"sh","hd":true,"nm":"Path 1 (44)","d":1,"ks":{"a":0,"k":{"c":true,"i":[[0,0],[0,0],[0,0],[0,0],[0,0],[0,0],[0,0],[0,0]],"o":[[0,0],[0,0],[0,0],[0,0],[0,0],[0,0],[0,0],[0,0]],"v":[[129.17,102.871],[129.17,110.076],[127.639,110.076],[127.639,109.57],[125.328,109.57],[125.328,108.641],[127.639,108.641],[127.639,102.871]]}}},{"ty":"sh","hd":true,"nm":"Path 1 (44)","d":1,"ks":{"a":0,"k":{"c":true,"i":[[0,0],[-2.652,0.267],[0,0],[1.141,-0.055],[0,0],[0,0],[0,0],[0.93,0.006]],"o":[[2.386,0],[0,0],[-1.128,0.15],[0,0],[0,0],[0,0],[-1.06,0.028],[0,0]],"v":[[118.793,107.328],[126.818,107.041],[126.9,107.998],[123.469,108.306],[123.469,110.09],[121.965,110.09],[121.965,108.367],[118.957,108.395]]}}},{"ty":"sh","hd":true,"nm":"Path 1 (44)","d":1,"ks":{"a":0,"k":{"c":false,"i":[[0,0],[-1.88,0.007],[-0.007,-1.121],[1.839,0],[0,1.148]],"o":[[0,-1.121],[1.839,0.007],[-0.007,1.148],[-1.88,0],[0,0]],"v":[[119.668,104.922],[122.785,103.062],[125.875,104.922],[122.785,106.768],[119.668,104.922]]}}},{"ty":"sh","hd":true,"nm":"Path 1 (44)","d":1,"ks":{"a":0,"k":{"c":true,"i":[[0,0],[0,0],[0,0],[0,0],[0,0],[0,0],[0,0],[0,0],[0,0],[0,0],[0,0],[0,0]],"o":[[0,0],[0,0],[0,0],[0,0],[0,0],[0,0],[0,0],[0,0],[0,0],[0,0],[0,0],[0,0]],"v":[[120.598,111.498],[120.598,110.459],[129.17,110.459],[129.17,113.234],[122.143,113.234],[122.143,114.027],[129.498,114.027],[129.498,115.107],[120.652,115.107],[120.652,112.236],[127.666,112.236],[127.666,111.498]]}}},{"ty":"sh","hd":true,"nm":"Path 1 (44)","d":1,"ks":{"a":0,"k":{"c":false,"i":[[0,0],[-1.039,0.007],[0,0.519],[1.019,-0.007],[-0.013,-0.52]],"o":[[-0.013,0.519],[1.019,0.007],[0,-0.52],[-1.039,-0.007],[0,0]],"v":[[121.117,104.922],[122.785,105.756],[124.453,104.922],[122.785,104.074],[121.117,104.922]]}}},{"ty":"sh","hd":true,"nm":"Path 1 (44)","d":1,"ks":{"a":0,"k":{"c":true,"i":[[0,0],[0,0],[0,0],[0,0],[0,0],[0,0],[0,0],[0,0],[0,0],[0,0],[0,0],[0,0]],"o":[[0,0],[0,0],[0,0],[0,0],[0,0],[0,0],[0,0],[0,0],[0,0],[0,0],[0,0],[0,0]],"v":[[145.521,112.469],[145.521,113.713],[134.229,113.713],[134.229,112.469],[139.096,112.469],[139.096,109.775],[135.473,109.775],[135.473,103.814],[144.223,103.814],[144.223,109.775],[140.6,109.775],[140.6,112.469]]}}},{"ty":"sh","hd":true,"nm":"Path 1 (44)","d":1,"ks":{"a":0,"k":{"c":true,"i":[[0,0],[0,0],[0,0],[0,0]],"o":[[0,0],[0,0],[0,0],[0,0]],"v":[[136.963,108.586],[142.719,108.586],[142.719,105.031],[136.963,105.031]]}}},{"ty":"sh","hd":true,"nm":"Path 1 (44)","d":1,"ks":{"a":0,"k":{"c":true,"i":[[0,0],[0,0],[0,0],[0,0]],"o":[[0,0],[0,0],[0,0],[0,0]],"v":[[156.623,102.871],[156.623,109.871],[155.092,109.871],[155.092,102.871]]}}},{"ty":"sh","hd":true,"nm":"Path 1 (44)","d":1,"ks":{"a":0,"k":{"c":false,"i":[[0,0],[-1.914,0.007],[0.007,-1.743],[1.907,0],[0,1.702]],"o":[[0,-1.743],[1.907,0.007],[0.007,1.702],[-1.914,0],[0,0]],"v":[[146.547,106.412],[149.883,103.459],[153.205,106.412],[149.883,109.338],[146.547,106.412]]}}},{"ty":"sh","hd":true,"nm":"Path 1 (44)","d":1,"ks":{"a":0,"k":{"c":false,"i":[[0,0],[-1.08,0.007],[0,0.998],[1.059,0],[-0.007,-1.025]],"o":[[-0.007,0.998],[1.059,0.007],[0,-1.025],[-1.08,0],[0,0]],"v":[[148.037,106.412],[149.883,108.053],[151.715,106.412],[149.883,104.744],[148.037,106.412]]}}},{"ty":"sh","hd":true,"nm":"Path 1 (44)","d":1,"ks":{"a":0,"k":{"c":true,"i":[[0,0],[0,0],[0,0],[0,0]],"o":[[0,0],[0,0],[0,0],[0,0]],"v":[[148.42,115.066],[148.42,110.473],[156.623,110.473],[156.623,115.066]]}}},{"ty":"sh","hd":true,"nm":"Path 1 (44)","d":1,"ks":{"a":0,"k":{"c":true,"i":[[0,0],[0,0],[0,0],[0,0]],"o":[[0,0],[0,0],[0,0],[0,0]],"v":[[149.924,113.836],[155.133,113.836],[155.133,111.676],[149.924,111.676]]}}},{"ty":"sh","hd":true,"nm":"Path 1 (44)","d":1,"ks":{"a":0,"k":{"c":true,"i":[[0,0],[0,0],[0,0],[0,0],[0,0],[0,0],[0,0],[0,0]],"o":[[0,0],[0,0],[0,0],[0,0],[0,0],[0,0],[0,0],[0,0]],"v":[[171.43,102.857],[171.43,107.561],[173.33,107.561],[173.33,108.846],[171.43,108.846],[171.43,115.217],[169.912,115.217],[169.912,102.857]]}}},{"ty":"sh","hd":true,"nm":"Path 1 (44)","d":1,"ks":{"a":0,"k":{"c":true,"i":[[0,0],[0,0],[0,0],[0,0],[0,0],[0,0],[0,0],[0,0]],"o":[[0,0],[0,0],[0,0],[0,0],[0,0],[0,0],[0,0],[0,0]],"v":[[162.188,112.318],[162.188,103.869],[163.691,103.869],[163.691,106.959],[166.604,106.959],[166.604,103.869],[168.121,103.869],[168.121,112.318]]}}},{"ty":"sh","hd":true,"nm":"Path 1 (44)","d":1,"ks":{"a":0,"k":{"c":true,"i":[[0,0],[0,0],[0,0],[0,0]],"o":[[0,0],[0,0],[0,0],[0,0]],"v":[[163.691,111.074],[166.604,111.074],[166.604,108.148],[163.691,108.148]]}}},{"ty":"sh","hd":true,"nm":"Path 1 (44)","d":1,"ks":{"a":0,"k":{"c":true,"i":[[0,0],[0,0],[0,0],[0,0],[0,0],[0,0],[0,0],[0,0],[0,0],[0,0],[0,0],[0,0],[0,0],[0,0],[0,0],[0,0],[0,0],[0,0],[0,0],[0,0]],"o":[[0,0],[0,0],[0,0],[0,0],[0,0],[0,0],[0,0],[0,0],[0,0],[0,0],[0,0],[0,0],[0,0],[0,0],[0,0],[0,0],[0,0],[0,0],[0,0],[0,0]],"v":[[185.143,112.523],[185.143,113.781],[173.85,113.781],[173.85,112.523],[178.717,112.523],[178.717,110.514],[175.189,110.514],[175.189,106.467],[182.299,106.467],[182.299,104.936],[175.162,104.936],[175.162,103.705],[183.803,103.705],[183.803,107.67],[176.707,107.67],[176.707,109.27],[184.09,109.27],[184.09,110.514],[180.221,110.514],[180.221,112.523]]}}},{"ty":"sh","hd":true,"nm":"Path 1 (44)","d":1,"ks":{"a":0,"k":{"c":true,"i":[[0,0],[0,0],[0,0],[0,0],[0,0],[0,0],[0,0],[0,0]],"o":[[0,0],[0,0],[0,0],[0,0],[0,0],[0,0],[0,0],[0,0]],"v":[[195.629,102.857],[195.629,107.684],[197.461,107.684],[197.461,108.955],[195.629,108.955],[195.629,115.189],[194.111,115.189],[194.111,102.857]]}}},{"ty":"sh","hd":true,"nm":"Path 1 (44)","d":1,"ks":{"a":0,"k":{"c":true,"i":[[0,0],[-0.3,2.817],[0,0],[0,0],[0,0],[4.109,-2.023]],"o":[[3.008,-1.503],[0,0],[0,0],[0,0],[-0.007,3.629],[0,0]],"v":[[185.881,111.812],[190.816,105.4],[186.551,105.4],[186.551,104.143],[192.361,104.143],[186.742,112.988]]}}},{"ty":"sh","hd":true,"nm":"Path 1 (44)","d":1,"ks":{"a":0,"k":{"c":true,"i":[[0,0],[0,0],[0,0],[0,0]],"o":[[0,0],[0,0],[0,0],[0,0]],"v":[[208.371,102.857],[208.371,115.217],[206.84,115.217],[206.84,102.857]]}}},{"ty":"sh","hd":true,"nm":"Path 1 (44)","d":1,"ks":{"a":0,"k":{"c":true,"i":[[0,0],[-0.274,2.81],[0,0],[0,0],[0,0],[4.327,-2.057]],"o":[[3.24,-1.538],[0,0],[0,0],[0,0],[0,3.678],[0,0]],"v":[[198.131,111.812],[203.135,105.373],[198.76,105.373],[198.76,104.17],[204.68,104.17],[198.924,113.029]]}}},{"ty":"fl","hd":false,"bm":0,"c":{"a":0,"k":[0.243,0.247,0.271]},"r":1,"o":{"a":0,"k":100}},{"ty":"tr","nm":"Transform","a":{"a":0,"k":[0,0]},"o":{"a":0,"k":100},"p":{"a":0,"k":[0,0]},"r":{"a":0,"k":0},"s":{"a":0,"k":[100,100]},"sk":{"a":0,"k":0},"sa":{"a":0,"k":0}}],"np":0}]},{"ddd":0,"ind":12,"ty":4,"nm":"star1","hd":false,"sr":1,"ks":{"a":{"a":0,"k":[0,0]},"o":{"a":0,"k":100},"p":{"a":0,"k":[206.501,213.369]},"r":{"a":1,"k":[{"t":0,"s":[0],"i":{"x":0.5,"y":1},"o":{"x":0.12,"y":0.23}},{"t":82.8,"s":[360],"i":{"x":0,"y":0},"o":{"x":1,"y":1}}]},"s":{"a":0,"k":[100,100]},"sk":{"a":0,"k":0},"sa":{"a":0,"k":0}},"ao":0,"ip":0,"op":121,"st":0,"bm":0,"shapes":[{"ty":"gr","hd":false,"nm":"Layer 3 Group","bm":0,"it":[{"ty":"gr","hd":false,"nm":"Path 1 (2) Group","bm":0,"it":[{"ty":"sh","hd":false,"nm":"Path 1 (2)","d":1,"ks":{"a":0,"k":{"c":false,"i":[[0,0],[4.194,-4.412],[0.372,-1.015],[1.28,0.628],[1.205,-0.001],[0,-4.366],[-0.518,-1.051],[0.256,-0.615],[0.729,-0.245],[-4.567,-4.026],[-1.055,-0.332],[-0.269,-0.608],[0.323,-0.697],[-5.777,0.001],[-1.043,0.483],[-0.608,-0.269],[-0.23,-0.732],[-4.119,4.482],[-0.347,1.117],[-0.605,0.271],[-0.696,-0.318],[-2.232,1.33],[2.234,3.751],[-0.246,0.562],[-0.65,0.152],[4.162,4.441],[1.255,0.414],[0.261,0.597],[-0.31,0.679],[6.059,-0.574],[1.006,-0.599],[0.534,0.209],[0.185,0.601]],"o":[[-1.724,-5.838],[-0.745,0.783],[-0.491,1.341],[-1.083,-0.529],[-4.366,0],[0,1.254],[0.34,0.69],[-0.257,0.614],[-5.77,1.943],[0.83,0.731],[0.732,0.229],[0.269,0.608],[-2.431,5.24],[1.149,0.001],[0.696,-0.324],[0.608,0.269],[1.822,5.808],[0.791,-0.861],[0.226,-0.73],[0.605,-0.271],[2.362,1.084],[3.752,-2.233],[-0.307,-0.531],[0.216,-0.508],[5.927,-1.384],[-0.904,-0.964],[-0.708,-0.234],[-0.26,-0.596],[2.532,-5.534],[-1.166,0.11],[-0.586,0.349],[-0.588,-0.224],[0,0]],"v":[[213.848,190.669],[200.534,187.46],[198.841,190.186],[195.42,191.559],[191.943,190.756],[184.038,198.661],[184.847,202.15],[184.882,204.222],[183.386,205.656],[180.68,219.085],[183.539,220.697],[185.061,222.095],[185.072,224.163],[192.245,235.396],[195.573,234.664],[197.64,234.674],[199.039,236.196],[212.407,239.18],[214.136,236.176],[215.524,234.654],[217.584,234.633],[224.922,234.239],[227.671,223.403],[227.573,221.664],[228.893,220.531],[232.864,207.426],[229.575,205.325],[228.101,203.948],[228.094,201.932],[220.159,190.772],[216.861,191.849],[215.072,191.977],[213.848,190.669]]}}},{"ty":"sh","hd":false,"nm":"Path 1 (2)","d":1,"ks":{"a":0,"k":{"c":false,"i":[[0,0],[-0.559,0.333],[-0.093,-6.854],[0.549,-1.2],[-0.795,-0.262],[5.117,-4.561],[0.488,-0.291],[0.889,-0.21],[-0.307,-0.515],[4.227,-2.515],[2.661,1.22],[0.254,-0.82],[4.651,5.041],[0.394,1.254],[0.781,-0.363],[-0.607,6.829],[-0.434,0.935],[0.822,0.258],[-5.053,4.638],[-1.179,0.397],[0.381,0.775],[-6.595,-0.002],[-1.182,-0.58],[-0.286,0.782],[-4.395,-5.261],[-0.242,-0.406],[-0.207,-0.697]],"o":[[0.184,0.623],[5.89,-3.508],[0.018,1.32],[-0.348,0.762],[6.509,2.151],[-0.424,0.378],[-0.786,0.467],[-0.583,0.136],[2.516,4.226],[-2.514,1.498],[-0.78,-0.357],[-2.04,6.549],[-0.891,-0.966],[-0.257,-0.822],[-6.218,2.889],[0.091,-1.027],[0.363,-0.781],[-6.543,-2.057],[0.917,-0.841],[0.819,-0.275],[-2.911,-5.918],[1.406,0],[0.748,0.367],[2.358,-6.437],[0.303,0.363],[0.389,0.653],[0,0]],"v":[[214.807,190.385],[216.35,190.99],[229.811,198.52],[229.004,202.347],[229.889,204.375],[233.02,219.478],[231.648,220.483],[229.121,221.505],[228.531,222.891],[225.433,235.098],[217.168,235.543],[215.091,236.473],[200.036,239.866],[198.084,236.495],[195.994,235.571],[183.371,226.705],[184.165,223.741],[183.24,221.651],[179.888,206.587],[183.067,204.708],[183.95,202.591],[191.943,189.756],[195.86,190.661],[197.902,189.842],[213.097,187.196],[213.916,188.352],[214.807,190.385]]}}},{"ty":"gf","hd":false,"bm":0,"e":{"a":0,"k":[181.06333210881155,229.40161895755392]},"g":{"p":2,"k":{"a":0,"k":[0,1,1,1,1,1,1,1,0,1,1,0.17]}},"t":1,"a":{"a":0,"k":0},"h":{"a":0,"k":0},"o":{"a":0,"k":100},"r":1,"s":{"a":0,"k":[206.50000143633156,187.198288879985]}},{"ty":"tr","nm":"Transform","a":{"a":0,"k":[0,0]},"o":{"a":0,"k":100},"p":{"a":0,"k":[0,0]},"r":{"a":0,"k":0},"s":{"a":0,"k":[100,100]},"sk":{"a":0,"k":0},"sa":{"a":0,"k":0}}],"np":0},{"ty":"tr","nm":"Transform","a":{"a":0,"k":[206.501,213.368]},"o":{"a":0,"k":100},"p":{"a":0,"k":[0,-0.001]},"r":{"a":0,"k":0},"s":{"a":0,"k":[100,100]},"sk":{"a":0,"k":0},"sa":{"a":0,"k":0}}],"np":0},{"ty":"gr","hd":false,"nm":"Layer 4 Group","bm":0,"it":[{"ty":"gr","hd":false,"nm":"Path 1 Group","bm":0,"it":[{"ty":"sh","hd":false,"nm":"Path 1","d":1,"ks":{"a":0,"k":{"c":false,"i":[[0,0],[0.184,0.623],[0.38,0.638],[3.349,-5.981],[0.163,-0.444],[0.748,0.367],[1.358,-0.001],[-2.911,-5.918],[0.819,-0.275],[-5.147,-4.534],[-1.187,-0.373],[0.363,-0.781],[-6.829,0.607],[-0.935,0.434],[-0.257,-0.822],[-4.64,5.05],[-0.391,1.257],[-0.78,-0.357],[-2.514,1.498],[2.516,4.226],[-0.583,0.136],[-0.786,0.467],[5.981,3.349],[0.539,0.178],[-0.348,0.762],[6.825,-0.646],[1.134,-0.675]],"o":[[-0.559,0.333],[-0.212,-0.712],[-3.505,-5.891],[-0.231,0.413],[-0.286,0.782],[-1.22,-0.596],[-6.595,-0.002],[0.381,0.775],[-6.5,2.191],[0.934,0.822],[0.822,0.258],[-2.889,6.217],[1.027,-0.091],[0.781,-0.363],[2.054,6.543],[0.891,-0.969],[0.254,-0.82],[2.661,1.22],[4.227,-2.515],[-0.307,-0.515],[0.889,-0.21],[5.891,-3.505],[-0.496,-0.278],[-0.795,-0.262],[2.853,-6.233],[-1.314,0.124],[0,0]],"v":[[216.35,190.99],[214.807,190.385],[213.916,188.352],[198.493,188.555],[197.902,189.842],[195.86,190.661],[191.943,189.756],[183.95,202.591],[183.067,204.708],[180.023,219.837],[183.24,221.651],[184.165,223.741],[193.03,236.365],[195.994,235.571],[198.084,236.495],[213.145,239.854],[215.091,236.473],[217.168,235.543],[225.433,235.098],[228.531,222.891],[229.121,221.505],[231.648,220.483],[231.445,205.06],[229.889,204.375],[229.004,202.347],[220.068,189.775],[216.35,190.99]]}}},{"ty":"fl","hd":false,"bm":0,"c":{"a":0,"k":[0.435,0.42,1]},"r":1,"o":{"a":0,"k":92}},{"ty":"tr","nm":"Transform","a":{"a":0,"k":[0,0]},"o":{"a":0,"k":100},"p":{"a":0,"k":[0,0]},"r":{"a":0,"k":0},"s":{"a":0,"k":[100,100]},"sk":{"a":0,"k":0},"sa":{"a":0,"k":0}}],"np":0},{"ty":"tr","nm":"Transform","a":{"a":0,"k":[206.5,213.37]},"o":{"a":0,"k":100},"p":{"a":0,"k":[-0.001,0.001]},"r":{"a":0,"k":0},"s":{"a":0,"k":[100,100]},"sk":{"a":0,"k":0},"sa":{"a":0,"k":0}}],"np":0}]},{"ddd":0,"ind":17,"ty":4,"nm":"Layer 5","hd":false,"sr":1,"ks":{"a":{"a":0,"k":[165.37,189.037]},"o":{"a":1,"k":[{"t":0,"s":[0],"i":{"x":0.75,"y":0.75},"o":{"x":0.25,"y":0.25}},{"t":12.3,"s":[0],"i":{"x":0.75,"y":0.75},"o":{"x":0.25,"y":0.25}},{"t":37.5,"s":[100],"i":{"x":0,"y":0},"o":{"x":1,"y":1}}]},"p":{"a":1,"k":[{"t":0,"s":[139.406,215.216],"i":{"x":0.75,"y":0.75},"o":{"x":0.25,"y":0.25},"ti":[0,0],"to":[0,0]},{"t":38.4,"s":[164.367,187.038],"i":{"x":0,"y":0},"o":{"x":1,"y":1}}]},"r":{"a":0,"k":0},"s":{"a":0,"k":[100,100]},"sk":{"a":0,"k":0},"sa":{"a":0,"k":0}},"ao":0,"ip":0,"op":121,"st":0,"bm":0,"shapes":[{"ty":"gr","hd":false,"nm":"Path 1 Group","bm":0,"it":[{"ty":"sh","hd":false,"nm":"Path 1","d":1,"ks":{"a":0,"k":{"c":true,"i":[[0,0],[0,0],[0,-0.583],[0,0],[0.583,0],[0,0],[0,0.583],[0,0],[-0.583,0]],"o":[[0,0],[0.583,0],[0,0],[0,0.583],[0,0],[-0.583,0],[0,0],[0,-0.583],[0,0]],"v":[[187.793,164.328],[250.98,164.328],[252.036,165.383],[252.036,165.383],[250.98,166.439],[187.793,166.439],[186.737,165.383],[186.737,165.383],[187.793,164.328]]}}},{"ty":"gf","hd":false,"bm":0,"e":{"a":0,"k":[245.67433684226214,165.3093311347346]},"g":{"p":2,"k":{"a":0,"k":[0,0.933,0.933,1,1,0.882,0.878,1,0,1,1,0]}},"t":1,"a":{"a":0,"k":0},"h":{"a":0,"k":0},"o":{"a":0,"k":100},"r":1,"s":{"a":0,"k":[186.736998597057,165.38400256454094]}},{"ty":"tr","nm":"Transform","a":{"a":0,"k":[186.737,164.328]},"o":{"a":0,"k":100},"p":{"a":0,"k":[186.737,164.328]},"r":{"a":0,"k":129},"s":{"a":0,"k":[100,100]},"sk":{"a":0,"k":0},"sa":{"a":0,"k":0}}],"np":0}]},{"ddd":0,"ind":19,"ty":4,"nm":"Group 5","hd":false,"sr":1,"ks":{"a":{"a":0,"k":[0,0]},"o":{"a":1,"k":[{"t":0,"s":[0],"i":{"x":0.75,"y":0.75},"o":{"x":0.25,"y":0.25}},{"t":10.8,"s":[0],"i":{"x":0.75,"y":0.75},"o":{"x":0.25,"y":0.25}},{"t":21.6,"s":[50],"i":{"x":0,"y":0},"o":{"x":1,"y":1}}]},"p":{"a":0,"k":[4.861,243.541]},"r":{"a":0,"k":0},"s":{"a":0,"k":[100,100]},"sk":{"a":0,"k":0},"sa":{"a":0,"k":0}},"ao":0,"ip":0,"op":121,"st":0,"bm":0,"shapes":[{"ty":"gr","hd":false,"nm":"Layer 6 Group","bm":0,"it":[{"ty":"gr","hd":false,"nm":"Path 1 Group","bm":0,"it":[{"ty":"sh","hd":false,"nm":"Path 1","d":1,"ks":{"a":0,"k":{"c":true,"i":[[0,0],[0,0],[0,-0.409],[0,0],[0.409,0],[0,0],[0,0.409],[0,0],[-0.409,0]],"o":[[0,0],[0.409,0],[0,0],[0,0.409],[0,0],[-0.409,0],[0,0],[0,-0.409],[0,0]],"v":[[26.735,203.461],[71.081,203.461],[71.822,204.202],[71.822,204.202],[71.081,204.943],[26.735,204.943],[25.994,204.202],[25.994,204.202],[26.735,203.461]]}}},{"ty":"gf","hd":false,"bm":0,"e":{"a":0,"k":[104.30932593088706,196.79933671622064]},"g":{"p":2,"k":{"a":0,"k":[0,0.933,0.933,1,1,0.576,0.569,1,0,1,1,0.45]}},"t":1,"a":{"a":0,"k":0},"h":{"a":0,"k":0},"o":{"a":0,"k":100},"r":1,"s":{"a":0,"k":[25.993990751443846,204.20199599946645]}},{"ty":"tr","nm":"Transform","a":{"a":0,"k":[25.994,203.461]},"o":{"a":0,"k":100},"p":{"a":0,"k":[25.994,203.461]},"r":{"a":0,"k":129},"s":{"a":0,"k":[100,100]},"sk":{"a":0,"k":0},"sa":{"a":0,"k":0}}],"np":0},{"ty":"tr","nm":"Transform","a":{"a":0,"k":[10.998,220.802]},"o":{"a":0,"k":100},"p":{"a":0,"k":[-2.758,3.264]},"r":{"a":0,"k":0},"s":{"a":0,"k":[100,100]},"sk":{"a":0,"k":0},"sa":{"a":0,"k":0}}],"np":0},{"ty":"gr","hd":false,"nm":"Layer 15 Group","bm":0,"it":[{"ty":"gr","hd":false,"nm":"Path 1 Group","bm":0,"it":[{"ty":"sh","hd":false,"nm":"Path 1","d":1,"ks":{"a":0,"k":{"c":true,"i":[[0,0],[0.969,0],[0,0.969],[-0.969,0],[0,-0.969]],"o":[[0,0.969],[-0.969,0],[0,-0.969],[0.969,0],[0,0]],"v":[[31.51,197.755],[29.755,199.51],[28,197.755],[29.755,196],[31.51,197.755]]}}},{"ty":"fl","hd":false,"bm":0,"c":{"a":0,"k":[1,1,1]},"r":1,"o":{"a":0,"k":100}},{"ty":"tr","nm":"Transform","a":{"a":0,"k":[0,0]},"o":{"a":0,"k":100},"p":{"a":0,"k":[0,0]},"r":{"a":0,"k":0},"s":{"a":0,"k":[100,100]},"sk":{"a":0,"k":0},"sa":{"a":0,"k":0}}],"np":0},{"ty":"tr","nm":"Transform","a":{"a":0,"k":[29.755,197.755]},"o":{"a":0,"k":100},"p":{"a":0,"k":[15.999,-19.783]},"r":{"a":0,"k":0},"s":{"a":0,"k":[100,100]},"sk":{"a":0,"k":0},"sa":{"a":0,"k":0}}],"np":0},{"ty":"tm","hd":false,"bm":0,"e":{"a":0,"k":100},"o":{"a":0,"k":0},"s":{"a":0,"k":0},"m":1}]},{"ddd":0,"ind":24,"ty":4,"nm":"circle","hd":false,"sr":1,"ks":{"a":{"a":0,"k":[311.5,212.5]},"o":{"a":1,"k":[{"t":0,"s":[0],"i":{"x":0.75,"y":0.75},"o":{"x":0.25,"y":0.25}},{"t":48,"s":[0],"i":{"x":0.75,"y":0.75},"o":{"x":0.25,"y":0.25}},{"t":60.9,"s":[50],"i":{"x":0,"y":0},"o":{"x":1,"y":1}}]},"p":{"a":0,"k":[311.5,212.5]},"r":{"a":0,"k":0},"s":{"a":0,"k":[100,100]},"sk":{"a":0,"k":0},"sa":{"a":0,"k":0}},"ao":0,"ip":0,"op":121,"st":0,"bm":0,"shapes":[{"ty":"gr","hd":false,"nm":"Path 1 Group","bm":0,"it":[{"ty":"sh","hd":false,"nm":"Path 1","d":1,"ks":{"a":0,"k":{"c":true,"i":[[0,0],[1.381,0],[0,1.381],[-1.381,0],[0,-1.381]],"o":[[0,1.381],[-1.381,0],[0,-1.381],[1.381,0],[0,0]],"v":[[314,212.5],[311.5,215],[309,212.5],[311.5,210],[314,212.5]]}}},{"ty":"fl","hd":false,"bm":0,"c":{"a":0,"k":[1,1,1]},"r":1,"o":{"a":0,"k":100}},{"ty":"tr","nm":"Transform","a":{"a":0,"k":[0,0]},"o":{"a":0,"k":100},"p":{"a":0,"k":[0,0]},"r":{"a":0,"k":0},"s":{"a":0,"k":[100,100]},"sk":{"a":0,"k":0},"sa":{"a":0,"k":0}}],"np":0}]},{"ddd":0,"ind":26,"ty":4,"nm":"white","hd":false,"sr":1,"ks":{"a":{"a":0,"k":[0,0]},"o":{"a":0,"k":100},"p":{"a":0,"k":[0,0]},"r":{"a":0,"k":0},"s":{"a":0,"k":[100,100]},"sk":{"a":0,"k":0},"sa":{"a":0,"k":0}},"ao":0,"ip":0,"op":121,"st":0,"bm":0,"shapes":[{"ty":"sh","hd":false,"nm":"white","d":1,"ks":{"a":0,"k":{"c":true,"i":[[0,0],[83.671,0],[0,83.671],[-83.671,0],[0,-83.671]],"o":[[0,83.671],[-83.671,0],[0,-83.671],[83.671,0],[0,0]],"v":[[420,32.5],[268.5,184],[117,32.5],[268.5,-119],[420,32.5]]}}},{"ty":"gf","hd":false,"bm":0,"e":{"a":0,"k":[268.5,175.33557625758897]},"g":{"p":2,"k":{"a":0,"k":[0,1,1,1,1,1,1,1,0,1,1,0]}},"t":2,"a":{"a":0,"k":0},"h":{"a":0,"k":0},"o":{"a":0,"k":100},"r":1,"s":{"a":0,"k":[268.5,32.5]}}]},{"ddd":0,"ind":27,"ty":4,"nm":"line","hd":false,"sr":1,"ks":{"a":{"a":0,"k":[268.5,84.037]},"o":{"a":1,"k":[{"t":0,"s":[0],"i":{"x":0.75,"y":0.75},"o":{"x":0.25,"y":0.25}},{"t":10.2,"s":[0],"i":{"x":0.75,"y":0.75},"o":{"x":0.25,"y":0.25}},{"t":33.6,"s":[100],"i":{"x":0,"y":0},"o":{"x":1,"y":1}}]},"p":{"a":1,"k":[{"t":0,"s":[256.5,101.037],"i":{"x":0.75,"y":0.75},"o":{"x":0.25,"y":0.25},"ti":[0,0],"to":[0,0]},{"t":33.6,"s":[268.5,84.037],"i":{"x":0,"y":0},"o":{"x":1,"y":1}}]},"r":{"a":0,"k":0},"s":{"a":0,"k":[100,100]},"sk":{"a":0,"k":0},"sa":{"a":0,"k":0}},"ao":0,"ip":0,"op":121,"st":0,"bm":0,"shapes":[{"ty":"gr","hd":false,"nm":"Path 1 Group","bm":0,"it":[{"ty":"sh","hd":false,"nm":"Path 1","d":1,"ks":{"a":0,"k":{"c":true,"i":[[0,0],[0,0],[0,-0.583],[0,0],[0.583,0],[0,0],[0,0.583],[0,0],[-0.583,0]],"o":[[0,0],[0.583,0],[0,0],[0,0.583],[0,0],[-0.583,0],[0,0],[0,-0.583],[0,0]],"v":[[294.793,236.328],[357.98,236.328],[359.036,237.383],[359.036,237.383],[357.98,238.439],[294.793,238.439],[293.737,237.383],[293.737,237.383],[294.793,236.328]]}}},{"ty":"gf","hd":false,"bm":0,"e":{"a":0,"k":[359.1203238096947,237.46733608097176]},"g":{"p":2,"k":{"a":0,"k":[0,0.933,0.933,1,1,0.576,0.569,1,0,1,1,1]}},"t":1,"a":{"a":0,"k":0},"h":{"a":0,"k":0},"o":{"a":0,"k":100},"r":1,"s":{"a":0,"k":[293.73699889722417,237.38400274205353]}},{"ty":"tr","nm":"Transform","a":{"a":0,"k":[293.737,236.328]},"o":{"a":0,"k":100},"p":{"a":0,"k":[293.737,236.328]},"r":{"a":0,"k":129},"s":{"a":0,"k":[100,100]},"sk":{"a":0,"k":0},"sa":{"a":0,"k":0}}],"np":0}]},{"ddd":0,"ind":29,"ty":4,"nm":"circle","hd":false,"sr":1,"ks":{"a":{"a":0,"k":[300.499,226.5]},"o":{"a":1,"k":[{"t":0,"s":[0],"i":{"x":0.75,"y":0.75},"o":{"x":0.25,"y":0.25}},{"t":36.9,"s":[0],"i":{"x":0.75,"y":0.75},"o":{"x":0.25,"y":0.25}},{"t":53.7,"s":[100],"i":{"x":0,"y":0},"o":{"x":1,"y":1}}]},"p":{"a":0,"k":[300.499,226.5]},"r":{"a":0,"k":0},"s":{"a":0,"k":[100,100]},"sk":{"a":0,"k":0},"sa":{"a":0,"k":0}},"ao":0,"ip":0,"op":121,"st":0,"bm":0,"shapes":[{"ty":"gr","hd":false,"nm":"Path 1 Group","bm":0,"it":[{"ty":"sh","hd":false,"nm":"Path 1","d":1,"ks":{"a":0,"k":{"c":true,"i":[[0,0],[1.381,0],[0,1.381],[-1.381,0],[0,-1.381]],"o":[[0,1.381],[-1.381,0],[0,-1.381],[1.381,0],[0,0]],"v":[[302.999,226.5],[300.499,229],[297.999,226.5],[300.499,224],[302.999,226.5]]}}},{"ty":"fl","hd":false,"bm":0,"c":{"a":0,"k":[1,1,1]},"r":1,"o":{"a":0,"k":100}},{"ty":"tr","nm":"Transform","a":{"a":0,"k":[0,0]},"o":{"a":0,"k":100},"p":{"a":0,"k":[0,0]},"r":{"a":0,"k":0},"s":{"a":0,"k":[100,100]},"sk":{"a":0,"k":0},"sa":{"a":0,"k":0}}],"np":0}]},{"ddd":0,"ind":31,"ty":4,"nm":"lili","hd":false,"sr":1,"ks":{"a":{"a":0,"k":[107.737,257.328]},"o":{"a":1,"k":[{"t":0,"s":[0],"i":{"x":0.75,"y":0.75},"o":{"x":0.25,"y":0.25}},{"t":12,"s":[0],"i":{"x":0.75,"y":0.75},"o":{"x":0.25,"y":0.25}},{"t":27.3,"s":[80],"i":{"x":0,"y":0},"o":{"x":1,"y":1}}]},"p":{"a":0,"k":[107.737,257.328]},"r":{"a":0,"k":129},"s":{"a":0,"k":[100,100]},"sk":{"a":0,"k":0},"sa":{"a":0,"k":0}},"ao":0,"ip":0,"op":121,"st":0,"bm":0,"shapes":[{"ty":"sh","hd":false,"nm":"lili","d":1,"ks":{"a":0,"k":{"c":true,"i":[[0,0],[0,0],[0,-0.583],[0,0],[0.583,0],[0,0],[0,0.583],[0,0],[-0.583,0]],"o":[[0,0],[0.583,0],[0,0],[0,0.583],[0,0],[-0.583,0],[0,0],[0,-0.583],[0,0]],"v":[[108.793,257.328],[171.98,257.328],[173.036,258.384],[173.036,258.384],[171.98,259.439],[108.793,259.439],[107.737,258.384],[107.737,258.384],[108.793,257.328]]}}},{"ty":"gf","hd":false,"bm":0,"e":{"a":0,"k":[173.12034009939043,258.46733608229556]},"g":{"p":2,"k":{"a":0,"k":[0,0.933,0.933,1,1,0.576,0.569,1,0,1,1,1]}},"t":1,"a":{"a":0,"k":0},"h":{"a":0,"k":0},"o":{"a":1,"k":[{"t":0,"s":[100],"i":{"x":0.75,"y":0.75},"o":{"x":0.25,"y":0.25}},{"t":12,"s":[0],"i":{"x":0.75,"y":0.75},"o":{"x":0.25,"y":0.25}},{"t":27.3,"s":[75],"i":{"x":0,"y":0},"o":{"x":1,"y":1}}]},"r":1,"s":{"a":0,"k":[107.73699950629775,258.3840027429502]}}]},{"ddd":0,"ind":32,"ty":4,"nm":"circir","hd":false,"sr":1,"ks":{"a":{"a":0,"k":[0,0]},"o":{"a":1,"k":[{"t":0,"s":[0],"i":{"x":0.75,"y":0.75},"o":{"x":0.25,"y":0.25}},{"t":28.8,"s":[0],"i":{"x":0.75,"y":0.75},"o":{"x":0.25,"y":0.25}},{"t":39,"s":[100],"i":{"x":0,"y":0},"o":{"x":1,"y":1}}]},"p":{"a":0,"k":[0,0]},"r":{"a":0,"k":0},"s":{"a":0,"k":[100,100]},"sk":{"a":0,"k":0},"sa":{"a":0,"k":0}},"ao":0,"ip":0,"op":121,"st":0,"bm":0,"shapes":[{"ty":"sh","hd":false,"nm":"circir","d":1,"ks":{"a":0,"k":{"c":true,"i":[[0,0],[1.105,0],[0,1.105],[-1.105,0],[0,-1.105]],"o":[[0,1.105],[-1.105,0],[0,-1.105],[1.105,0],[0,0]],"v":[[121,241],[119,243],[117,241],[119,239],[121,241]]}}},{"ty":"fl","hd":false,"bm":0,"c":{"a":0,"k":[1,1,1]},"r":1,"o":{"a":0,"k":100}}]},{"ddd":0,"ind":33,"ty":4,"nm":"white1","hd":false,"sr":1,"ks":{"a":{"a":0,"k":[108,32.5]},"o":{"a":0,"k":100},"p":{"a":0,"k":[108,32.5]},"r":{"a":0,"k":0},"s":{"a":0,"k":[100,100]},"sk":{"a":0,"k":0},"sa":{"a":0,"k":0}},"ao":0,"ip":0,"op":121,"st":0,"bm":0,"shapes":[{"ty":"gr","hd":false,"nm":"Path 1 Group","bm":0,"it":[{"ty":"sh","hd":false,"nm":"Path 1","d":1,"ks":{"a":0,"k":{"c":true,"i":[[0,0],[83.671,0],[0,83.671],[-83.671,0],[0,-83.671]],"o":[[0,83.671],[-83.671,0],[0,-83.671],[83.671,0],[0,0]],"v":[[202,32.5],[50.5,184],[-101,32.5],[50.5,-119],[202,32.5]]}}},{"ty":"gf","hd":false,"bm":0,"e":{"a":0,"k":[50.5,175.33557625758897]},"g":{"p":2,"k":{"a":0,"k":[0,1,1,1,1,1,1,1,0,1,1,0]}},"t":2,"a":{"a":0,"k":0},"h":{"a":0,"k":0},"o":{"a":0,"k":100},"r":1,"s":{"a":0,"k":[50.5,32.5]}},{"ty":"tr","nm":"Transform","a":{"a":0,"k":[0,0]},"o":{"a":0,"k":100},"p":{"a":0,"k":[0,0]},"r":{"a":0,"k":0},"s":{"a":0,"k":[100,100]},"sk":{"a":0,"k":0},"sa":{"a":0,"k":0}}],"np":0},{"ty":"gr","hd":false,"nm":"Path 1 Group","bm":0,"it":[{"ty":"sh","hd":false,"nm":"Path 1","d":1,"ks":{"a":0,"k":{"c":true,"i":[[0,0],[83.671,0],[0,83.671],[-83.671,0],[0,-83.671]],"o":[[0,83.671],[-83.671,0],[0,-83.671],[83.671,0],[0,0]],"v":[[317,32.5],[165.5,184],[14,32.5],[165.5,-119],[317,32.5]]}}},{"ty":"gf","hd":false,"bm":0,"e":{"a":0,"k":[165.5,175.33557625758897]},"g":{"p":2,"k":{"a":0,"k":[0,1,1,1,1,1,1,1,0,1,1,0]}},"t":2,"a":{"a":0,"k":0},"h":{"a":0,"k":0},"o":{"a":0,"k":100},"r":1,"s":{"a":0,"k":[165.5,32.5]}},{"ty":"tr","nm":"Transform","a":{"a":0,"k":[0,0]},"o":{"a":0,"k":100},"p":{"a":0,"k":[0,0]},"r":{"a":0,"k":0},"s":{"a":0,"k":[100,100]},"sk":{"a":0,"k":0},"sa":{"a":0,"k":0}}],"np":0}]},{"ddd":0,"ind":36,"ty":4,"nm":"star3","hd":false,"sr":1,"ks":{"a":{"a":0,"k":[103.4,185.401]},"o":{"a":0,"k":100},"p":{"a":0,"k":[103.4,185.401]},"r":{"a":1,"k":[{"t":0,"s":[0],"i":{"x":0.5,"y":1},"o":{"x":0.12,"y":0.23}},{"t":106.8,"s":[360],"i":{"x":0,"y":0},"o":{"x":1,"y":1}}]},"s":{"a":0,"k":[100,100]},"sk":{"a":0,"k":0},"sa":{"a":0,"k":0}},"ao":0,"ip":0,"op":121,"st":0,"bm":0,"shapes":[{"ty":"gr","hd":false,"nm":"Path 1 Group","bm":0,"it":[{"ty":"sh","hd":false,"nm":"Path 1","d":1,"ks":{"a":0,"k":{"c":false,"i":[[0,0],[0,0],[0,0],[-0.776,-1.197],[0,0],[0,0],[0.297,-1.395],[0,0],[0,0],[1.196,-0.776],[0,0],[0,0],[1.394,0.297],[0,0],[0,0],[0.776,1.197],[0,0],[0,0],[-0.297,1.395],[0,0],[0,0],[-1.197,0.776],[0,0],[0,0],[-1.394,-0.297]],"o":[[0,0],[0,0],[-0.186,-1.414],[0,0],[0,0],[0.868,-1.131],[0,0],[0,0],[1.413,-0.187],[0,0],[0,0],[1.131,0.868],[0,0],[0,0],[0.186,1.413],[0,0],[0,0],[-0.868,1.131],[0,0],[0,0],[-1.414,0.187],[0,0],[0,0],[-1.131,-0.868],[0,0]],"v":[[97.092,182.054],[99.945,182.662],[99.564,179.77],[102.013,178.867],[103.601,181.314],[105.376,179],[107.746,180.093],[107.138,182.946],[110.031,182.565],[110.934,185.014],[108.486,186.602],[110.801,188.377],[109.708,190.747],[106.855,190.139],[107.236,193.032],[104.786,193.934],[103.199,191.487],[101.423,193.801],[99.053,192.708],[99.661,189.856],[96.769,190.236],[95.866,187.787],[98.313,186.199],[96,184.424],[97.093,182.054]]}}},{"ty":"fl","hd":false,"bm":0,"c":{"a":0,"k":[1,1,1]},"r":1,"o":{"a":0,"k":100}},{"ty":"tr","nm":"Transform","a":{"a":0,"k":[0,0]},"o":{"a":0,"k":100},"p":{"a":0,"k":[0,-1]},"r":{"a":0,"k":0},"s":{"a":0,"k":[100,100]},"sk":{"a":0,"k":0},"sa":{"a":0,"k":0}}],"np":0}]},{"ddd":0,"ind":38,"ty":4,"nm":"star2","hd":false,"sr":1,"ks":{"a":{"a":0,"k":[368.792,200.792]},"o":{"a":1,"k":[{"t":0,"s":[0],"i":{"x":0.75,"y":0.75},"o":{"x":0.25,"y":0.25}},{"t":43.8,"s":[100],"i":{"x":0,"y":0},"o":{"x":1,"y":1}}]},"p":{"a":0,"k":[368.792,200.792]},"r":{"a":1,"k":[{"t":0,"s":[0],"i":{"x":0.5,"y":1},"o":{"x":0.12,"y":0.23}},{"t":96,"s":[360],"i":{"x":0,"y":0},"o":{"x":1,"y":1}}]},"s":{"a":0,"k":[100,100]},"sk":{"a":0,"k":0},"sa":{"a":0,"k":0}},"ao":0,"ip":0,"op":121,"st":0,"bm":0,"shapes":[{"ty":"gr","hd":false,"nm":"Path 1 Group","bm":0,"it":[{"ty":"sh","hd":false,"nm":"Path 1","d":1,"ks":{"a":0,"k":{"c":false,"i":[[0,0],[0,0],[0,0],[-1.483,-2.286],[0,0],[0,0],[0.568,-2.665],[0,0],[0,0],[2.287,-1.483],[0,0],[0,0],[2.665,0.568],[0,0],[0,0],[1.483,2.286],[0,0],[0,0],[-0.568,2.665],[0,0],[0,0],[-2.287,1.483],[0,0],[0,0],[-2.666,-0.568]],"o":[[0,0],[0,0],[-0.356,-2.702],[0,0],[0,0],[1.659,-2.162],[0,0],[0,0],[2.702,-0.356],[0,0],[0,0],[2.162,1.659],[0,0],[0,0],[0.356,2.702],[0,0],[0,0],[-1.659,2.162],[0,0],[0,0],[-2.702,0.356],[0,0],[0,0],[-2.162,-1.659],[0,0]],"v":[[356.734,192.483],[362.187,193.645],[361.459,188.116],[366.141,186.39],[369.176,191.068],[372.57,186.644],[377.1,188.734],[375.939,194.187],[381.467,193.459],[383.193,198.141],[378.515,201.176],[382.939,204.57],[380.85,209.1],[375.396,207.939],[376.124,213.467],[371.442,215.194],[368.407,210.515],[365.013,214.939],[360.483,212.85],[361.645,207.396],[356.116,208.124],[354.39,203.443],[359.068,200.407],[354.644,197.013],[356.734,192.483]]}}},{"ty":"fl","hd":false,"bm":0,"c":{"a":0,"k":[0.886,0.882,1]},"r":1,"o":{"a":0,"k":100}},{"ty":"tr","nm":"Transform","a":{"a":0,"k":[0,0]},"o":{"a":0,"k":100},"p":{"a":0,"k":[0,0]},"r":{"a":0,"k":0},"s":{"a":0,"k":[100,100]},"sk":{"a":0,"k":0},"sa":{"a":0,"k":0}}],"np":0}]},{"ddd":0,"ind":40,"ty":4,"nm":"circircir","hd":false,"sr":1,"ks":{"a":{"a":0,"k":[194.499,150.5]},"o":{"a":0,"k":100},"p":{"a":0,"k":[194.499,150.5]},"r":{"a":0,"k":0},"s":{"a":0,"k":[100,100]},"sk":{"a":0,"k":0},"sa":{"a":0,"k":0}},"ao":0,"ip":0,"op":121,"st":0,"bm":0,"shapes":[{"ty":"gr","hd":false,"nm":"cicicici Group","bm":0,"it":[{"ty":"sh","hd":false,"nm":"cicicici","d":1,"ks":{"a":0,"k":{"c":true,"i":[[0,0],[1.381,0],[0,1.381],[-1.381,0],[0,-1.381]],"o":[[0,1.381],[-1.381,0],[0,-1.381],[1.381,0],[0,0]],"v":[[196.999,150.5],[194.499,153],[191.999,150.5],[194.499,148],[196.999,150.5]]}}},{"ty":"fl","hd":false,"bm":0,"c":{"a":0,"k":[1,1,1]},"r":1,"o":{"a":0,"k":100}},{"ty":"tr","nm":"Transform","a":{"a":0,"k":[0,0]},"o":{"a":1,"k":[{"t":0,"s":[0],"i":{"x":0.75,"y":0.75},"o":{"x":0.25,"y":0.25}},{"t":41.4,"s":[0],"i":{"x":0.75,"y":0.75},"o":{"x":0.25,"y":0.25}},{"t":55.2,"s":[100],"i":{"x":0,"y":0},"o":{"x":1,"y":1}}]},"p":{"a":0,"k":[0,0]},"r":{"a":0,"k":0},"s":{"a":0,"k":[100,100]},"sk":{"a":0,"k":0},"sa":{"a":0,"k":0}}],"np":0}]},{"ddd":0,"ind":42,"ty":4,"nm":"white","hd":false,"sr":1,"ks":{"a":{"a":0,"k":[94.5,23.5]},"o":{"a":0,"k":100},"p":{"a":0,"k":[94.5,23.5]},"r":{"a":0,"k":0},"s":{"a":0,"k":[100,100]},"sk":{"a":0,"k":0},"sa":{"a":0,"k":0}},"ao":0,"ip":0,"op":121,"st":0,"bm":0,"shapes":[{"ty":"gr","hd":false,"nm":"Path 1 Group","bm":0,"it":[{"ty":"sh","hd":false,"nm":"Path 1","d":1,"ks":{"a":0,"k":{"c":true,"i":[[0,0],[83.671,0],[0,83.671],[-83.671,0],[0,-83.671]],"o":[[0,83.671],[-83.671,0],[0,-83.671],[83.671,0],[0,0]],"v":[[246,23.5],[94.5,175],[-57,23.5],[94.5,-128],[246,23.5]]}}},{"ty":"gf","hd":false,"bm":0,"e":{"a":0,"k":[94.5,166.33557625758897]},"g":{"p":2,"k":{"a":0,"k":[0,1,1,1,1,1,1,1,0,1,1,0]}},"t":2,"a":{"a":0,"k":0},"h":{"a":0,"k":0},"o":{"a":0,"k":100},"r":1,"s":{"a":0,"k":[94.5,23.5]}},{"ty":"tr","nm":"Transform","a":{"a":0,"k":[0,0]},"o":{"a":0,"k":100},"p":{"a":0,"k":[0,0]},"r":{"a":0,"k":0},"s":{"a":0,"k":[100,100]},"sk":{"a":0,"k":0},"sa":{"a":0,"k":0}}],"np":0}]},{"ddd":0,"ind":44,"ty":4,"nm":"circle1","hd":false,"sr":1,"ks":{"a":{"a":0,"k":[350,159]},"o":{"a":1,"k":[{"t":0,"s":[0],"i":{"x":0.75,"y":0.75},"o":{"x":0.25,"y":0.25}},{"t":37.5,"s":[0],"i":{"x":0.75,"y":0.75},"o":{"x":0.25,"y":0.25}},{"t":72.3,"s":[75],"i":{"x":0,"y":0},"o":{"x":1,"y":1}}]},"p":{"a":0,"k":[350,159]},"r":{"a":0,"k":0},"s":{"a":0,"k":[100,100]},"sk":{"a":0,"k":0},"sa":{"a":0,"k":0}},"ao":0,"ip":0,"op":121,"st":0,"bm":0,"shapes":[{"ty":"gr","hd":false,"nm":"Path 1 Group","bm":0,"it":[{"ty":"sh","hd":false,"nm":"Path 1","d":1,"ks":{"a":0,"k":{"c":true,"i":[[0,0],[2.209,0],[0,2.209],[-2.209,0],[0,-2.209]],"o":[[0,2.209],[-2.209,0],[0,-2.209],[2.209,0],[0,0]],"v":[[354,159],[350,163],[346,159],[350,155],[354,159]]}}},{"ty":"fl","hd":false,"bm":0,"c":{"a":0,"k":[1,1,1]},"r":1,"o":{"a":1,"k":[{"t":0,"s":[100],"i":{"x":0.75,"y":0.75},"o":{"x":0.25,"y":0.25}},{"t":97.2,"s":[50],"i":{"x":0,"y":0},"o":{"x":1,"y":1}}]}},{"ty":"tr","nm":"Transform","a":{"a":0,"k":[0,0]},"o":{"a":0,"k":100},"p":{"a":0,"k":[0,0]},"r":{"a":0,"k":0},"s":{"a":0,"k":[100,100]},"sk":{"a":0,"k":0},"sa":{"a":0,"k":0}}],"np":0}]},{"ddd":0,"ind":46,"ty":4,"nm":"linecircle","hd":false,"sr":1,"ks":{"a":{"a":0,"k":[273.543,244.543]},"o":{"a":0,"k":100},"p":{"a":1,"k":[{"t":0,"s":[262.543,257.543],"i":{"x":0.75,"y":0.75},"o":{"x":0.25,"y":0.25},"ti":[0,0],"to":[0,0]},{"t":16.5,"s":[273.543,244.543],"i":{"x":0,"y":0},"o":{"x":1,"y":1}}]},"r":{"a":0,"k":0},"s":{"a":0,"k":[100,100]},"sk":{"a":0,"k":0},"sa":{"a":0,"k":0}},"ao":0,"ip":0,"op":121,"st":0,"bm":0,"shapes":[{"ty":"gr","hd":false,"nm":"Layer 25 Group","bm":0,"it":[{"ty":"gr","hd":false,"nm":"Path 1 Group","bm":0,"it":[{"ty":"sh","hd":false,"nm":"Path 1","d":1,"ks":{"a":0,"k":{"c":true,"i":[[0,0],[35.8,0],[0,35.8],[-35.8,0],[0,-35.8]],"o":[[0,35.8],[-35.8,0],[0,-35.8],[35.8,0],[0,0]],"v":[[338.365,244.543],[273.543,309.365],[208.721,244.543],[273.543,179.721],[338.365,244.543]]}}},{"ty":"gf","hd":false,"bm":0,"e":{"a":0,"k":[273.6263325902639,309.4483226228316]},"g":{"p":2,"k":{"a":0,"k":[0.5,1,1,1,1,1,1,1,0.5,0.14,1,1]}},"t":1,"a":{"a":0,"k":0},"h":{"a":0,"k":0},"o":{"a":0,"k":18},"r":1,"s":{"a":0,"k":[273.5429992577774,179.72099304373438]}},{"ty":"tr","nm":"Transform","a":{"a":0,"k":[273.543,244.543]},"o":{"a":0,"k":100},"p":{"a":0,"k":[273.543,244.543]},"r":{"a":0,"k":24},"s":{"a":0,"k":[100,100]},"sk":{"a":0,"k":0},"sa":{"a":0,"k":0}}],"np":0},{"ty":"tr","nm":"Transform","a":{"a":0,"k":[273.543,244.543]},"o":{"a":0,"k":100},"p":{"a":0,"k":[273.543,244.543]},"r":{"a":0,"k":0},"s":{"a":0,"k":[100,100]},"sk":{"a":0,"k":0},"sa":{"a":0,"k":0}}],"np":0},{"ty":"gr","hd":false,"nm":"Path 1 Group","bm":0,"it":[{"ty":"sh","hd":false,"nm":"Path 1","d":1,"ks":{"a":0,"k":{"c":true,"i":[[0,0],[34.696,0],[0,34.696],[-34.696,0],[0,-34.696]],"o":[[0,34.696],[-34.696,0],[0,-34.696],[34.696,0],[0,0]],"v":[[336.365,244.543],[273.543,307.365],[210.721,244.543],[273.543,181.721],[336.365,244.543]]}}},{"ty":"gs","hd":false,"bm":0,"o":{"a":0,"k":100},"e":{"a":1,"k":[{"t":0,"s":[271.5133262594674,289.2793410688357],"i":{"x":0,"y":0},"o":{"x":1,"y":1}},{"t":120,"s":[271.5133262594674,289.2793410688357],"i":{"x":0,"y":0},"o":{"x":1,"y":1}}]},"g":{"p":2,"k":{"a":1,"k":[{"t":0,"s":[0,1,1,1,1,1,1,1,0,1,1,0],"i":{"x":0.75,"y":0.75},"o":{"x":0.25,"y":0.25}},{"t":120,"s":[0,1,1,1,0.81,1,1,1,0,1,0.81,0],"i":{"x":0,"y":0},"o":{"x":1,"y":1}}]}},"t":1,"a":{"a":0,"k":0},"h":{"a":0,"k":0},"s":{"a":1,"k":[{"t":0,"s":[273.5429995378976,179.72099289405037],"i":{"x":0,"y":0},"o":{"x":1,"y":1}},{"t":120,"s":[273.5429995378976,179.72099289405037],"i":{"x":0,"y":0},"o":{"x":1,"y":1}}]},"lc":1,"lj":1,"ml":4,"w":{"a":0,"k":4}},{"ty":"tr","nm":"Transform","a":{"a":0,"k":[273.543,244.543]},"o":{"a":0,"k":100},"p":{"a":0,"k":[273.543,244.543]},"r":{"a":0,"k":24},"s":{"a":0,"k":[100,100]},"sk":{"a":0,"k":0},"sa":{"a":0,"k":0}}],"np":0}]},{"ddd":0,"ind":50,"ty":4,"nm":"bar3","hd":false,"sr":1,"ks":{"a":{"a":0,"k":[137.596,322.886]},"o":{"a":1,"k":[{"t":0,"s":[50],"i":{"x":0.75,"y":0.75},"o":{"x":0.25,"y":0.25}},{"t":18.9,"s":[100],"i":{"x":0,"y":0},"o":{"x":1,"y":1}}]},"p":{"a":1,"k":[{"t":0,"s":[115.596,346.886],"i":{"x":0.88,"y":0.77},"o":{"x":0.5,"y":0},"ti":[0,0],"to":[0,0]},{"t":18.9,"s":[137.596,322.886],"i":{"x":0,"y":0},"o":{"x":1,"y":1}}]},"r":{"a":0,"k":0},"s":{"a":0,"k":[100,100]},"sk":{"a":0,"k":0},"sa":{"a":0,"k":0}},"ao":0,"ip":0,"op":121,"st":0,"bm":0,"shapes":[{"ty":"gr","hd":false,"nm":"Path 1 Group","bm":0,"it":[{"ty":"sh","hd":false,"nm":"Path 1","d":1,"ks":{"a":0,"k":{"c":true,"i":[[0,0],[0,0],[0,-25.256],[0,0],[25.256,0],[0,0],[0,25.256],[0,0],[-25.256,0]],"o":[[0,0],[25.256,0],[0,0],[0,25.256],[0,0],[-25.256,0],[0,0],[0,-25.256],[0,0]],"v":[[363.107,178.201],[722.809,178.201],[768.539,223.931],[768.539,229.797],[722.809,275.527],[363.107,275.527],[317.377,229.797],[317.377,223.931],[363.107,178.201]]}}},{"ty":"gf","hd":false,"bm":0,"e":{"a":0,"k":[768.6223207839564,226.9473335769283]},"g":{"p":3,"k":{"a":0,"k":[0,0.914,0.898,1,0,0.922,0.91,1,1,1,1,1,0,1,0,1,1,1]}},"t":1,"a":{"a":0,"k":0},"h":{"a":0,"k":0},"o":{"a":0,"k":20},"r":1,"s":{"a":0,"k":[317.37701657338135,226.8640002407687]}},{"ty":"tr","nm":"Transform","a":{"a":0,"k":[317.377,178.201]},"o":{"a":0,"k":100},"p":{"a":0,"k":[317.377,178.201]},"r":{"a":0,"k":129},"s":{"a":0,"k":[100,100]},"sk":{"a":0,"k":0},"sa":{"a":0,"k":0}}],"np":0}]},{"ddd":0,"ind":52,"ty":4,"nm":"star0","hd":false,"sr":1,"ks":{"a":{"a":0,"k":[0,0]},"o":{"a":0,"k":100},"p":{"a":0,"k":[299.354,133.138]},"r":{"a":1,"k":[{"t":0,"s":[0],"i":{"x":0.5,"y":1},"o":{"x":0.12,"y":0.23}},{"t":120,"s":[360],"i":{"x":0,"y":0},"o":{"x":1,"y":1}}]},"s":{"a":0,"k":[100,100]},"sk":{"a":0,"k":0},"sa":{"a":0,"k":0}},"ao":0,"ip":0,"op":121,"st":0,"bm":0,"shapes":[{"ty":"gr","hd":false,"nm":"Layer 26 Group","bm":0,"it":[{"ty":"gr","hd":false,"nm":"Path 1 (2) Group","bm":0,"it":[{"ty":"sh","hd":false,"nm":"Path 1 (2)","d":1,"ks":{"a":0,"k":{"c":false,"i":[[0,0],[0.334,0.729],[4.821,-2.21],[0.973,-1.98],[1.921,1.213],[1.455,0.155],[0.567,-5.273],[-0.503,-1.38],[0.496,-0.904],[1.209,-0.267],[0.442,-4.1],[-3.748,-1.632],[-0.314,-0.981],[0.638,-1.059],[0.148,-1.388],[-5.273,-0.566],[-1.321,0.451],[-0.891,-0.515],[-0.241,-1.211],[-5.555,4.882],[-0.564,1.301],[-0.977,0.317],[-1.058,-0.628],[-2.869,1.318],[2.21,4.821],[-0.442,0.789],[-1.119,0.139],[2.709,5.905],[2.107,0.952],[0.304,0.968],[-0.612,1.032],[1.317,2.866],[4.821,-2.21],[0.822,0.428],[0.204,1.115]],"o":[[-0.145,-0.788],[-2.211,-4.82],[-2.007,0.916],[-1.005,2.041],[-1.239,-0.78],[-5.273,-0.566],[-0.158,1.46],[0.426,1.164],[-0.497,0.904],[-4.026,0.892],[-0.46,4.275],[1.132,0.493],[0.314,0.981],[-0.718,1.197],[-0.567,5.273],[1.388,0.153],[1.17,-0.398],[0.892,0.515],[1.45,7.252],[1.065,-0.936],[0.487,-1.129],[0.977,-0.318],[2.712,1.617],[4.82,-2.21],[-0.472,-1.027],[0.441,-0.79],[6.448,-0.795],[-0.959,-2.104],[-1.094,-0.497],[-0.304,-0.967],[1.613,-2.711],[-2.21,-4.821],[-1.033,0.474],[-0.82,-0.429],[0,0]],"v":[[311.293,104.893],[310.572,102.609],[297.841,97.882],[293.232,102.361],[287.612,103.945],[283.518,102.524],[272.944,111.046],[273.468,115.363],[273.182,118.627],[270.584,120.622],[263.107,128.975],[268.817,138.807],[270.98,141.257],[270.638,144.509],[269.323,148.432],[277.844,159.005],[281.957,158.553],[285.207,158.911],[287.142,161.545],[302.904,166.878],[305.378,163.48],[307.812,161.315],[311.055,161.638],[319.969,162.115],[324.696,149.384],[324.835,146.488],[327.226,144.852],[334.78,131.317],[330.024,126.577],[327.929,124.162],[328.266,120.985],[328.739,112.077],[316.008,107.35],[313.06,107.251],[311.293,104.893]]}}},{"ty":"sh","hd":false,"nm":"Path 1 (2)","d":1,"ks":{"a":0,"k":{"c":false,"i":[[0,0],[-0.77,0.353],[-2.671,-5.824],[1.948,-3.275],[-0.993,-0.45],[-1.161,-2.542],[5.825,-2.671],[1.181,-0.147],[-0.326,-0.709],[5.825,-2.671],[3.276,1.951],[0.444,-1.026],[5.179,0.556],[0.964,4.842],[1.062,-0.362],[1.735,0.186],[-0.685,6.371],[-0.845,1.402],[1.029,0.447],[-0.555,5.168],[-4.733,1.044],[0.387,1.057],[-0.191,1.765],[-6.371,-0.684],[-1.451,-0.916],[-0.48,0.974],[-2.426,1.107],[-2.671,-5.825],[-0.17,-0.931]],"o":[[0.153,0.834],[5.825,-2.67],[1.591,3.463],[-0.556,0.938],[2.545,1.152],[2.671,5.824],[-1.082,0.497],[-0.775,0.096],[2.67,5.825],[-3.465,1.591],[-0.961,-0.571],[-1.963,4.542],[-5.168,-0.556],[-0.219,-1.1],[-1.55,0.527],[-6.371,-0.685],[0.187,-1.735],[0.579,-0.961],[-4.526,-1.971],[0.547,-5.086],[1.099,-0.243],[-0.608,-1.668],[0.684,-6.371],[1.821,0.195],[0.917,0.58],[1.176,-2.393],[5.824,-2.67],[0.412,0.9],[0,0]],"v":[[313.26,104.533],[315.175,105.532],[330.557,111.243],[329.986,122.005],[330.85,124.755],[336.598,130.484],[330.887,145.866],[327.472,146.837],[326.514,148.551],[320.802,163.933],[310.034,163.358],[307.213,164.274],[295.322,171.202],[285.181,161.935],[282.602,160.447],[277.63,160.994],[267.334,148.219],[268.925,143.477],[268.018,140.641],[261.118,128.762],[270.153,118.669],[271.59,116.05],[270.956,110.832],[283.731,100.536],[288.68,102.254],[291.438,101.477],[297.008,96.064],[312.39,101.776],[313.26,104.533]]}}},{"ty":"gf","hd":false,"bm":0,"e":{"a":0,"k":[248.58333866400585,144.64146192540215]},"g":{"p":2,"k":{"a":0,"k":[0,1,1,1,1,1,1,1,0,1,1,0.17]}},"t":1,"a":{"a":0,"k":0},"h":{"a":0,"k":0},"o":{"a":0,"k":100},"r":1,"s":{"a":0,"k":[332.50000474232445,82.5581306565912]}},{"ty":"tr","nm":"Transform","a":{"a":0,"k":[0,0]},"o":{"a":0,"k":100},"p":{"a":0,"k":[0,0]},"r":{"a":0,"k":0},"s":{"a":0,"k":[100,100]},"sk":{"a":0,"k":0},"sa":{"a":0,"k":0}}],"np":0},{"ty":"tr","nm":"Transform","a":{"a":0,"k":[299.354,133.138]},"o":{"a":0,"k":100},"p":{"a":0,"k":[0,0]},"r":{"a":0,"k":0},"s":{"a":0,"k":[100,100]},"sk":{"a":0,"k":0},"sa":{"a":0,"k":0}}],"np":0},{"ty":"gr","hd":false,"nm":"Layer 27 Group","bm":0,"it":[{"ty":"gr","hd":false,"nm":"Path 1 Group","bm":0,"it":[{"ty":"sh","hd":false,"nm":"Path 1","d":1,"ks":{"a":0,"k":{"c":false,"i":[[0,0],[0.153,0.834],[0.403,0.88],[5.824,-2.67],[1.176,-2.393],[0.917,0.58],[1.759,0.186],[0.684,-6.371],[-0.608,-1.668],[1.099,-0.243],[0.547,-5.086],[-4.526,-1.971],[0.579,-0.961],[0.179,-1.678],[-6.371,-0.685],[-1.55,0.527],[-0.219,-1.1],[-5.168,-0.556],[-1.963,4.542],[-0.961,-0.571],[-3.465,1.591],[2.67,5.825],[-0.775,0.096],[-1.082,0.497],[2.671,5.824],[2.545,1.152],[-0.556,0.938],[1.591,3.463],[5.825,-2.67]],"o":[[-0.77,0.353],[-0.175,-0.951],[-2.671,-5.825],[-2.426,1.107],[-0.48,0.974],[-1.496,-0.944],[-6.371,-0.685],[-0.191,1.765],[0.387,1.057],[-4.733,1.044],[-0.555,5.168],[1.029,0.447],[-0.869,1.446],[-0.685,6.371],[1.735,0.186],[1.062,-0.362],[0.964,4.842],[5.179,0.556],[0.444,-1.026],[3.276,1.951],[5.825,-2.671],[-0.326,-0.709],[1.181,-0.147],[5.825,-2.671],[-1.161,-2.542],[-0.993,-0.45],[1.948,-3.275],[-2.671,-5.824],[0,0]],"v":[[315.175,105.532],[313.26,104.533],[312.39,101.776],[297.008,96.064],[291.438,101.477],[288.68,102.254],[283.731,100.536],[270.956,110.832],[271.59,116.05],[270.153,118.669],[261.118,128.762],[268.018,140.641],[268.925,143.477],[267.334,148.219],[277.63,160.994],[282.602,160.447],[285.181,161.935],[295.322,171.202],[307.213,164.274],[310.034,163.358],[320.802,163.933],[326.514,148.551],[327.472,146.837],[330.887,145.866],[336.598,130.484],[330.85,124.755],[329.986,122.005],[330.557,111.243],[315.175,105.532]]}}},{"ty":"fl","hd":false,"bm":0,"c":{"a":0,"k":[0.643,0.631,1]},"r":1,"o":{"a":0,"k":42}},{"ty":"tr","nm":"Transform","a":{"a":0,"k":[0,0]},"o":{"a":0,"k":100},"p":{"a":0,"k":[0,0]},"r":{"a":0,"k":0},"s":{"a":0,"k":[100,100]},"sk":{"a":0,"k":0},"sa":{"a":0,"k":0}}],"np":0},{"ty":"tr","nm":"Transform","a":{"a":0,"k":[299.354,133.138]},"o":{"a":0,"k":100},"p":{"a":0,"k":[0,0]},"r":{"a":0,"k":0},"s":{"a":0,"k":[100,100]},"sk":{"a":0,"k":0},"sa":{"a":0,"k":0}}],"np":0}]},{"ddd":0,"ind":57,"ty":4,"nm":"bar2","hd":false,"sr":1,"ks":{"a":{"a":0,"k":[0,0]},"o":{"a":1,"k":[{"t":0,"s":[30],"i":{"x":0.5,"y":1},"o":{"x":0.12,"y":0.23}},{"t":15.9,"s":[100],"i":{"x":0,"y":0},"o":{"x":1,"y":1}}]},"p":{"a":1,"k":[{"t":0,"s":[87.976,222.83],"i":{"x":0.5,"y":1},"o":{"x":0.12,"y":0.23},"ti":[0,0],"to":[0,0]},{"t":15.9,"s":[104.663,211.615],"i":{"x":0,"y":0},"o":{"x":1,"y":1}}]},"r":{"a":0,"k":0},"s":{"a":0,"k":[100,100]},"sk":{"a":0,"k":0},"sa":{"a":0,"k":0}},"ao":0,"ip":0,"op":121,"st":0,"bm":0,"shapes":[{"ty":"gr","hd":false,"nm":"Layer 30 Group","bm":0,"it":[{"ty":"gr","hd":false,"nm":"Path 1 Group","bm":0,"it":[{"ty":"sh","hd":false,"nm":"Path 1","d":1,"ks":{"a":0,"k":{"c":true,"i":[[0,0],[0,0],[0,-11.04],[0,0],[11.04,0],[0,0],[0,11.04],[0,0],[-11.04,0]],"o":[[0,0],[11.04,0],[0,0],[0,11.04],[0,0],[-11.04,0],[0,0],[0,-11.04],[0,0]],"v":[[177.692,177.882],[256.902,177.882],[276.892,197.872],[276.892,197.872],[256.902,217.862],[177.692,217.862],[157.702,197.872],[157.702,197.872],[177.692,177.882]]}}},{"ty":"gs","hd":false,"bm":0,"o":{"a":0,"k":100},"e":{"a":0,"k":[200.8973279481403,188.34734147744402]},"g":{"p":2,"k":{"a":0,"k":[0,1,1,1,1,1,1,1,0,1,1,0.12]}},"t":1,"a":{"a":0,"k":0},"h":{"a":0,"k":0},"s":{"a":0,"k":[153.93499708017174,179.23800686232664]},"lc":1,"lj":1,"ml":4,"w":{"a":0,"k":1.332}},{"ty":"tr","nm":"Transform","a":{"a":0,"k":[157.702,177.882]},"o":{"a":0,"k":100},"p":{"a":0,"k":[157.702,177.882]},"r":{"a":0,"k":129},"s":{"a":0,"k":[100,100]},"sk":{"a":0,"k":0},"sa":{"a":0,"k":0}}],"np":0},{"ty":"tr","nm":"Transform","a":{"a":0,"k":[104.663,211.616]},"o":{"a":0,"k":100},"p":{"a":0,"k":[-0.001,0.001]},"r":{"a":0,"k":0},"s":{"a":0,"k":[100,100]},"sk":{"a":0,"k":0},"sa":{"a":0,"k":0}}],"np":0},{"ty":"gr","hd":false,"nm":"Layer 31 Group","bm":0,"it":[{"ty":"gr","hd":false,"nm":"Path 1 Group","bm":0,"it":[{"ty":"sh","hd":false,"nm":"Path 1","d":1,"ks":{"a":0,"k":{"c":true,"i":[[0,0],[0,0],[0,-11.408],[0,0],[11.408,0],[0,0],[0,11.408],[0,0],[-11.408,0]],"o":[[0,0],[11.408,0],[0,0],[0,11.408],[0,0],[-11.408,0],[0,0],[0,-11.408],[0,0]],"v":[[179.295,177.783],[258.504,177.783],[279.16,198.439],[279.16,198.439],[258.504,219.095],[179.295,219.095],[158.639,198.439],[158.639,198.439],[179.295,177.783]]}}},{"ty":"gf","hd":false,"bm":0,"e":{"a":1,"k":[{"t":0,"s":[279.2433341828642,198.52232893687037],"i":{"x":0,"y":0},"o":{"x":1,"y":1}},{"t":31.2,"s":[279.2433341828642,198.52232893687037],"i":{"x":0,"y":0},"o":{"x":1,"y":1}}]},"g":{"p":2,"k":{"a":1,"k":[{"t":0,"s":[0,0.475,0.376,1,1,1,1,1,0,1,1,1],"i":{"x":0.75,"y":0.75},"o":{"x":0.25,"y":0.25}},{"t":31.2,"s":[0,0.184,0.039,1,1,1,1,1,0,1,1,1],"i":{"x":0,"y":0},"o":{"x":1,"y":1}}]}},"t":1,"a":{"a":0,"k":0},"h":{"a":0,"k":0},"o":{"a":0,"k":20},"r":1,"s":{"a":1,"k":[{"t":0,"s":[158.63900898776984,198.43899559940522],"i":{"x":0,"y":0},"o":{"x":1,"y":1}},{"t":31.2,"s":[158.63900898776984,198.43899559940522],"i":{"x":0,"y":0},"o":{"x":1,"y":1}}]}},{"ty":"tr","nm":"Transform","a":{"a":0,"k":[158.639,177.783]},"o":{"a":0,"k":100},"p":{"a":0,"k":[158.639,177.783]},"r":{"a":0,"k":129},"s":{"a":0,"k":[100,100]},"sk":{"a":0,"k":0},"sa":{"a":0,"k":0}}],"np":0},{"ty":"tr","nm":"Transform","a":{"a":0,"k":[104.663,211.615]},"o":{"a":0,"k":100},"p":{"a":0,"k":[0,0]},"r":{"a":0,"k":0},"s":{"a":0,"k":[100,100]},"sk":{"a":0,"k":0},"sa":{"a":0,"k":0}}],"np":0}]},{"ddd":0,"ind":62,"ty":4,"nm":"bar1","hd":false,"sr":1,"ks":{"a":{"a":0,"k":[0,0]},"o":{"a":1,"k":[{"t":0,"s":[0],"i":{"x":0.75,"y":0.75},"o":{"x":0.25,"y":0.25}},{"t":5.1,"s":[0],"i":{"x":0.5,"y":1},"o":{"x":0.12,"y":0.23}},{"t":29.1,"s":[75],"i":{"x":0,"y":0},"o":{"x":1,"y":1}}]},"p":{"a":1,"k":[{"t":0,"s":[-2.662,300.473],"i":{"x":0.5,"y":1},"o":{"x":0.12,"y":0.23},"ti":[0,0],"to":[0,0]},{"t":29.1,"s":[49.3,247.455],"i":{"x":0,"y":0},"o":{"x":1,"y":1}}]},"r":{"a":0,"k":0},"s":{"a":0,"k":[100,100]},"sk":{"a":0,"k":0},"sa":{"a":0,"k":0}},"ao":0,"ip":0,"op":121,"st":0,"bm":0,"shapes":[{"ty":"gr","hd":false,"nm":"Layer 32 Group","bm":0,"it":[{"ty":"gr","hd":false,"nm":"Path 1 Group","bm":0,"it":[{"ty":"sh","hd":false,"nm":"Path 1","d":1,"ks":{"a":0,"k":{"c":true,"i":[[0,0],[0,0],[0,-9.682],[0,0],[9.683,0],[0,0],[0,9.682],[0,0],[-9.683,0]],"o":[[0,0],[9.683,0],[0,0],[0,9.682],[0,0],[-9.683,0],[0,0],[0,-9.682],[0,0]],"v":[[113.349,217.87],[182.817,217.87],[200.349,235.401],[200.349,235.401],[182.817,252.933],[113.349,252.933],[95.817,235.401],[95.817,235.401],[113.349,217.87]]}}},{"ty":"gs","hd":false,"bm":0,"o":{"a":0,"k":100},"e":{"a":0,"k":[133.71033056182884,227.05833948393797]},"g":{"p":2,"k":{"a":0,"k":[0,1,1,1,1,1,1,1,0,1,1,0.12]}},"t":1,"a":{"a":0,"k":0},"h":{"a":0,"k":0},"s":{"a":0,"k":[92.51299989133324,219.05900606962715]},"lc":1,"lj":1,"ml":4,"w":{"a":0,"k":1.168}},{"ty":"tr","nm":"Transform","a":{"a":0,"k":[95.817,217.87]},"o":{"a":0,"k":100},"p":{"a":0,"k":[95.817,217.87]},"r":{"a":0,"k":129},"s":{"a":0,"k":[100,100]},"sk":{"a":0,"k":0},"sa":{"a":0,"k":0}}],"np":0},{"ty":"tr","nm":"Transform","a":{"a":0,"k":[49.3,247.455]},"o":{"a":0,"k":100},"p":{"a":0,"k":[0,0.001]},"r":{"a":0,"k":0},"s":{"a":0,"k":[100,100]},"sk":{"a":0,"k":0},"sa":{"a":0,"k":0}}],"np":0},{"ty":"gr","hd":false,"nm":"Layer 33 Group","bm":0,"it":[{"ty":"gr","hd":false,"nm":"Path 1 Group","bm":0,"it":[{"ty":"sh","hd":false,"nm":"Path 1","d":1,"ks":{"a":0,"k":{"c":true,"i":[[0,0],[0,0],[0,-10.005],[0,0],[10.005,0],[0,0],[0,10.005],[0,0],[-10.005,0]],"o":[[0,0],[10.005,0],[0,0],[0,10.005],[0,0],[-10.005,0],[0,0],[0,-10.005],[0,0]],"v":[[114.754,217.783],[184.222,217.783],[202.338,235.898],[202.338,235.898],[184.222,254.014],[114.754,254.014],[96.638,235.898],[96.638,235.898],[114.754,217.783]]}}},{"ty":"gf","hd":false,"bm":0,"e":{"a":0,"k":[202.42133706372954,235.98233658775376]},"g":{"p":2,"k":{"a":0,"k":[0,0.475,0.376,1,1,1,1,1,0,1,1,1]}},"t":1,"a":{"a":0,"k":0},"h":{"a":0,"k":0},"o":{"a":0,"k":20},"r":1,"s":{"a":0,"k":[96.63800171186502,235.89900325304652]}},{"ty":"tr","nm":"Transform","a":{"a":0,"k":[96.638,217.783]},"o":{"a":0,"k":100},"p":{"a":0,"k":[96.638,217.783]},"r":{"a":0,"k":129},"s":{"a":0,"k":[100,100]},"sk":{"a":0,"k":0},"sa":{"a":0,"k":0}}],"np":0},{"ty":"tr","nm":"Transform","a":{"a":0,"k":[49.3,247.455]},"o":{"a":0,"k":100},"p":{"a":0,"k":[0,0]},"r":{"a":0,"k":0},"s":{"a":0,"k":[100,100]},"sk":{"a":0,"k":0},"sa":{"a":0,"k":0}}],"np":0}]},{"ddd":0,"ind":67,"ty":4,"nm":"background","hd":false,"sr":1,"ks":{"a":{"a":0,"k":[245.5,98]},"o":{"a":0,"k":100},"p":{"a":0,"k":[245.5,98]},"r":{"a":0,"k":0},"s":{"a":0,"k":[100,100]},"sk":{"a":0,"k":0},"sa":{"a":0,"k":0}},"ao":0,"ip":0,"op":121,"st":0,"bm":0,"shapes":[{"ty":"gr","hd":false,"nm":"Path 1 Group","bm":0,"it":[{"ty":"sh","hd":false,"nm":"Path 1","d":1,"ks":{"a":0,"k":{"c":true,"i":[[0,0],[0,0],[0,0],[0,0]],"o":[[0,0],[0,0],[0,0],[0,0]],"v":[[0,0],[375,0],[375,315],[0,315]]}}},{"ty":"gf","hd":false,"bm":0,"e":{"a":1,"k":[{"t":0,"s":[187.58334451030575,315.0833132138756],"i":{"x":0,"y":0},"o":{"x":1,"y":1}},{"t":51.9,"s":[187.58334451030575,315.0833132138756],"i":{"x":0,"y":0},"o":{"x":1,"y":1}}]},"g":{"p":2,"k":{"a":1,"k":[{"t":0,"s":[0,1,1,1,1,0.329,0.318,1,0,0.52,1,1],"i":{"x":0.75,"y":0.75},"o":{"x":0.25,"y":0.25}},{"t":51.9,"s":[0,1,1,1,1,0.329,0.318,1,0,0.52,1,1],"i":{"x":0,"y":0},"o":{"x":1,"y":1}}]}},"t":1,"a":{"a":0,"k":0},"h":{"a":0,"k":0},"o":{"a":0,"k":100},"r":1,"s":{"a":1,"k":[{"t":0,"s":[187.50001117882678,-2.086162520509305e-9],"i":{"x":0,"y":0},"o":{"x":1,"y":1}},{"t":51.9,"s":[187.50001117882678,-2.086162520509305e-9],"i":{"x":0,"y":0},"o":{"x":1,"y":1}}]}},{"ty":"tr","nm":"Transform","a":{"a":0,"k":[0,0]},"o":{"a":0,"k":100},"p":{"a":0,"k":[0,0]},"r":{"a":0,"k":0},"s":{"a":0,"k":[100,100]},"sk":{"a":0,"k":0},"sa":{"a":0,"k":0}}],"np":0},{"ty":"gr","hd":false,"nm":"Path 1 Group","bm":0,"it":[{"ty":"sh","hd":false,"nm":"Path 1","d":1,"ks":{"a":0,"k":{"c":true,"i":[[0,0],[83.671,0],[0,83.671],[-83.671,0],[0,-83.671]],"o":[[0,83.671],[-83.671,0],[0,-83.671],[83.671,0],[0,0]],"v":[[491,37.5],[339.5,189],[188,37.5],[339.5,-114],[491,37.5]]}}},{"ty":"gf","hd":false,"bm":0,"e":{"a":0,"k":[339.5,180.33557625758897]},"g":{"p":2,"k":{"a":0,"k":[0,1,1,1,1,1,1,1,0,1,1,0]}},"t":2,"a":{"a":0,"k":0},"h":{"a":0,"k":0},"o":{"a":0,"k":100},"r":1,"s":{"a":0,"k":[339.5,37.5]}},{"ty":"tr","nm":"Transform","a":{"a":0,"k":[0,0]},"o":{"a":0,"k":100},"p":{"a":0,"k":[0,0]},"r":{"a":0,"k":0},"s":{"a":0,"k":[100,100]},"sk":{"a":0,"k":0},"sa":{"a":0,"k":0}}],"np":0},{"ty":"gr","hd":false,"nm":"Path 1 Group","bm":0,"it":[{"ty":"sh","hd":false,"nm":"Path 1","d":1,"ks":{"a":0,"k":{"c":true,"i":[[0,0],[83.671,0],[0,83.671],[-83.671,0],[0,-83.671]],"o":[[0,83.671],[-83.671,0],[0,-83.671],[83.671,0],[0,0]],"v":[[468,32.5],[316.5,184],[165,32.5],[316.5,-119],[468,32.5]]}}},{"ty":"gf","hd":false,"bm":0,"e":{"a":0,"k":[316.5,175.33557625758897]},"g":{"p":2,"k":{"a":0,"k":[0,1,1,1,1,1,1,1,0,1,1,0]}},"t":2,"a":{"a":0,"k":0},"h":{"a":0,"k":0},"o":{"a":0,"k":100},"r":1,"s":{"a":0,"k":[316.5,32.5]}},{"ty":"tr","nm":"Transform","a":{"a":0,"k":[0,0]},"o":{"a":0,"k":100},"p":{"a":0,"k":[0,0]},"r":{"a":0,"k":0},"s":{"a":0,"k":[100,100]},"sk":{"a":0,"k":0},"sa":{"a":0,"k":0}}],"np":0},{"ty":"gr","hd":false,"nm":"Path 1 Group","bm":0,"it":[{"ty":"sh","hd":false,"nm":"Path 1","d":1,"ks":{"a":0,"k":{"c":true,"i":[[0,0],[0,0],[0,0],[0,0]],"o":[[0,0],[0,0],[0,0],[0,0]],"v":[[0,0],[375,0],[375,280],[0,280]]}}},{"ty":"fl","hd":false,"bm":0,"c":{"a":0,"k":[0.973,0.976,0.988]},"r":1,"o":{"a":0,"k":100}},{"ty":"tr","nm":"Transform","a":{"a":0,"k":[0,0]},"o":{"a":0,"k":100},"p":{"a":0,"k":[0,0]},"r":{"a":0,"k":0},"s":{"a":0,"k":[100,100]},"sk":{"a":0,"k":0},"sa":{"a":0,"k":0}}],"np":0}]},{"ddd":0,"ind":72,"ty":4,"nm":"Screen","hd":false,"sr":1,"ks":{"a":{"a":0,"k":[187.5,140]},"o":{"a":0,"k":100},"p":{"a":0,"k":[250,250]},"r":{"a":0,"k":0},"s":{"a":0,"k":[100,100]},"sk":{"a":0,"k":0},"sa":{"a":0,"k":0}},"ao":0,"ip":0,"op":121,"st":0,"bm":0,"shapes":[{"ty":"gr","hd":false,"nm":"Screen Group","bm":0,"it":[{"ty":"rc","hd":false,"nm":"Screen","d":1,"p":{"a":0,"k":[187.5,140]},"r":{"a":0,"k":0},"s":{"a":0,"k":[375,280]}},{"ty":"fl","hd":false,"bm":0,"c":{"a":0,"k":[1,1,1]},"r":1,"o":{"a":0,"k":100}},{"ty":"tr","nm":"Transform","a":{"a":0,"k":[0,0]},"o":{"a":0,"k":100},"p":{"a":0,"k":[0,0]},"r":{"a":0,"k":0},"s":{"a":0,"k":[100,100]},"sk":{"a":0,"k":0},"sa":{"a":0,"k":0}}],"np":0}]}],"meta":{"g":"@phase-software/lottie-exporter 0.7.0"},"nm":"","op":120,"v":"5.6.0","w":375}